Workbook

Sheet Cover
B10: Financial Model (36 months)
B12: Three scenarios (Conservative, Base, High-growth) driven from one assumptions sheet. Change the scenario selector on the Assumptions sheet. Nothing here is an actual; all figures are scenario outputs.
B16: Prepared for | C16: The Founder, Vytalix
B17: Date | C17: 8 September 2026
B18: Version | C18: 1.0 · Confidential draft
B20: Contents
B21: README
B22: Assumptions
B23: Revenue build
B24: Cost of sales
B25: Opex
B26: Headcount
B27: P&L
B28: Cash flow
B29: Funding requirement
B30: Dashboard
B31: Sensitivity
... B35: Colour code: yellow cells are inputs you can change; blue headers are fixed; every figure is an ESTIMATE unless labelled VERIFIED (see FACTS_BASE).

Sheet README
A1: VYTALIX — 36-month financial model (Jan 2027 – Dec 2029)
A3: Status: SCENARIO MODEL v1.1, built 7 September 2026 and revised 8 September 2026 by finance/build_model.py. GBP. UK-domiciled entity (to be incorporated — TO VALIDATE).
A4: No figure in this workbook is an actual. Vytalix has no revenue, customers, contracts, grants or product in production (FACTS_BASE.md). Every number is a scenario built from the stated assumptions.
A6: HOW TO USE
A7: 1. Assumptions!C4 selects the scenario (1 Conservative, 2 Base, 3 High-growth). Column F ('ACTIVE') = INDEX(C:E, selector) and every formula sheet reads column F.
A8: 2. Blue/yellow cells in Assumptions are inputs. Year-dependent inputs (Y1/Y2/Y3) are read with CHOOSE(year index, Y1, Y2, Y3).
A9: 3. Timeline sheets run left to right: Revenue build → Cost of sales → Headcount → Opex → P&L → Cash flow → Funding requirement → Dashboard. Months are in columns C:AL; annual totals in AN:AQ.
A10: 4. Sensitivity and Static summary are values computed in Python with identical logic; they do not react to C4. Re-run the script after editing assumptions.
A11: 5. Assumptions!ml_delay adds months to the MaternaLink licence go-live for slippage tests.
A13: SHEETS
A14: Assumptions — three scenario columns, selector, derived payroll on-costs. | Revenue build — advisory days × rate × utilisation, retainers, consulting projects × value, e-learning learners × ARPU + corporate licences, MaternaLink pilots × value then per-woman licences from go-live.
A15: Cost of sales — direct costs and gross margin. | Opex — founder salary, hires by start month, contractors, technology, marketing, legal, compliance, insurance, software, travel, operations, accountancy; employer NI 15% above £5,000 and pension 3% of qualifying earnings (2026/27 — see notes in Assumptions).
... A37: EIS from 6 April 2026: £10m per 12 months (£20m knowledge-intensive), £24m lifetime (£40m KIC), gross assets £30m/£35m, investor £1m (£2m KIC): https://www.farrer.co.uk/news-and-insights/using-eis-and-seis-to-attract-investment-the-benefits-and-some-traps-to-avoid/ ; https://ct.me/content-hub/articles/eis-changes-from-april-2026-higher-investment-limits-for-innovative-companies/

Sheet Assumptions
A1: VYTALIX — Assumptions (all values are scenario inputs; none are actuals)
A2: Labels: KNOWN (cited) · ESTIMATE · ASSUMPTION · PROPOSED · TO VALIDATE. Blue cells are inputs. Column F = active scenario via INDEX.
A4: SCENARIO SELECTOR (1 = Conservative, 2 = Base, 3 = High-growth) | C4: 2 | D4: =INDEX({"Conservative","Base","High-growth"},1,$C$4)
A5: Change C4 and the whole workbook (Revenue → Cash flow → Dashboard) re-points. Sensitivity and Static summary are Python-computed values and do not change.
A7: Key | B7: Assumption | C7: Conservative | D7: Base | E7: High-growth | F7: ACTIVE | G7: Unit | H7: Label | I7: Note / source
A8: General
A9: opening_cash | B9: Opening cash (founder capital + director's loan, month 1) | C9: 25000 | D9: 35000 | E9: 50000 | F9: =INDEX($C9:$E9,1,$C$4) | G9: GBP | H9: ASSUMPTION | I9: Founder's own contribution incl. a director's loan that bridges month-1 set-up costs until the pre-seed lands; TO VALIDATE with founder. (Revised 8 Sept 2026 from £10k/£20k/£30k, which left cash negative in months 2–5 of every scenario.)
A10: collection_lag | B10: Collection lag — services & MaternaLink invoices | C10: 1 | D10: 1 | E10: 1 | F10: =INDEX($C10:$E10,1,$C$4) | G10: months | H10: ASSUMPTION | I10: E-learning collected same month (prepaid).
A11: avail_days | B11: Founder available working days per month | C11: 17.33 | D11: 17.33 | E11: 17.33 | F11: =INDEX($C11:$E11,1,$C$4) | G11: days | H11: ASSUMPTION | I11: 208 days/year ÷ 12 (4 days/week on Vytalix, per 01_BUSINESS_MODEL).
A12: ramp_months | B12: Sales ramp-up (months to full run-rate) | C12: 4 | D12: 3 | E12: 2 | F12: =INDEX($C12:$E12,1,$C$4) | G12: months | H12: ASSUMPTION | I12: Ramp factor = MIN(1,(month-1)/ramp). Month 1 = 0 revenue (incorporation, outreach).
A13: Advisory (founder-led days and retainers)
A14: day_rate | B14: Founder day rate | C14: 1200 | D14: 1500 | E14: 1800 | F14: =INDEX($C14:$E14,1,$C$4) | G14: GBP/day | H14: ESTIMATE | I14: Range £1,200–£1,800 per 01_BUSINESS_MODEL §4.1.
A15: utilisation | B15: Founder billable utilisation (all client work) | C15: 0.3 | D15: 0.42 | E15: 0.55 | F15: =INDEX($C15:$E15,1,$C$4) | G15: % | H15: ESTIMATE | I15: Share of available days billed (advisory days + retainers + consulting delivery).
A16: ret_start | B16: Retainers — first retainer month | C16: 3 | D16: 2 | E16: 2 | F16: =INDEX($C16:$E16,1,$C$4) | G16: month | H16: ASSUMPTION
A17: ret_y1 | B17: Retainers active — Y1 (average) | C17: 0.5 | D17: 1 | E17: 2 | F17: =INDEX($C17:$E17,1,$C$4) | G17: count | H17: ESTIMATE | I17: Fractional = part-year.
A18: ret_y2 | B18: Retainers active — Y2 (average) | C18: 1 | D18: 2 | E18: 3 | F18: =INDEX($C18:$E18,1,$C$4) | G18: count | H18: ESTIMATE
A19: ret_y3 | B19: Retainers active — Y3 (average) | C19: 1 | D19: 2 | E19: 3 | F19: =INDEX($C19:$E19,1,$C$4) | G19: count | H19: ESTIMATE
A20: ret_fee | B20: Retainer fee per month | C20: 3500 | D20: 4000 | E20: 5000 | F20: =INDEX($C20:$E20,1,$C$4) | G20: GBP/month | H20: ESTIMATE | I20: £2,500–£6,000 per 01_BUSINESS_MODEL #2.
A21: ret_days | B21: Founder days consumed per retainer per month | C21: 2.5 | D21: 2.5 | E21: 2.5 | F21: =INDEX($C21:$E21,1,$C$4) | G21: days | H21: ASSUMPTION
A22: adv_cost_day | B22: Direct cost per founder billable day (travel, tools) | C22: 50 | D22: 50 | E22: 50 | F22: =INDEX($C22:$E22,1,$C$4) | G22: GBP/day | H22: ESTIMATE
A23: cons_days | B23: Senior consultant billable days per month (once hired) | C23: 0 | D23: 10 | E23: 10 | F23: =INDEX($C23:$E23,1,$C$4) | G23: days | H23: ASSUMPTION | I23: Hire start month in Headcount block; 0 if never hired.
A24: cons_rate | B24: Senior consultant billed day rate | C24: 900 | D24: 900 | E24: 1000 | F24: =INDEX($C24:$E24,1,$C$4) | G24: GBP/day | H24: ESTIMATE | I24: Associate-level rate £700–£1,000 per 01_BUSINESS_MODEL.
A25: Consulting (packaged projects)
A26: proj_y1 | B26: Projects won — Y1 | C26: 2 | D26: 5 | E26: 8 | F26: =INDEX($C26:$E26,1,$C$4) | G26: count | H26: ESTIMATE | I26: Spread evenly across the year after ramp.
A27: proj_y2 | B27: Projects won — Y2 | C27: 4 | D27: 8 | E27: 14 | F27: =INDEX($C27:$E27,1,$C$4) | G27: count | H27: ESTIMATE
A28: proj_y3 | B28: Projects won — Y3 | C28: 5 | D28: 10 | E28: 18 | F28: =INDEX($C28:$E28,1,$C$4) | G28: count | H28: ESTIMATE
A29: proj_value | B29: Average project value | C29: 15000 | D29: 20000 | E29: 30000 | F29: =INDEX($C29:$E29,1,$C$4) | G29: GBP | H29: ESTIMATE | I29: Range £15k–£60k; catalogue prices £9.5k–£28k in 01_BUSINESS_MODEL §5.
A30: fdays_proj | B30: Founder days per project | C30: 8 | D30: 7 | E30: 5 | F30: =INDEX($C30:$E30,1,$C$4) | G30: days | H30: ASSUMPTION | I30: Lower in High-growth because associates deliver more (see delivery cost %).
A31: proj_cost_pct | B31: Consulting delivery cost (associates, expenses) % of value | C31: 0.3 | D31: 0.35 | E31: 0.45 | F31: =INDEX($C31:$E31,1,$C$4) | G31: % | H31: ESTIMATE | I31: Cost of sales. Rises with associate share.
A32: E-learning
A33: el_launch | B33: E-learning launch month | C33: 12 | D33: 9 | E33: 7 | F33: =INDEX($C33:$E33,1,$C$4) | G33: month | H33: ASSUMPTION | I33: Two founder-authored courses first (01_BUSINESS_MODEL §6).
A34: el_init | B34: New learners per month at launch | C34: 8 | D34: 15 | E34: 30 | F34: =INDEX($C34:$E34,1,$C$4) | G34: learners | H34: ESTIMATE
A35: el_growth | B35: Monthly growth in new learners | C35: 0.03 | D35: 0.05 | E35: 0.07 | F35: =INDEX($C35:$E35,1,$C$4) | G35: % | H35: ESTIMATE | I35: Compound, from launch.
A36: el_arpu | B36: Average revenue per learner (ARPU) | C36: 150 | D36: 200 | E36: 300 | F36: =INDEX($C36:$E36,1,$C$4) | G36: GBP | H36: ESTIMATE | I36: Range £150–£400; course prices £49–£299 UK, regional pricing lower.
A37: corp_y1 | B37: Corporate licences active — Y1 | C37: 0 | D37: 0 | E37: 1 | F37: =INDEX($C37:$E37,1,$C$4) | G37: count | H37: ESTIMATE
A38: corp_y2 | B38: Corporate licences active — Y2 | C38: 1 | D38: 3 | E38: 6 | F38: =INDEX($C38:$E38,1,$C$4) | G38: count | H38: ESTIMATE
A39: corp_y3 | B39: Corporate licences active — Y3 | C39: 2 | D39: 6 | E39: 12 | F39: =INDEX($C39:$E39,1,$C$4) | G39: count | H39: ESTIMATE
A40: corp_value | B40: Corporate licence value per year | C40: 2500 | D40: 5000 | E40: 9000 | F40: =INDEX($C40:$E40,1,$C$4) | G40: GBP/year | H40: ESTIMATE | I40: £2,500 (10 seats) – £25,000 (250 seats) ladder.
A41: el_cos_pct | B41: E-learning platform + payment fees % of revenue | C41: 0.15 | D41: 0.15 | E41: 0.15 | F41: =INDEX($C41:$E41,1,$C$4) | G41: % | H41: ESTIMATE
A42: el_content | B42: E-learning content build (one-off, launch month) | C42: 8000 | D42: 12000 | E42: 20000 | F42: =INDEX($C42:$E42,1,$C$4) | G42: GBP | H42: ESTIMATE | I42: £8k–£15k per course; two courses at launch (High builds more).
A43: MaternaLink (in development) — pilots then licences
A44: ml_pilot_start | B44: First paid pilot month | C44: 18 | D44: 13 | E44: 10 | F44: =INDEX($C44:$E44,1,$C$4) | G44: month | H44: TO VALIDATE | I44: Gated by IP ownership, safety case, DPIA, a partner site (01_BUSINESS_MODEL §7).
A45: ml_pil_y1 | B45: Active paid pilots — Y1 | C45: 0 | D45: 0 | E45: 1 | F45: =INDEX($C45:$E45,1,$C$4) | G45: count | H45: ESTIMATE
A46: ml_pil_y2 | B46: Active paid pilots — Y2 | C46: 1 | D46: 1 | E46: 2 | F46: =INDEX($C46:$E46,1,$C$4) | G46: count | H46: ESTIMATE
A47: ml_pil_y3 | B47: Active paid pilots — Y3 | C47: 1 | D47: 2 | E47: 4 | F47: =INDEX($C47:$E47,1,$C$4) | G47: count | H47: ESTIMATE
A48: ml_pilot_value | B48: Pilot value per pilot per year | C48: 40000 | D48: 75000 | E48: 150000 | F48: =INDEX($C48:$E48,1,$C$4) | G48: GBP/year | H48: ESTIMATE | I48: Range £40k–£150k. Recognised evenly over the months the pilot is active.
A49: ml_pilot_cost_pct | B49: Pilot delivery cost % of pilot value | C49: 0.5 | D49: 0.45 | E49: 0.4 | F49: =INDEX($C49:$E49,1,$C$4) | G49: % | H49: ESTIMATE | I49: Implementation, training, support; first pilots are near loss-leaders.
A50: ml_golive | B50: Per-woman licence go-live month | C50: 27 | D50: 19 | E50: 15 | F50: =INDEX($C50:$E50,1,$C$4) | G50: month | H50: TO VALIDATE | I50: Conservative: small and from month 18+ (here 27).
A51: ml_delay | B51: Go-live delay (sensitivity input, months) | C51: 0 | D51: 0 | E51: 0 | F51: =INDEX($C51:$E51,1,$C$4) | G51: months | H51: INPUT | I51: Add months here to test regulatory/partner slippage.
A52: uk_init | B52: UK women enrolled at go-live | C52: 200 | D52: 500 | E52: 1500 | F52: =INDEX($C52:$E52,1,$C$4) | G52: women | H52: ESTIMATE
A53: uk_add | B53: UK women added per month after go-live | C53: 50 | D53: 100 | E53: 300 | F53: =INDEX($C53:$E53,1,$C$4) | G53: women/month | H53: ESTIMATE
A54: uk_price | B54: UK licence per woman per year | C54: 8 | D54: 20 | E54: 40 | F54: =INDEX($C54:$E54,1,$C$4) | G54: GBP | H54: ESTIMATE | I54: Range £8–£40. Equivalent to £40k–£120k per trust site licence at 3,000–5,000 births.
A55: uk_cost | B55: UK hosting/support cost per woman per year | C55: 4 | D55: 4 | E55: 4 | F55: =INDEX($C55:$E55,1,$C$4) | G55: GBP | H55: ESTIMATE
A56: af_init | B56: Africa women enrolled at go-live | C56: 1000 | D56: 5000 | E56: 15000 | F56: =INDEX($C56:$E56,1,$C$4) | G56: women | H56: ESTIMATE | I56: Donor- or state-funded programme cohorts (LGA-level pilots, not full state).
A57: af_add | B57: Africa women added per month after go-live | C57: 250 | D57: 1000 | E57: 3000 | F57: =INDEX($C57:$E57,1,$C$4) | G57: women/month | H57: ESTIMATE
A58: af_price | B58: Africa licence per woman per year | C58: 3 | D58: 6 | E58: 12 | F58: =INDEX($C58:$E58,1,$C$4) | G58: GBP | H58: ESTIMATE | I58: Range £3–£12 at scale. The Ekiti proposal's £300/woman/year is UNVALIDATED and far above comparables (FACTS_BASE A5); NOT used.
A59: af_cost | B59: Africa hosting/SMS/support cost per woman per year | C59: 2 | D59: 2.5 | E59: 3 | F59: =INDEX($C59:$E59,1,$C$4) | G59: GBP | H59: ESTIMATE | I59: SMS pass-through excluded (billed at cost).
A60: Payroll rates (UK 2026/27)
A61: ni_rate | B61: Employer NI rate (Class 1 secondary) | C61: 0.15 | D61: 0.15 | E61: 0.15 | F61: =INDEX($C61:$E61,1,$C$4) | G61: % | H61: KNOWN | I61: 15% for 2026/27. Source: https://www.moorepay.co.uk/payroll-hr-rates/tax-and-national-insurance-changes/ ; TO VALIDATE against gov.uk rates page before use.
A62: ni_threshold | B62: Employer NI secondary threshold (annual) | C62: 5000 | D62: 5000 | E62: 5000 | F62: =INDEX($C62:$E62,1,$C$4) | G62: GBP | H62: KNOWN | I62: £5,000 for 2026/27 (same source).
A63: emp_allowance | B63: Employment Allowance (annual; applied once headcount ≥ 2) | C63: 10500 | D63: 10500 | E63: 10500 | F63: =INDEX($C63:$E63,1,$C$4) | G63: GBP | H63: KNOWN | I63: £10,500; a company whose only employee paid above the threshold is a sole director cannot claim — hence applied only from 2+ employees. TO VALIDATE eligibility.
A64: pen_rate | B64: Employer auto-enrolment pension minimum | C64: 0.03 | D64: 0.03 | E64: 0.03 | F64: =INDEX($C64:$E64,1,$C$4) | G64: % | H64: KNOWN | I64: 3% of qualifying earnings. Source: https://www.moorepay.co.uk/payroll-hr-rates/automatic-enrolment/
A65: pen_lower | B65: Qualifying earnings lower limit (annual) | C65: 6240 | D65: 6240 | E65: 6240 | F65: =INDEX($C65:$E65,1,$C$4) | G65: GBP | H65: KNOWN | I65: 2026/27 band £6,240–£50,270 (same source).
A66: pen_upper | B66: Qualifying earnings upper limit (annual) | C66: 50270 | D66: 50270 | E66: 50270 | F66: =INDEX($C66:$E66,1,$C$4) | G66: GBP | H66: KNOWN
A67: Founder and hires (start month; 99 = not hired within model)
A68: founder_start | B68: Founder salary — start month | C68: 4 | D68: 3 | E68: 3 | F68: =INDEX($C68:$E68,1,$C$4) | G68: month | H68: ASSUMPTION | I68: Founder draws nothing until the first invoices (month 2) are collected (month 3, one-month lag). Conservative waits one more month. (Revised 8 Sept 2026 from 4/2/1.)
A69: founder_salary | B69: Founder salary (annual) | C69: 36000 | D69: 48000 | E69: 60000 | F69: =INDEX($C69:$E69,1,$C$4) | G69: GBP/year | H69: ASSUMPTION | I69: Below market; opportunity cost £120k (01_BUSINESS_MODEL §3).
A70: product_lead_start | B70: Product lead / CTO — start month | C70: 13 | D70: 7 | E70: 4 | F70: =INDEX($C70:$E70,1,$C$4) | G70: month | H70: ASSUMPTION
A71: product_lead_salary | B71: Product lead / CTO — annual salary | C71: 60000 | D71: 65000 | E71: 70000 | F71: =INDEX($C71:$E71,1,$C$4) | G71: GBP/year | H71: ESTIMATE
A72: dev1_start | B72: Developer 1 — start month | C72: 99 | D72: 10 | E72: 6 | F72: =INDEX($C72:$E72,1,$C$4) | G72: month | H72: ASSUMPTION | I72: Conservative: not hired — a £250k pre-seed cannot carry a second technical salary (cash went negative at month 31 when it was); contractors instead. (Revised 8 Sept 2026 from month 19.)
A73: dev1_salary | B73: Developer 1 — annual salary | C73: 50000 | D73: 55000 | E73: 60000 | F73: =INDEX($C73:$E73,1,$C$4) | G73: GBP/year | H73: ESTIMATE
A74: dev2_start | B74: Developer 2 — start month | C74: 99 | D74: 22 | E74: 12 | F74: =INDEX($C74:$E74,1,$C$4) | G74: month | H74: ASSUMPTION
A75: dev2_salary | B75: Developer 2 — annual salary | C75: 50000 | D75: 55000 | E75: 60000 | F75: =INDEX($C75:$E75,1,$C$4) | G75: GBP/year | H75: ESTIMATE
A76: dev3_start | B76: Developer 3 — start month | C76: 99 | D76: 99 | E76: 24 | F76: =INDEX($C76:$E76,1,$C$4) | G76: month | H76: ASSUMPTION
A77: dev3_salary | B77: Developer 3 — annual salary | C77: 55000 | D77: 55000 | E77: 60000 | F77: =INDEX($C77:$E77,1,$C$4) | G77: GBP/year | H77: ESTIMATE
A78: bd_lead_start | B78: BD / sales lead — start month | C78: 99 | D78: 16 | E78: 10 | F78: =INDEX($C78:$E78,1,$C$4) | G78: month | H78: ASSUMPTION
A79: bd_lead_salary | B79: BD / sales lead — annual salary | C79: 45000 | D79: 50000 | E79: 55000 | F79: =INDEX($C79:$E79,1,$C$4) | G79: GBP/year | H79: ESTIMATE
A80: prog_mgr_start | B80: Programme manager (Nigeria) — start month | C80: 99 | D80: 20 | E80: 14 | F80: =INDEX($C80:$E80,1,$C$4) | G80: month | H80: ASSUMPTION | I80: Nigeria-based role modelled with UK on-costs as a conservative simplification; local employment/contractor route TO VALIDATE.
A81: prog_mgr_salary | B81: Programme manager (Nigeria) — annual salary | C81: 25000 | D81: 30000 | E81: 30000 | F81: =INDEX($C81:$E81,1,$C$4) | G81: GBP/year | H81: ESTIMATE
A82: clinical_lead_start | B82: Clinical lead (midwife/obstetrician) — start month | C82: 99 | D82: 25 | E82: 16 | F82: =INDEX($C82:$E82,1,$C$4) | G82: month | H82: ASSUMPTION
A83: clinical_lead_salary | B83: Clinical lead (midwife/obstetrician) — annual salary | C83: 70000 | D83: 70000 | E83: 75000 | F83: =INDEX($C83:$E83,1,$C$4) | G83: GBP/year | H83: ESTIMATE
A84: content_lead_start | B84: E-learning content lead — start month | C84: 99 | D84: 99 | E84: 18 | F84: =INDEX($C84:$E84,1,$C$4) | G84: month | H84: ASSUMPTION
A85: content_lead_salary | B85: E-learning content lead — annual salary | C85: 40000 | D85: 40000 | E85: 45000 | F85: =INDEX($C85:$E85,1,$C$4) | G85: GBP/year | H85: ESTIMATE
A86: consultant_start | B86: Senior consultant (billable) — start month | C86: 99 | D86: 19 | E86: 10 | F86: =INDEX($C86:$E86,1,$C$4) | G86: month | H86: ASSUMPTION | I86: Adds billable capacity (see Advisory block).
A87: consultant_salary | B87: Senior consultant (billable) — annual salary | C87: 55000 | D87: 55000 | E87: 60000 | F87: =INDEX($C87:$E87,1,$C$4) | G87: GBP/year | H87: ESTIMATE
A88: Other operating costs (GBP per month, by year)
A89: contractors_y1 | B89: Contractors (dev, design, implementation, fractional clinical safety officer) — Y1 | C89: 1500 | D89: 2500 | E89: 3000 | F89: =INDEX($C89:$E89,1,$C$4) | G89: GBP/month | H89: ESTIMATE
A90: contractors_y2 | B90: Contractors (dev, design, implementation, fractional clinical safety officer) — Y2 | C90: 4000 | D90: 10000 | E90: 20000 | F90: =INDEX($C90:$E90,1,$C$4) | G90: GBP/month | H90: ESTIMATE
A91: contractors_y3 | B91: Contractors (dev, design, implementation, fractional clinical safety officer) — Y3 | C91: 8000 | D91: 30000 | E91: 45000 | F91: =INDEX($C91:$E91,1,$C$4) | G91: GBP/month | H91: ESTIMATE
A92: technology_y1 | B92: Technology (cloud, hosting, messaging, tooling) — Y1 | C92: 300 | D92: 800 | E92: 1500 | F92: =INDEX($C92:$E92,1,$C$4) | G92: GBP/month | H92: ESTIMATE
A93: technology_y2 | B93: Technology (cloud, hosting, messaging, tooling) — Y2 | C93: 600 | D93: 3000 | E93: 6000 | F93: =INDEX($C93:$E93,1,$C$4) | G93: GBP/month | H93: ESTIMATE
A94: technology_y3 | B94: Technology (cloud, hosting, messaging, tooling) — Y3 | C94: 1500 | D94: 10000 | E94: 20000 | F94: =INDEX($C94:$E94,1,$C$4) | G94: GBP/month | H94: ESTIMATE
A95: marketing_y1 | B95: Marketing (content, events, paid tests, demand generation) — Y1 | C95: 300 | D95: 600 | E95: 1000 | F95: =INDEX($C95:$E95,1,$C$4) | G95: GBP/month | H95: ESTIMATE
A96: marketing_y2 | B96: Marketing (content, events, paid tests, demand generation) — Y2 | C96: 750 | D96: 4000 | E96: 12000 | F96: =INDEX($C96:$E96,1,$C$4) | G96: GBP/month | H96: ESTIMATE
A97: marketing_y3 | B97: Marketing (content, events, paid tests, demand generation) — Y3 | C97: 2000 | D97: 15000 | E97: 35000 | F97: =INDEX($C97:$E97,1,$C$4) | G97: GBP/month | H97: ESTIMATE
A98: legal_y1 | B98: Legal (ongoing contracts, IP, employment) — Y1 | C98: 300 | D98: 400 | E98: 500 | F98: =INDEX($C98:$E98,1,$C$4) | G98: GBP/month | H98: ESTIMATE
A99: legal_y2 | B99: Legal (ongoing contracts, IP, employment) — Y2 | C99: 500 | D99: 800 | E99: 1000 | F99: =INDEX($C99:$E99,1,$C$4) | G99: GBP/month | H99: ESTIMATE
A100: legal_y3 | B100: Legal (ongoing contracts, IP, employment) — Y3 | C100: 1000 | D100: 1500 | E100: 2000 | F100: =INDEX($C100:$E100,1,$C$4) | G100: GBP/month | H100: ESTIMATE
... A118: accountancy_y3 | B118: Accountancy, payroll, company secretarial — Y3 | C118: 250 | D118: 400 | E118: 600 | F118: =INDEX($C118:$E118,1,$C$4) | G118: GBP/month | H118: ESTIMATE
A119: legal_setup | B119: Legal & IP set-up (one-off, month 1) | C119: 6000 | D119: 10000 | E119: 15000 | F119: =INDEX($C119:$E119,1,$C$4) | G119: GBP | H119: ESTIMATE | I119: Incorporation, shareholders' agreement, MaternaLink IP assignment/licence, SEIS/EIS advance assurance, trade mark filing.
...

Sheet Revenue build
A1: Revenue build — Advisory, Consulting, E-learning, MaternaLink (in development)
A2: ="Scenario: "&Assumptions!$D$4&" — all figures GBP, scenario values, not actuals"
A3: Month # | C3: 1 | D3: 2 | E3: 3 | F3: 4 | G3: 5 | H3: 6 | I3: 7 | J3: 8 | K3: 9 | L3: 10 | M3: 11 | N3: 12 | O3: 13 | P3: 14 | Q3: 15 | R3: 16 | S3: 17 | T3: 18 | U3: 19 | V3: 20 | W3: 21 | X3: 22 | Y3: 23 | Z3: 24 | AA3: 25 | AB3: 26 | AC3: 27 | AD3: 28 | AE3: 29 | AF3: 30 | AG3: 31 | AH3: 32 | AI3: 33 | AJ3: 34 | AK3: 35 | AL3: 36
A4: Month | C4: 46388 | D4: 46419 | E4: 46447 | F4: 46478 | G4: 46508 | H4: 46539 | I4: 46569 | J4: 46600 | K4: 46631 | L4: 46661 | M4: 46692 | N4: 46722 | O4: 46753 | P4: 46784 | Q4: 46813 | R4: 46844 | S4: 46874 | T4: 46905 | U4: 46935 | V4: 46966 | W4: 46997 | X4: 47027 | Y4: 47058 | Z4: 47088 | AA4: 47119 | AB4: 47150 | AC4: 47178 | AD4: 47209 | AE4: 47239 | AF4: 47270 | AG4: 47300 | AH4: 47331 | AI4: 47362 | AJ4: 47392 | AK4: 47423 | AL4: 47453 | AN4: FY2027 | AO4: FY2028 | AP4: FY2029 | AQ4: 3-year total
A5: Year | C5: 2027 | D5: 2027 | E5: 2027 | F5: 2027 | G5: 2027 | H5: 2027 | I5: 2027 | J5: 2027 | K5: 2027 | L5: 2027 | M5: 2027 | N5: 2027 | O5: 2028 | P5: 2028 | Q5: 2028 | R5: 2028 | S5: 2028 | T5: 2028 | U5: 2028 | V5: 2028 | W5: 2028 | X5: 2028 | Y5: 2028 | Z5: 2028 | AA5: 2029 | AB5: 2029 | AC5: 2029 | AD5: 2029 | AE5: 2029 | AF5: 2029 | AG5: 2029 | AH5: 2029 | AI5: 2029 | AJ5: 2029 | AK5: 2029 | AL5: 2029 | AN5: 2027 | AO5: 2028 | AP5: 2029
A6: Year index | C6: =C5-2026 | D6: =D5-2026 | E6: =E5-2026 | F6: =F5-2026 | G6: =G5-2026 | H6: =H5-2026 | I6: =I5-2026 | J6: =J5-2026 | ... AL6: =AL5-2026
A7: Sales ramp factor | C7: =MIN(1,MAX(0,(C3-1)/Assumptions!$F$12)) | D7: =MIN(1,MAX(0,(D3-1)/Assumptions!$F$12)) | E7: =MIN(1,MAX(0,(E3-1)/Assumptions!$F$12)) | F7: =MIN(1,MAX(0,(F3-1)/Assumptions!$F$12)) | G7: =MIN(1,MAX(0,(G3-1)/Assumptions!$F$12)) | H7: =MIN(1,MAX(0,(H3-1)/Assumptions!$F$12)) | I7: =MIN(1,MAX(0,(I3-1)/Assumptions!$F$12)) | J7: =MIN(1,MAX(0,(J3-1)/Assumptions!$F$12)) | ... AL7: =MIN(1,MAX(0,(AL3-1)/Assumptions!$F$12)) | AN7: =AVERAGEIF($C$5:$AL$5,AN$5,C7:AL7) | AO7: =AVERAGEIF($C$5:$AL$5,AO$5,C7:AL7) | AP7: =AVERAGEIF($C$5:$AL$5,AP$5,C7:AL7) | AQ7: =AVERAGE(C7:AL7)
A8: ADVISORY
A9: Founder available days | B9: days | C9: =Assumptions!$F$11 | D9: =Assumptions!$F$11 | E9: =Assumptions!$F$11 | F9: =Assumptions!$F$11 | G9: =Assumptions!$F$11 | H9: =Assumptions!$F$11 | I9: =Assumptions!$F$11 | J9: =Assumptions!$F$11 | ... AL9: =Assumptions!$F$11 | AN9: =SUMIF($C$5:$AL$5,AN$5,C9:AL9) | AO9: =SUMIF($C$5:$AL$5,AO$5,C9:AL9) | AP9: =SUMIF($C$5:$AL$5,AP$5,C9:AL9) | AQ9: =SUM(C9:AL9)
A10: Founder billable utilisation | C10: =Assumptions!$F$15 | D10: =Assumptions!$F$15 | E10: =Assumptions!$F$15 | F10: =Assumptions!$F$15 | G10: =Assumptions!$F$15 | H10: =Assumptions!$F$15 | I10: =Assumptions!$F$15 | J10: =Assumptions!$F$15 | ... AL10: =Assumptions!$F$15 | AN10: =AVERAGEIF($C$5:$AL$5,AN$5,C10:AL10) | AO10: =AVERAGEIF($C$5:$AL$5,AO$5,C10:AL10) | AP10: =AVERAGEIF($C$5:$AL$5,AP$5,C10:AL10) | AQ10: =AVERAGE(C10:AL10)
A11: Founder billable days (utilisation × ramp) | B11: days | C11: ='Revenue build'!C9*'Revenue build'!C10*'Revenue build'!C7 | D11: ='Revenue build'!D9*'Revenue build'!D10*'Revenue build'!D7 | E11: ='Revenue build'!E9*'Revenue build'!E10*'Revenue build'!E7 | F11: ='Revenue build'!F9*'Revenue build'!F10*'Revenue build'!F7 | G11: ='Revenue build'!G9*'Revenue build'!G10*'Revenue build'!G7 | H11: ='Revenue build'!H9*'Revenue build'!H10*'Revenue build'!H7 | I11: ='Revenue build'!I9*'Revenue build'!I10*'Revenue build'!I7 | J11: ='Revenue build'!J9*'Revenue build'!J10*'Revenue build'!J7 | ... AL11: ='Revenue build'!AL9*'Revenue build'!AL10*'Revenue build'!AL7 | AN11: =SUMIF($C$5:$AL$5,AN$5,C11:AL11) | AO11: =SUMIF($C$5:$AL$5,AO$5,C11:AL11) | AP11: =SUMIF($C$5:$AL$5,AP$5,C11:AL11) | AQ11: =SUM(C11:AL11)
A12: Retainers active | B12: count | C12: =IF(C3>=Assumptions!$F$16,CHOOSE(C6,Assumptions!$F$17,Assumptions!$F$18,Assumptions!$F$19),0) | D12: =IF(D3>=Assumptions!$F$16,CHOOSE(D6,Assumptions!$F$17,Assumptions!$F$18,Assumptions!$F$19),0) | E12: =IF(E3>=Assumptions!$F$16,CHOOSE(E6,Assumptions!$F$17,Assumptions!$F$18,Assumptions!$F$19),0) | F12: =IF(F3>=Assumptions!$F$16,CHOOSE(F6,Assumptions!$F$17,Assumptions!$F$18,Assumptions!$F$19),0) | G12: =IF(G3>=Assumptions!$F$16,CHOOSE(G6,Assumptions!$F$17,Assumptions!$F$18,Assumptions!$F$19),0) | H12: =IF(H3>=Assumptions!$F$16,CHOOSE(H6,Assumptions!$F$17,Assumptions!$F$18,Assumptions!$F$19),0) | I12: =IF(I3>=Assumptions!$F$16,CHOOSE(I6,Assumptions!$F$17,Assumptions!$F$18,Assumptions!$F$19),0) | J12: =IF(J3>=Assumptions!$F$16,CHOOSE(J6,Assumptions!$F$17,Assumptions!$F$18,Assumptions!$F$19),0) | ... AL12: =IF(AL3>=Assumptions!$F$16,CHOOSE(AL6,Assumptions!$F$17,Assumptions!$F$18,Assumptions!$F$19),0) | AN12: =AVERAGEIF($C$5:$AL$5,AN$5,C12:AL12) | AO12: =AVERAGEIF($C$5:$AL$5,AO$5,C12:AL12) | AP12: =AVERAGEIF($C$5:$AL$5,AP$5,C12:AL12) | AQ12: =AVERAGE(C12:AL12)
A13: Founder days consumed by retainers | B13: days | C13: ='Revenue build'!C12*Assumptions!$F$21 | D13: ='Revenue build'!D12*Assumptions!$F$21 | E13: ='Revenue build'!E12*Assumptions!$F$21 | F13: ='Revenue build'!F12*Assumptions!$F$21 | G13: ='Revenue build'!G12*Assumptions!$F$21 | H13: ='Revenue build'!H12*Assumptions!$F$21 | I13: ='Revenue build'!I12*Assumptions!$F$21 | J13: ='Revenue build'!J12*Assumptions!$F$21 | ... AL13: ='Revenue build'!AL12*Assumptions!$F$21 | AN13: =SUMIF($C$5:$AL$5,AN$5,C13:AL13) | AO13: =SUMIF($C$5:$AL$5,AO$5,C13:AL13) | AP13: =SUMIF($C$5:$AL$5,AP$5,C13:AL13) | AQ13: =SUM(C13:AL13)
A14: Consulting projects (per month, smoothed) | B14: count | C14: =CHOOSE(C6,Assumptions!$F$26,Assumptions!$F$27,Assumptions!$F$28)/12*'Revenue build'!C7 | D14: =CHOOSE(D6,Assumptions!$F$26,Assumptions!$F$27,Assumptions!$F$28)/12*'Revenue build'!D7 | E14: =CHOOSE(E6,Assumptions!$F$26,Assumptions!$F$27,Assumptions!$F$28)/12*'Revenue build'!E7 | F14: =CHOOSE(F6,Assumptions!$F$26,Assumptions!$F$27,Assumptions!$F$28)/12*'Revenue build'!F7 | G14: =CHOOSE(G6,Assumptions!$F$26,Assumptions!$F$27,Assumptions!$F$28)/12*'Revenue build'!G7 | H14: =CHOOSE(H6,Assumptions!$F$26,Assumptions!$F$27,Assumptions!$F$28)/12*'Revenue build'!H7 | I14: =CHOOSE(I6,Assumptions!$F$26,Assumptions!$F$27,Assumptions!$F$28)/12*'Revenue build'!I7 | J14: =CHOOSE(J6,Assumptions!$F$26,Assumptions!$F$27,Assumptions!$F$28)/12*'Revenue build'!J7 | ... AL14: =CHOOSE(AL6,Assumptions!$F$26,Assumptions!$F$27,Assumptions!$F$28)/12*'Revenue build'!AL7 | AN14: =SUMIF($C$5:$AL$5,AN$5,C14:AL14) | AO14: =SUMIF($C$5:$AL$5,AO$5,C14:AL14) | AP14: =SUMIF($C$5:$AL$5,AP$5,C14:AL14) | AQ14: =SUM(C14:AL14)
A15: Founder days consumed by consulting delivery | B15: days | C15: ='Revenue build'!C14*Assumptions!$F$30 | D15: ='Revenue build'!D14*Assumptions!$F$30 | E15: ='Revenue build'!E14*Assumptions!$F$30 | F15: ='Revenue build'!F14*Assumptions!$F$30 | G15: ='Revenue build'!G14*Assumptions!$F$30 | H15: ='Revenue build'!H14*Assumptions!$F$30 | I15: ='Revenue build'!I14*Assumptions!$F$30 | J15: ='Revenue build'!J14*Assumptions!$F$30 | ... AL15: ='Revenue build'!AL14*Assumptions!$F$30 | AN15: =SUMIF($C$5:$AL$5,AN$5,C15:AL15) | AO15: =SUMIF($C$5:$AL$5,AO$5,C15:AL15) | AP15: =SUMIF($C$5:$AL$5,AP$5,C15:AL15) | AQ15: =SUM(C15:AL15)
A16: Advisory day-rate days sold (residual capacity) | B16: days | C16: =MAX(0,'Revenue build'!C11-'Revenue build'!C13-'Revenue build'!C15) | D16: =MAX(0,'Revenue build'!D11-'Revenue build'!D13-'Revenue build'!D15) | E16: =MAX(0,'Revenue build'!E11-'Revenue build'!E13-'Revenue build'!E15) | F16: =MAX(0,'Revenue build'!F11-'Revenue build'!F13-'Revenue build'!F15) | G16: =MAX(0,'Revenue build'!G11-'Revenue build'!G13-'Revenue build'!G15) | H16: =MAX(0,'Revenue build'!H11-'Revenue build'!H13-'Revenue build'!H15) | I16: =MAX(0,'Revenue build'!I11-'Revenue build'!I13-'Revenue build'!I15) | J16: =MAX(0,'Revenue build'!J11-'Revenue build'!J13-'Revenue build'!J15) | ... AL16: =MAX(0,'Revenue build'!AL11-'Revenue build'!AL13-'Revenue build'!AL15) | AN16: =SUMIF($C$5:$AL$5,AN$5,C16:AL16) | AO16: =SUMIF($C$5:$AL$5,AO$5,C16:AL16) | AP16: =SUMIF($C$5:$AL$5,AP$5,C16:AL16) | AQ16: =SUM(C16:AL16)
A17: Founder capacity used by retainers + projects (>100% = associate-dependent) | C17: =IF('Revenue build'!C11>0,('Revenue build'!C13+'Revenue build'!C15)/'Revenue build'!C11,0) | D17: =IF('Revenue build'!D11>0,('Revenue build'!D13+'Revenue build'!D15)/'Revenue build'!D11,0) | E17: =IF('Revenue build'!E11>0,('Revenue build'!E13+'Revenue build'!E15)/'Revenue build'!E11,0) | F17: =IF('Revenue build'!F11>0,('Revenue build'!F13+'Revenue build'!F15)/'Revenue build'!F11,0) | G17: =IF('Revenue build'!G11>0,('Revenue build'!G13+'Revenue build'!G15)/'Revenue build'!G11,0) | H17: =IF('Revenue build'!H11>0,('Revenue build'!H13+'Revenue build'!H15)/'Revenue build'!H11,0) | I17: =IF('Revenue build'!I11>0,('Revenue build'!I13+'Revenue build'!I15)/'Revenue build'!I11,0) | J17: =IF('Revenue build'!J11>0,('Revenue build'!J13+'Revenue build'!J15)/'Revenue build'!J11,0) | ... AL17: =IF('Revenue build'!AL11>0,('Revenue build'!AL13+'Revenue build'!AL15)/'Revenue build'!AL11,0) | AN17: =AVERAGEIF($C$5:$AL$5,AN$5,C17:AL17) | AO17: =AVERAGEIF($C$5:$AL$5,AO$5,C17:AL17) | AP17: =AVERAGEIF($C$5:$AL$5,AP$5,C17:AL17) | AQ17: =AVERAGE(C17:AL17)
A18: Founder day rate | B18: GBP/day | C18: =Assumptions!$F$14 | D18: =Assumptions!$F$14 | E18: =Assumptions!$F$14 | F18: =Assumptions!$F$14 | G18: =Assumptions!$F$14 | H18: =Assumptions!$F$14 | I18: =Assumptions!$F$14 | J18: =Assumptions!$F$14 | ... AL18: =Assumptions!$F$14 | AN18: =AVERAGEIF($C$5:$AL$5,AN$5,C18:AL18) | AO18: =AVERAGEIF($C$5:$AL$5,AO$5,C18:AL18) | AP18: =AVERAGEIF($C$5:$AL$5,AP$5,C18:AL18) | AQ18: =AVERAGE(C18:AL18)
A19: Advisory day-rate revenue | C19: ='Revenue build'!C16*'Revenue build'!C18 | D19: ='Revenue build'!D16*'Revenue build'!D18 | E19: ='Revenue build'!E16*'Revenue build'!E18 | F19: ='Revenue build'!F16*'Revenue build'!F18 | G19: ='Revenue build'!G16*'Revenue build'!G18 | H19: ='Revenue build'!H16*'Revenue build'!H18 | I19: ='Revenue build'!I16*'Revenue build'!I18 | J19: ='Revenue build'!J16*'Revenue build'!J18 | ... AL19: ='Revenue build'!AL16*'Revenue build'!AL18 | AN19: =SUMIF($C$5:$AL$5,AN$5,C19:AL19) | AO19: =SUMIF($C$5:$AL$5,AO$5,C19:AL19) | AP19: =SUMIF($C$5:$AL$5,AP$5,C19:AL19) | AQ19: =SUM(C19:AL19)
A20: Retainer revenue | C20: ='Revenue build'!C12*Assumptions!$F$20 | D20: ='Revenue build'!D12*Assumptions!$F$20 | E20: ='Revenue build'!E12*Assumptions!$F$20 | F20: ='Revenue build'!F12*Assumptions!$F$20 | G20: ='Revenue build'!G12*Assumptions!$F$20 | H20: ='Revenue build'!H12*Assumptions!$F$20 | I20: ='Revenue build'!I12*Assumptions!$F$20 | J20: ='Revenue build'!J12*Assumptions!$F$20 | ... AL20: ='Revenue build'!AL12*Assumptions!$F$20 | AN20: =SUMIF($C$5:$AL$5,AN$5,C20:AL20) | AO20: =SUMIF($C$5:$AL$5,AO$5,C20:AL20) | AP20: =SUMIF($C$5:$AL$5,AP$5,C20:AL20) | AQ20: =SUM(C20:AL20)
A21: Senior consultant billable days | B21: days | C21: ='Headcount'!C17*Assumptions!$F$23 | D21: ='Headcount'!D17*Assumptions!$F$23 | E21: ='Headcount'!E17*Assumptions!$F$23 | F21: ='Headcount'!F17*Assumptions!$F$23 | G21: ='Headcount'!G17*Assumptions!$F$23 | H21: ='Headcount'!H17*Assumptions!$F$23 | I21: ='Headcount'!I17*Assumptions!$F$23 | J21: ='Headcount'!J17*Assumptions!$F$23 | ... AL21: ='Headcount'!AL17*Assumptions!$F$23 | AN21: =SUMIF($C$5:$AL$5,AN$5,C21:AL21) | AO21: =SUMIF($C$5:$AL$5,AO$5,C21:AL21) | AP21: =SUMIF($C$5:$AL$5,AP$5,C21:AL21) | AQ21: =SUM(C21:AL21)
A22: Senior consultant revenue | C22: ='Revenue build'!C21*Assumptions!$F$24 | D22: ='Revenue build'!D21*Assumptions!$F$24 | E22: ='Revenue build'!E21*Assumptions!$F$24 | F22: ='Revenue build'!F21*Assumptions!$F$24 | G22: ='Revenue build'!G21*Assumptions!$F$24 | H22: ='Revenue build'!H21*Assumptions!$F$24 | I22: ='Revenue build'!I21*Assumptions!$F$24 | J22: ='Revenue build'!J21*Assumptions!$F$24 | ... AL22: ='Revenue build'!AL21*Assumptions!$F$24 | AN22: =SUMIF($C$5:$AL$5,AN$5,C22:AL22) | AO22: =SUMIF($C$5:$AL$5,AO$5,C22:AL22) | AP22: =SUMIF($C$5:$AL$5,AP$5,C22:AL22) | AQ22: =SUM(C22:AL22)
A23: ADVISORY REVENUE | C23: ='Revenue build'!C19+'Revenue build'!C20+'Revenue build'!C22 | D23: ='Revenue build'!D19+'Revenue build'!D20+'Revenue build'!D22 | E23: ='Revenue build'!E19+'Revenue build'!E20+'Revenue build'!E22 | F23: ='Revenue build'!F19+'Revenue build'!F20+'Revenue build'!F22 | G23: ='Revenue build'!G19+'Revenue build'!G20+'Revenue build'!G22 | H23: ='Revenue build'!H19+'Revenue build'!H20+'Revenue build'!H22 | I23: ='Revenue build'!I19+'Revenue build'!I20+'Revenue build'!I22 | J23: ='Revenue build'!J19+'Revenue build'!J20+'Revenue build'!J22 | ... AL23: ='Revenue build'!AL19+'Revenue build'!AL20+'Revenue build'!AL22 | AN23: =SUMIF($C$5:$AL$5,AN$5,C23:AL23) | AO23: =SUMIF($C$5:$AL$5,AO$5,C23:AL23) | AP23: =SUMIF($C$5:$AL$5,AP$5,C23:AL23) | AQ23: =SUM(C23:AL23)
A25: CONSULTING
A26: Average project value | B26: GBP | C26: =Assumptions!$F$29 | D26: =Assumptions!$F$29 | E26: =Assumptions!$F$29 | F26: =Assumptions!$F$29 | G26: =Assumptions!$F$29 | H26: =Assumptions!$F$29 | I26: =Assumptions!$F$29 | J26: =Assumptions!$F$29 | ... AL26: =Assumptions!$F$29 | AN26: =AVERAGEIF($C$5:$AL$5,AN$5,C26:AL26) | AO26: =AVERAGEIF($C$5:$AL$5,AO$5,C26:AL26) | AP26: =AVERAGEIF($C$5:$AL$5,AP$5,C26:AL26) | AQ26: =AVERAGE(C26:AL26)
A27: CONSULTING REVENUE (projects × value) | C27: ='Revenue build'!C14*'Revenue build'!C26 | D27: ='Revenue build'!D14*'Revenue build'!D26 | E27: ='Revenue build'!E14*'Revenue build'!E26 | F27: ='Revenue build'!F14*'Revenue build'!F26 | G27: ='Revenue build'!G14*'Revenue build'!G26 | H27: ='Revenue build'!H14*'Revenue build'!H26 | I27: ='Revenue build'!I14*'Revenue build'!I26 | J27: ='Revenue build'!J14*'Revenue build'!J26 | ... AL27: ='Revenue build'!AL14*'Revenue build'!AL26 | AN27: =SUMIF($C$5:$AL$5,AN$5,C27:AL27) | AO27: =SUMIF($C$5:$AL$5,AO$5,C27:AL27) | AP27: =SUMIF($C$5:$AL$5,AP$5,C27:AL27) | AQ27: =SUM(C27:AL27)
A29: E-LEARNING
A30: Launched (1/0) | C30: =IF(C3>=Assumptions!$F$33,1,0) | D30: =IF(D3>=Assumptions!$F$33,1,0) | E30: =IF(E3>=Assumptions!$F$33,1,0) | F30: =IF(F3>=Assumptions!$F$33,1,0) | G30: =IF(G3>=Assumptions!$F$33,1,0) | H30: =IF(H3>=Assumptions!$F$33,1,0) | I30: =IF(I3>=Assumptions!$F$33,1,0) | J30: =IF(J3>=Assumptions!$F$33,1,0) | ... AL30: =IF(AL3>=Assumptions!$F$33,1,0) | AN30: =INDEX(C30:AL30,1,12) | AO30: =INDEX(C30:AL30,1,24) | AP30: =INDEX(C30:AL30,1,36) | AQ30: =INDEX(C30:AL30,1,36)
A31: New learners per month | B31: learners | C31: =IF('Revenue build'!C30=1,Assumptions!$F$34*(1+Assumptions!$F$35)^(C3-Assumptions!$F$33),0) | D31: =IF('Revenue build'!D30=1,Assumptions!$F$34*(1+Assumptions!$F$35)^(D3-Assumptions!$F$33),0) | E31: =IF('Revenue build'!E30=1,Assumptions!$F$34*(1+Assumptions!$F$35)^(E3-Assumptions!$F$33),0) | F31: =IF('Revenue build'!F30=1,Assumptions!$F$34*(1+Assumptions!$F$35)^(F3-Assumptions!$F$33),0) | G31: =IF('Revenue build'!G30=1,Assumptions!$F$34*(1+Assumptions!$F$35)^(G3-Assumptions!$F$33),0) | H31: =IF('Revenue build'!H30=1,Assumptions!$F$34*(1+Assumptions!$F$35)^(H3-Assumptions!$F$33),0) | I31: =IF('Revenue build'!I30=1,Assumptions!$F$34*(1+Assumptions!$F$35)^(I3-Assumptions!$F$33),0) | J31: =IF('Revenue build'!J30=1,Assumptions!$F$34*(1+Assumptions!$F$35)^(J3-Assumptions!$F$33),0) | ... AL31: =IF('Revenue build'!AL30=1,Assumptions!$F$34*(1+Assumptions!$F$35)^(AL3-Assumptions!$F$33),0) | AN31: =SUMIF($C$5:$AL$5,AN$5,C31:AL31) | AO31: =SUMIF($C$5:$AL$5,AO$5,C31:AL31) | AP31: =SUMIF($C$5:$AL$5,AP$5,C31:AL31) | AQ31: =SUM(C31:AL31)
A32: ARPU | B32: GBP | C32: =Assumptions!$F$36 | D32: =Assumptions!$F$36 | E32: =Assumptions!$F$36 | F32: =Assumptions!$F$36 | G32: =Assumptions!$F$36 | H32: =Assumptions!$F$36 | I32: =Assumptions!$F$36 | J32: =Assumptions!$F$36 | ... AL32: =Assumptions!$F$36 | AN32: =AVERAGEIF($C$5:$AL$5,AN$5,C32:AL32) | AO32: =AVERAGEIF($C$5:$AL$5,AO$5,C32:AL32) | AP32: =AVERAGEIF($C$5:$AL$5,AP$5,C32:AL32) | AQ32: =AVERAGE(C32:AL32)
A33: Course revenue (learners × ARPU) | C33: ='Revenue build'!C31*'Revenue build'!C32 | D33: ='Revenue build'!D31*'Revenue build'!D32 | E33: ='Revenue build'!E31*'Revenue build'!E32 | F33: ='Revenue build'!F31*'Revenue build'!F32 | G33: ='Revenue build'!G31*'Revenue build'!G32 | H33: ='Revenue build'!H31*'Revenue build'!H32 | I33: ='Revenue build'!I31*'Revenue build'!I32 | J33: ='Revenue build'!J31*'Revenue build'!J32 | ... AL33: ='Revenue build'!AL31*'Revenue build'!AL32 | AN33: =SUMIF($C$5:$AL$5,AN$5,C33:AL33) | AO33: =SUMIF($C$5:$AL$5,AO$5,C33:AL33) | AP33: =SUMIF($C$5:$AL$5,AP$5,C33:AL33) | AQ33: =SUM(C33:AL33)
A34: Corporate licences active | B34: count | C34: ='Revenue build'!C30*CHOOSE(C6,Assumptions!$F$37,Assumptions!$F$38,Assumptions!$F$39) | D34: ='Revenue build'!D30*CHOOSE(D6,Assumptions!$F$37,Assumptions!$F$38,Assumptions!$F$39) | E34: ='Revenue build'!E30*CHOOSE(E6,Assumptions!$F$37,Assumptions!$F$38,Assumptions!$F$39) | F34: ='Revenue build'!F30*CHOOSE(F6,Assumptions!$F$37,Assumptions!$F$38,Assumptions!$F$39) | G34: ='Revenue build'!G30*CHOOSE(G6,Assumptions!$F$37,Assumptions!$F$38,Assumptions!$F$39) | H34: ='Revenue build'!H30*CHOOSE(H6,Assumptions!$F$37,Assumptions!$F$38,Assumptions!$F$39) | I34: ='Revenue build'!I30*CHOOSE(I6,Assumptions!$F$37,Assumptions!$F$38,Assumptions!$F$39) | J34: ='Revenue build'!J30*CHOOSE(J6,Assumptions!$F$37,Assumptions!$F$38,Assumptions!$F$39) | ... AL34: ='Revenue build'!AL30*CHOOSE(AL6,Assumptions!$F$37,Assumptions!$F$38,Assumptions!$F$39) | AN34: =AVERAGEIF($C$5:$AL$5,AN$5,C34:AL34) | AO34: =AVERAGEIF($C$5:$AL$5,AO$5,C34:AL34) | AP34: =AVERAGEIF($C$5:$AL$5,AP$5,C34:AL34) | AQ34: =AVERAGE(C34:AL34)
A35: Corporate licence revenue | C35: ='Revenue build'!C34*Assumptions!$F$40/12 | D35: ='Revenue build'!D34*Assumptions!$F$40/12 | E35: ='Revenue build'!E34*Assumptions!$F$40/12 | F35: ='Revenue build'!F34*Assumptions!$F$40/12 | G35: ='Revenue build'!G34*Assumptions!$F$40/12 | H35: ='Revenue build'!H34*Assumptions!$F$40/12 | I35: ='Revenue build'!I34*Assumptions!$F$40/12 | J35: ='Revenue build'!J34*Assumptions!$F$40/12 | ... AL35: ='Revenue build'!AL34*Assumptions!$F$40/12 | AN35: =SUMIF($C$5:$AL$5,AN$5,C35:AL35) | AO35: =SUMIF($C$5:$AL$5,AO$5,C35:AL35) | AP35: =SUMIF($C$5:$AL$5,AP$5,C35:AL35) | AQ35: =SUM(C35:AL35)
A36: E-LEARNING REVENUE | C36: ='Revenue build'!C33+'Revenue build'!C35 | D36: ='Revenue build'!D33+'Revenue build'!D35 | E36: ='Revenue build'!E33+'Revenue build'!E35 | F36: ='Revenue build'!F33+'Revenue build'!F35 | G36: ='Revenue build'!G33+'Revenue build'!G35 | H36: ='Revenue build'!H33+'Revenue build'!H35 | I36: ='Revenue build'!I33+'Revenue build'!I35 | J36: ='Revenue build'!J33+'Revenue build'!J35 | ... AL36: ='Revenue build'!AL33+'Revenue build'!AL35 | AN36: =SUMIF($C$5:$AL$5,AN$5,C36:AL36) | AO36: =SUMIF($C$5:$AL$5,AO$5,C36:AL36) | AP36: =SUMIF($C$5:$AL$5,AP$5,C36:AL36) | AQ36: =SUM(C36:AL36)
A38: MATERNALINK (IN DEVELOPMENT)
A39: Paid pilots started (1/0) | C39: =IF(C3>=Assumptions!$F$44,1,0) | D39: =IF(D3>=Assumptions!$F$44,1,0) | E39: =IF(E3>=Assumptions!$F$44,1,0) | F39: =IF(F3>=Assumptions!$F$44,1,0) | G39: =IF(G3>=Assumptions!$F$44,1,0) | H39: =IF(H3>=Assumptions!$F$44,1,0) | I39: =IF(I3>=Assumptions!$F$44,1,0) | J39: =IF(J3>=Assumptions!$F$44,1,0) | ... AL39: =IF(AL3>=Assumptions!$F$44,1,0) | AN39: =INDEX(C39:AL39,1,12) | AO39: =INDEX(C39:AL39,1,24) | AP39: =INDEX(C39:AL39,1,36) | AQ39: =INDEX(C39:AL39,1,36)
A40: Active paid pilots | B40: count | C40: ='Revenue build'!C39*CHOOSE(C6,Assumptions!$F$45,Assumptions!$F$46,Assumptions!$F$47) | D40: ='Revenue build'!D39*CHOOSE(D6,Assumptions!$F$45,Assumptions!$F$46,Assumptions!$F$47) | E40: ='Revenue build'!E39*CHOOSE(E6,Assumptions!$F$45,Assumptions!$F$46,Assumptions!$F$47) | F40: ='Revenue build'!F39*CHOOSE(F6,Assumptions!$F$45,Assumptions!$F$46,Assumptions!$F$47) | G40: ='Revenue build'!G39*CHOOSE(G6,Assumptions!$F$45,Assumptions!$F$46,Assumptions!$F$47) | H40: ='Revenue build'!H39*CHOOSE(H6,Assumptions!$F$45,Assumptions!$F$46,Assumptions!$F$47) | I40: ='Revenue build'!I39*CHOOSE(I6,Assumptions!$F$45,Assumptions!$F$46,Assumptions!$F$47) | J40: ='Revenue build'!J39*CHOOSE(J6,Assumptions!$F$45,Assumptions!$F$46,Assumptions!$F$47) | ... AL40: ='Revenue build'!AL39*CHOOSE(AL6,Assumptions!$F$45,Assumptions!$F$46,Assumptions!$F$47) | AN40: =AVERAGEIF($C$5:$AL$5,AN$5,C40:AL40) | AO40: =AVERAGEIF($C$5:$AL$5,AO$5,C40:AL40) | AP40: =AVERAGEIF($C$5:$AL$5,AP$5,C40:AL40) | AQ40: =AVERAGE(C40:AL40)
A41: Pilot revenue (pilots × value ÷ 12) | C41: ='Revenue build'!C40*Assumptions!$F$48/12 | D41: ='Revenue build'!D40*Assumptions!$F$48/12 | E41: ='Revenue build'!E40*Assumptions!$F$48/12 | F41: ='Revenue build'!F40*Assumptions!$F$48/12 | G41: ='Revenue build'!G40*Assumptions!$F$48/12 | H41: ='Revenue build'!H40*Assumptions!$F$48/12 | I41: ='Revenue build'!I40*Assumptions!$F$48/12 | J41: ='Revenue build'!J40*Assumptions!$F$48/12 | ... AL41: ='Revenue build'!AL40*Assumptions!$F$48/12 | AN41: =SUMIF($C$5:$AL$5,AN$5,C41:AL41) | AO41: =SUMIF($C$5:$AL$5,AO$5,C41:AL41) | AP41: =SUMIF($C$5:$AL$5,AP$5,C41:AL41) | AQ41: =SUM(C41:AL41)
A42: Licence go-live month (base + delay) | B42: month | C42: =Assumptions!$F$50+Assumptions!$F$51 | D42: =Assumptions!$F$50+Assumptions!$F$51 | E42: =Assumptions!$F$50+Assumptions!$F$51 | F42: =Assumptions!$F$50+Assumptions!$F$51 | G42: =Assumptions!$F$50+Assumptions!$F$51 | H42: =Assumptions!$F$50+Assumptions!$F$51 | I42: =Assumptions!$F$50+Assumptions!$F$51 | J42: =Assumptions!$F$50+Assumptions!$F$51 | ... AL42: =Assumptions!$F$50+Assumptions!$F$51 | AN42: =INDEX(C42:AL42,1,12) | AO42: =INDEX(C42:AL42,1,24) | AP42: =INDEX(C42:AL42,1,36) | AQ42: =INDEX(C42:AL42,1,36)
A43: Licences live (1/0) | C43: =IF(C3>='Revenue build'!C42,1,0) | D43: =IF(D3>='Revenue build'!D42,1,0) | E43: =IF(E3>='Revenue build'!E42,1,0) | F43: =IF(F3>='Revenue build'!F42,1,0) | G43: =IF(G3>='Revenue build'!G42,1,0) | H43: =IF(H3>='Revenue build'!H42,1,0) | I43: =IF(I3>='Revenue build'!I42,1,0) | J43: =IF(J3>='Revenue build'!J42,1,0) | ... AL43: =IF(AL3>='Revenue build'!AL42,1,0) | AN43: =INDEX(C43:AL43,1,12) | AO43: =INDEX(C43:AL43,1,24) | AP43: =INDEX(C43:AL43,1,36) | AQ43: =INDEX(C43:AL43,1,36)
A44: UK women enrolled | B44: women | C44: ='Revenue build'!C43*(Assumptions!$F$52+Assumptions!$F$53*(C3-'Revenue build'!C42)) | D44: ='Revenue build'!D43*(Assumptions!$F$52+Assumptions!$F$53*(D3-'Revenue build'!D42)) | E44: ='Revenue build'!E43*(Assumptions!$F$52+Assumptions!$F$53*(E3-'Revenue build'!E42)) | F44: ='Revenue build'!F43*(Assumptions!$F$52+Assumptions!$F$53*(F3-'Revenue build'!F42)) | G44: ='Revenue build'!G43*(Assumptions!$F$52+Assumptions!$F$53*(G3-'Revenue build'!G42)) | H44: ='Revenue build'!H43*(Assumptions!$F$52+Assumptions!$F$53*(H3-'Revenue build'!H42)) | I44: ='Revenue build'!I43*(Assumptions!$F$52+Assumptions!$F$53*(I3-'Revenue build'!I42)) | J44: ='Revenue build'!J43*(Assumptions!$F$52+Assumptions!$F$53*(J3-'Revenue build'!J42)) | ... AL44: ='Revenue build'!AL43*(Assumptions!$F$52+Assumptions!$F$53*(AL3-'Revenue build'!AL42)) | AN44: =INDEX(C44:AL44,1,12) | AO44: =INDEX(C44:AL44,1,24) | AP44: =INDEX(C44:AL44,1,36) | AQ44: =INDEX(C44:AL44,1,36)
A45: UK licence revenue (women × £/yr ÷ 12) | C45: ='Revenue build'!C44*Assumptions!$F$54/12 | D45: ='Revenue build'!D44*Assumptions!$F$54/12 | E45: ='Revenue build'!E44*Assumptions!$F$54/12 | F45: ='Revenue build'!F44*Assumptions!$F$54/12 | G45: ='Revenue build'!G44*Assumptions!$F$54/12 | H45: ='Revenue build'!H44*Assumptions!$F$54/12 | I45: ='Revenue build'!I44*Assumptions!$F$54/12 | J45: ='Revenue build'!J44*Assumptions!$F$54/12 | ... AL45: ='Revenue build'!AL44*Assumptions!$F$54/12 | AN45: =SUMIF($C$5:$AL$5,AN$5,C45:AL45) | AO45: =SUMIF($C$5:$AL$5,AO$5,C45:AL45) | AP45: =SUMIF($C$5:$AL$5,AP$5,C45:AL45) | AQ45: =SUM(C45:AL45)
A46: Africa women enrolled | B46: women | C46: ='Revenue build'!C43*(Assumptions!$F$56+Assumptions!$F$57*(C3-'Revenue build'!C42)) | D46: ='Revenue build'!D43*(Assumptions!$F$56+Assumptions!$F$57*(D3-'Revenue build'!D42)) | E46: ='Revenue build'!E43*(Assumptions!$F$56+Assumptions!$F$57*(E3-'Revenue build'!E42)) | F46: ='Revenue build'!F43*(Assumptions!$F$56+Assumptions!$F$57*(F3-'Revenue build'!F42)) | G46: ='Revenue build'!G43*(Assumptions!$F$56+Assumptions!$F$57*(G3-'Revenue build'!G42)) | H46: ='Revenue build'!H43*(Assumptions!$F$56+Assumptions!$F$57*(H3-'Revenue build'!H42)) | I46: ='Revenue build'!I43*(Assumptions!$F$56+Assumptions!$F$57*(I3-'Revenue build'!I42)) | J46: ='Revenue build'!J43*(Assumptions!$F$56+Assumptions!$F$57*(J3-'Revenue build'!J42)) | ... AL46: ='Revenue build'!AL43*(Assumptions!$F$56+Assumptions!$F$57*(AL3-'Revenue build'!AL42)) | AN46: =INDEX(C46:AL46,1,12) | AO46: =INDEX(C46:AL46,1,24) | AP46: =INDEX(C46:AL46,1,36) | AQ46: =INDEX(C46:AL46,1,36)
A47: Africa licence revenue (women × £/yr ÷ 12) | C47: ='Revenue build'!C46*Assumptions!$F$58/12 | D47: ='Revenue build'!D46*Assumptions!$F$58/12 | E47: ='Revenue build'!E46*Assumptions!$F$58/12 | F47: ='Revenue build'!F46*Assumptions!$F$58/12 | G47: ='Revenue build'!G46*Assumptions!$F$58/12 | H47: ='Revenue build'!H46*Assumptions!$F$58/12 | I47: ='Revenue build'!I46*Assumptions!$F$58/12 | J47: ='Revenue build'!J46*Assumptions!$F$58/12 | ... AL47: ='Revenue build'!AL46*Assumptions!$F$58/12 | AN47: =SUMIF($C$5:$AL$5,AN$5,C47:AL47) | AO47: =SUMIF($C$5:$AL$5,AO$5,C47:AL47) | AP47: =SUMIF($C$5:$AL$5,AP$5,C47:AL47) | AQ47: =SUM(C47:AL47)
A48: MATERNALINK REVENUE | C48: ='Revenue build'!C41+'Revenue build'!C45+'Revenue build'!C47 | D48: ='Revenue build'!D41+'Revenue build'!D45+'Revenue build'!D47 | E48: ='Revenue build'!E41+'Revenue build'!E45+'Revenue build'!E47 | F48: ='Revenue build'!F41+'Revenue build'!F45+'Revenue build'!F47 | G48: ='Revenue build'!G41+'Revenue build'!G45+'Revenue build'!G47 | H48: ='Revenue build'!H41+'Revenue build'!H45+'Revenue build'!H47 | I48: ='Revenue build'!I41+'Revenue build'!I45+'Revenue build'!I47 | J48: ='Revenue build'!J41+'Revenue build'!J45+'Revenue build'!J47 | ... AL48: ='Revenue build'!AL41+'Revenue build'!AL45+'Revenue build'!AL47 | AN48: =SUMIF($C$5:$AL$5,AN$5,C48:AL48) | AO48: =SUMIF($C$5:$AL$5,AO$5,C48:AL48) | AP48: =SUMIF($C$5:$AL$5,AP$5,C48:AL48) | AQ48: =SUM(C48:AL48)
A50: TOTAL REVENUE | C50: ='Revenue build'!C23+'Revenue build'!C27+'Revenue build'!C36+'Revenue build'!C48 | D50: ='Revenue build'!D23+'Revenue build'!D27+'Revenue build'!D36+'Revenue build'!D48 | E50: ='Revenue build'!E23+'Revenue build'!E27+'Revenue build'!E36+'Revenue build'!E48 | F50: ='Revenue build'!F23+'Revenue build'!F27+'Revenue build'!F36+'Revenue build'!F48 | G50: ='Revenue build'!G23+'Revenue build'!G27+'Revenue build'!G36+'Revenue build'!G48 | H50: ='Revenue build'!H23+'Revenue build'!H27+'Revenue build'!H36+'Revenue build'!H48 | I50: ='Revenue build'!I23+'Revenue build'!I27+'Revenue build'!I36+'Revenue build'!I48 | J50: ='Revenue build'!J23+'Revenue build'!J27+'Revenue build'!J36+'Revenue build'!J48 | ... AL50: ='Revenue build'!AL23+'Revenue build'!AL27+'Revenue build'!AL36+'Revenue build'!AL48 | AN50: =SUMIF($C$5:$AL$5,AN$5,C50:AL50) | AO50: =SUMIF($C$5:$AL$5,AO$5,C50:AL50) | AP50: =SUMIF($C$5:$AL$5,AP$5,C50:AL50) | AQ50: =SUM(C50:AL50)
A52: Note: the £300/woman/year in the Ekiti proposal is UNVALIDATED (FACTS_BASE A5) and is not used anywhere in this model.

Sheet Cost of sales
A1: Cost of sales and gross margin
A2: ="Scenario: "&Assumptions!$D$4&" — all figures GBP, scenario values, not actuals"
A3: Month # | C3: 1 | D3: 2 | E3: 3 | F3: 4 | G3: 5 | H3: 6 | I3: 7 | J3: 8 | K3: 9 | L3: 10 | M3: 11 | N3: 12 | O3: 13 | P3: 14 | Q3: 15 | R3: 16 | S3: 17 | T3: 18 | U3: 19 | V3: 20 | W3: 21 | X3: 22 | Y3: 23 | Z3: 24 | AA3: 25 | AB3: 26 | AC3: 27 | AD3: 28 | AE3: 29 | AF3: 30 | AG3: 31 | AH3: 32 | AI3: 33 | AJ3: 34 | AK3: 35 | AL3: 36
A4: Month | C4: 46388 | D4: 46419 | E4: 46447 | F4: 46478 | G4: 46508 | H4: 46539 | I4: 46569 | J4: 46600 | K4: 46631 | L4: 46661 | M4: 46692 | N4: 46722 | O4: 46753 | P4: 46784 | Q4: 46813 | R4: 46844 | S4: 46874 | T4: 46905 | U4: 46935 | V4: 46966 | W4: 46997 | X4: 47027 | Y4: 47058 | Z4: 47088 | AA4: 47119 | AB4: 47150 | AC4: 47178 | AD4: 47209 | AE4: 47239 | AF4: 47270 | AG4: 47300 | AH4: 47331 | AI4: 47362 | AJ4: 47392 | AK4: 47423 | AL4: 47453 | AN4: FY2027 | AO4: FY2028 | AP4: FY2029 | AQ4: 3-year total
A5: Year | C5: 2027 | D5: 2027 | E5: 2027 | F5: 2027 | G5: 2027 | H5: 2027 | I5: 2027 | J5: 2027 | K5: 2027 | L5: 2027 | M5: 2027 | N5: 2027 | O5: 2028 | P5: 2028 | Q5: 2028 | R5: 2028 | S5: 2028 | T5: 2028 | U5: 2028 | V5: 2028 | W5: 2028 | X5: 2028 | Y5: 2028 | Z5: 2028 | AA5: 2029 | AB5: 2029 | AC5: 2029 | AD5: 2029 | AE5: 2029 | AF5: 2029 | AG5: 2029 | AH5: 2029 | AI5: 2029 | AJ5: 2029 | AK5: 2029 | AL5: 2029 | AN5: 2027 | AO5: 2028 | AP5: 2029
A6: Year index | C6: =C5-2026 | D6: =D5-2026 | E6: =E5-2026 | F6: =F5-2026 | G6: =G5-2026 | H6: =H5-2026 | I6: =I5-2026 | J6: =J5-2026 | ... AL6: =AL5-2026
A7: Advisory direct costs (travel/tools per billable day) | C7: =('Revenue build'!C16+'Revenue build'!C13)*Assumptions!$F$22 | D7: =('Revenue build'!D16+'Revenue build'!D13)*Assumptions!$F$22 | E7: =('Revenue build'!E16+'Revenue build'!E13)*Assumptions!$F$22 | F7: =('Revenue build'!F16+'Revenue build'!F13)*Assumptions!$F$22 | G7: =('Revenue build'!G16+'Revenue build'!G13)*Assumptions!$F$22 | H7: =('Revenue build'!H16+'Revenue build'!H13)*Assumptions!$F$22 | I7: =('Revenue build'!I16+'Revenue build'!I13)*Assumptions!$F$22 | J7: =('Revenue build'!J16+'Revenue build'!J13)*Assumptions!$F$22 | ... AL7: =('Revenue build'!AL16+'Revenue build'!AL13)*Assumptions!$F$22 | AN7: =SUMIF($C$5:$AL$5,AN$5,C7:AL7) | AO7: =SUMIF($C$5:$AL$5,AO$5,C7:AL7) | AP7: =SUMIF($C$5:$AL$5,AP$5,C7:AL7) | AQ7: =SUM(C7:AL7)
A8: Consulting delivery (associates, expenses) | C8: ='Revenue build'!C27*Assumptions!$F$31 | D8: ='Revenue build'!D27*Assumptions!$F$31 | E8: ='Revenue build'!E27*Assumptions!$F$31 | F8: ='Revenue build'!F27*Assumptions!$F$31 | G8: ='Revenue build'!G27*Assumptions!$F$31 | H8: ='Revenue build'!H27*Assumptions!$F$31 | I8: ='Revenue build'!I27*Assumptions!$F$31 | J8: ='Revenue build'!J27*Assumptions!$F$31 | ... AL8: ='Revenue build'!AL27*Assumptions!$F$31 | AN8: =SUMIF($C$5:$AL$5,AN$5,C8:AL8) | AO8: =SUMIF($C$5:$AL$5,AO$5,C8:AL8) | AP8: =SUMIF($C$5:$AL$5,AP$5,C8:AL8) | AQ8: =SUM(C8:AL8)
A9: E-learning platform and payment fees | C9: ='Revenue build'!C36*Assumptions!$F$41 | D9: ='Revenue build'!D36*Assumptions!$F$41 | E9: ='Revenue build'!E36*Assumptions!$F$41 | F9: ='Revenue build'!F36*Assumptions!$F$41 | G9: ='Revenue build'!G36*Assumptions!$F$41 | H9: ='Revenue build'!H36*Assumptions!$F$41 | I9: ='Revenue build'!I36*Assumptions!$F$41 | J9: ='Revenue build'!J36*Assumptions!$F$41 | ... AL9: ='Revenue build'!AL36*Assumptions!$F$41 | AN9: =SUMIF($C$5:$AL$5,AN$5,C9:AL9) | AO9: =SUMIF($C$5:$AL$5,AO$5,C9:AL9) | AP9: =SUMIF($C$5:$AL$5,AP$5,C9:AL9) | AQ9: =SUM(C9:AL9)
A10: MaternaLink pilot delivery | C10: ='Revenue build'!C41*Assumptions!$F$49 | D10: ='Revenue build'!D41*Assumptions!$F$49 | E10: ='Revenue build'!E41*Assumptions!$F$49 | F10: ='Revenue build'!F41*Assumptions!$F$49 | G10: ='Revenue build'!G41*Assumptions!$F$49 | H10: ='Revenue build'!H41*Assumptions!$F$49 | I10: ='Revenue build'!I41*Assumptions!$F$49 | J10: ='Revenue build'!J41*Assumptions!$F$49 | ... AL10: ='Revenue build'!AL41*Assumptions!$F$49 | AN10: =SUMIF($C$5:$AL$5,AN$5,C10:AL10) | AO10: =SUMIF($C$5:$AL$5,AO$5,C10:AL10) | AP10: =SUMIF($C$5:$AL$5,AP$5,C10:AL10) | AQ10: =SUM(C10:AL10)
A11: MaternaLink licence hosting/support | C11: =('Revenue build'!C44*Assumptions!$F$55+'Revenue build'!C46*Assumptions!$F$59)/12 | D11: =('Revenue build'!D44*Assumptions!$F$55+'Revenue build'!D46*Assumptions!$F$59)/12 | E11: =('Revenue build'!E44*Assumptions!$F$55+'Revenue build'!E46*Assumptions!$F$59)/12 | F11: =('Revenue build'!F44*Assumptions!$F$55+'Revenue build'!F46*Assumptions!$F$59)/12 | G11: =('Revenue build'!G44*Assumptions!$F$55+'Revenue build'!G46*Assumptions!$F$59)/12 | H11: =('Revenue build'!H44*Assumptions!$F$55+'Revenue build'!H46*Assumptions!$F$59)/12 | I11: =('Revenue build'!I44*Assumptions!$F$55+'Revenue build'!I46*Assumptions!$F$59)/12 | J11: =('Revenue build'!J44*Assumptions!$F$55+'Revenue build'!J46*Assumptions!$F$59)/12 | ... AL11: =('Revenue build'!AL44*Assumptions!$F$55+'Revenue build'!AL46*Assumptions!$F$59)/12 | AN11: =SUMIF($C$5:$AL$5,AN$5,C11:AL11) | AO11: =SUMIF($C$5:$AL$5,AO$5,C11:AL11) | AP11: =SUMIF($C$5:$AL$5,AP$5,C11:AL11) | AQ11: =SUM(C11:AL11)
A12: TOTAL COST OF SALES | C12: =SUM(C7:C11) | D12: =SUM(D7:D11) | E12: =SUM(E7:E11) | F12: =SUM(F7:F11) | G12: =SUM(G7:G11) | H12: =SUM(H7:H11) | I12: =SUM(I7:I11) | J12: =SUM(J7:J11) | ... AL12: =SUM(AL7:AL11) | AN12: =SUMIF($C$5:$AL$5,AN$5,C12:AL12) | AO12: =SUMIF($C$5:$AL$5,AO$5,C12:AL12) | AP12: =SUMIF($C$5:$AL$5,AP$5,C12:AL12) | AQ12: =SUM(C12:AL12)
A14: Total revenue | C14: ='Revenue build'!C50 | D14: ='Revenue build'!D50 | E14: ='Revenue build'!E50 | F14: ='Revenue build'!F50 | G14: ='Revenue build'!G50 | H14: ='Revenue build'!H50 | I14: ='Revenue build'!I50 | J14: ='Revenue build'!J50 | ... AL14: ='Revenue build'!AL50 | AN14: =SUMIF($C$5:$AL$5,AN$5,C14:AL14) | AO14: =SUMIF($C$5:$AL$5,AO$5,C14:AL14) | AP14: =SUMIF($C$5:$AL$5,AP$5,C14:AL14) | AQ14: =SUM(C14:AL14)
A15: GROSS PROFIT | C15: ='Cost of sales'!C14-'Cost of sales'!C12 | D15: ='Cost of sales'!D14-'Cost of sales'!D12 | E15: ='Cost of sales'!E14-'Cost of sales'!E12 | F15: ='Cost of sales'!F14-'Cost of sales'!F12 | G15: ='Cost of sales'!G14-'Cost of sales'!G12 | H15: ='Cost of sales'!H14-'Cost of sales'!H12 | I15: ='Cost of sales'!I14-'Cost of sales'!I12 | J15: ='Cost of sales'!J14-'Cost of sales'!J12 | ... AL15: ='Cost of sales'!AL14-'Cost of sales'!AL12 | AN15: =SUMIF($C$5:$AL$5,AN$5,C15:AL15) | AO15: =SUMIF($C$5:$AL$5,AO$5,C15:AL15) | AP15: =SUMIF($C$5:$AL$5,AP$5,C15:AL15) | AQ15: =SUM(C15:AL15)
A16: Gross margin % | C16: =IF('Cost of sales'!C14>0,'Cost of sales'!C15/'Cost of sales'!C14,0) | D16: =IF('Cost of sales'!D14>0,'Cost of sales'!D15/'Cost of sales'!D14,0) | E16: =IF('Cost of sales'!E14>0,'Cost of sales'!E15/'Cost of sales'!E14,0) | F16: =IF('Cost of sales'!F14>0,'Cost of sales'!F15/'Cost of sales'!F14,0) | G16: =IF('Cost of sales'!G14>0,'Cost of sales'!G15/'Cost of sales'!G14,0) | H16: =IF('Cost of sales'!H14>0,'Cost of sales'!H15/'Cost of sales'!H14,0) | I16: =IF('Cost of sales'!I14>0,'Cost of sales'!I15/'Cost of sales'!I14,0) | J16: =IF('Cost of sales'!J14>0,'Cost of sales'!J15/'Cost of sales'!J14,0) | ... AL16: =IF('Cost of sales'!AL14>0,'Cost of sales'!AL15/'Cost of sales'!AL14,0) | AN16: =IF(AN14<>0,AN15/AN14,0) | AO16: =IF(AO14<>0,AO15/AO14,0) | AP16: =IF(AP14<>0,AP15/AP14,0) | AQ16: =IF(AQ14<>0,AQ15/AQ14,0)

Sheet Opex
A1: Operating expenses
A2: ="Scenario: "&Assumptions!$D$4&" — all figures GBP, scenario values, not actuals"
A3: Month # | C3: 1 | D3: 2 | E3: 3 | F3: 4 | G3: 5 | H3: 6 | I3: 7 | J3: 8 | K3: 9 | L3: 10 | M3: 11 | N3: 12 | O3: 13 | P3: 14 | Q3: 15 | R3: 16 | S3: 17 | T3: 18 | U3: 19 | V3: 20 | W3: 21 | X3: 22 | Y3: 23 | Z3: 24 | AA3: 25 | AB3: 26 | AC3: 27 | AD3: 28 | AE3: 29 | AF3: 30 | AG3: 31 | AH3: 32 | AI3: 33 | AJ3: 34 | AK3: 35 | AL3: 36
A4: Month | C4: 46388 | D4: 46419 | E4: 46447 | F4: 46478 | G4: 46508 | H4: 46539 | I4: 46569 | J4: 46600 | K4: 46631 | L4: 46661 | M4: 46692 | N4: 46722 | O4: 46753 | P4: 46784 | Q4: 46813 | R4: 46844 | S4: 46874 | T4: 46905 | U4: 46935 | V4: 46966 | W4: 46997 | X4: 47027 | Y4: 47058 | Z4: 47088 | AA4: 47119 | AB4: 47150 | AC4: 47178 | AD4: 47209 | AE4: 47239 | AF4: 47270 | AG4: 47300 | AH4: 47331 | AI4: 47362 | AJ4: 47392 | AK4: 47423 | AL4: 47453 | AN4: FY2027 | AO4: FY2028 | AP4: FY2029 | AQ4: 3-year total
A5: Year | C5: 2027 | D5: 2027 | E5: 2027 | F5: 2027 | G5: 2027 | H5: 2027 | I5: 2027 | J5: 2027 | K5: 2027 | L5: 2027 | M5: 2027 | N5: 2027 | O5: 2028 | P5: 2028 | Q5: 2028 | R5: 2028 | S5: 2028 | T5: 2028 | U5: 2028 | V5: 2028 | W5: 2028 | X5: 2028 | Y5: 2028 | Z5: 2028 | AA5: 2029 | AB5: 2029 | AC5: 2029 | AD5: 2029 | AE5: 2029 | AF5: 2029 | AG5: 2029 | AH5: 2029 | AI5: 2029 | AJ5: 2029 | AK5: 2029 | AL5: 2029 | AN5: 2027 | AO5: 2028 | AP5: 2029
A6: Year index | C6: =C5-2026 | D6: =D5-2026 | E6: =E5-2026 | F6: =F5-2026 | G6: =G5-2026 | H6: =H5-2026 | I6: =I5-2026 | J6: =J5-2026 | ... AL6: =AL5-2026
A7: PEOPLE
A8: Founder salary | C8: ='Headcount'!C21 | D8: ='Headcount'!D21 | E8: ='Headcount'!E21 | F8: ='Headcount'!F21 | G8: ='Headcount'!G21 | H8: ='Headcount'!H21 | I8: ='Headcount'!I21 | J8: ='Headcount'!J21 | ... AL8: ='Headcount'!AL21 | AN8: =SUMIF($C$5:$AL$5,AN$5,C8:AL8) | AO8: =SUMIF($C$5:$AL$5,AO$5,C8:AL8) | AP8: =SUMIF($C$5:$AL$5,AP$5,C8:AL8) | AQ8: =SUM(C8:AL8)
A9: Employee salaries (hires) | C9: ='Headcount'!C31-'Headcount'!C21 | D9: ='Headcount'!D31-'Headcount'!D21 | E9: ='Headcount'!E31-'Headcount'!E21 | F9: ='Headcount'!F31-'Headcount'!F21 | G9: ='Headcount'!G31-'Headcount'!G21 | H9: ='Headcount'!H31-'Headcount'!H21 | I9: ='Headcount'!I31-'Headcount'!I21 | J9: ='Headcount'!J31-'Headcount'!J21 | ... AL9: ='Headcount'!AL31-'Headcount'!AL21 | AN9: =SUMIF($C$5:$AL$5,AN$5,C9:AL9) | AO9: =SUMIF($C$5:$AL$5,AO$5,C9:AL9) | AP9: =SUMIF($C$5:$AL$5,AP$5,C9:AL9) | AQ9: =SUM(C9:AL9)
A10: Employer NI (15% above secondary threshold) | C10: ='Headcount'!C44 | D10: ='Headcount'!D44 | E10: ='Headcount'!E44 | F10: ='Headcount'!F44 | G10: ='Headcount'!G44 | H10: ='Headcount'!H44 | I10: ='Headcount'!I44 | J10: ='Headcount'!J44 | ... AL10: ='Headcount'!AL44 | AN10: =SUMIF($C$5:$AL$5,AN$5,C10:AL10) | AO10: =SUMIF($C$5:$AL$5,AO$5,C10:AL10) | AP10: =SUMIF($C$5:$AL$5,AP$5,C10:AL10) | AQ10: =SUM(C10:AL10)
A11: Employer pension (3% qualifying earnings) | C11: ='Headcount'!C57 | D11: ='Headcount'!D57 | E11: ='Headcount'!E57 | F11: ='Headcount'!F57 | G11: ='Headcount'!G57 | H11: ='Headcount'!H57 | I11: ='Headcount'!I57 | J11: ='Headcount'!J57 | ... AL11: ='Headcount'!AL57 | AN11: =SUMIF($C$5:$AL$5,AN$5,C11:AL11) | AO11: =SUMIF($C$5:$AL$5,AO$5,C11:AL11) | AP11: =SUMIF($C$5:$AL$5,AP$5,C11:AL11) | AQ11: =SUM(C11:AL11)
A12: Employment Allowance credit | C12: ='Headcount'!C59 | D12: ='Headcount'!D59 | E12: ='Headcount'!E59 | F12: ='Headcount'!F59 | G12: ='Headcount'!G59 | H12: ='Headcount'!H59 | I12: ='Headcount'!I59 | J12: ='Headcount'!J59 | ... AL12: ='Headcount'!AL59 | AN12: =SUMIF($C$5:$AL$5,AN$5,C12:AL12) | AO12: =SUMIF($C$5:$AL$5,AO$5,C12:AL12) | AP12: =SUMIF($C$5:$AL$5,AP$5,C12:AL12) | AQ12: =SUM(C12:AL12)
A13: Total employment cost | C13: =SUM(C8:C12) | D13: =SUM(D8:D12) | E13: =SUM(E8:E12) | F13: =SUM(F8:F12) | G13: =SUM(G8:G12) | H13: =SUM(H8:H12) | I13: =SUM(I8:I12) | J13: =SUM(J8:J12) | ... AL13: =SUM(AL8:AL12) | AN13: =SUMIF($C$5:$AL$5,AN$5,C13:AL13) | AO13: =SUMIF($C$5:$AL$5,AO$5,C13:AL13) | AP13: =SUMIF($C$5:$AL$5,AP$5,C13:AL13) | AQ13: =SUM(C13:AL13)
A15: OTHER OPERATING COSTS
A16: Contractors (dev, design, implementation, fractional clinical safety officer) | C16: =CHOOSE(C6,Assumptions!$F$89,Assumptions!$F$90,Assumptions!$F$91) | D16: =CHOOSE(D6,Assumptions!$F$89,Assumptions!$F$90,Assumptions!$F$91) | E16: =CHOOSE(E6,Assumptions!$F$89,Assumptions!$F$90,Assumptions!$F$91) | F16: =CHOOSE(F6,Assumptions!$F$89,Assumptions!$F$90,Assumptions!$F$91) | G16: =CHOOSE(G6,Assumptions!$F$89,Assumptions!$F$90,Assumptions!$F$91) | H16: =CHOOSE(H6,Assumptions!$F$89,Assumptions!$F$90,Assumptions!$F$91) | I16: =CHOOSE(I6,Assumptions!$F$89,Assumptions!$F$90,Assumptions!$F$91) | J16: =CHOOSE(J6,Assumptions!$F$89,Assumptions!$F$90,Assumptions!$F$91) | ... AL16: =CHOOSE(AL6,Assumptions!$F$89,Assumptions!$F$90,Assumptions!$F$91) | AN16: =SUMIF($C$5:$AL$5,AN$5,C16:AL16) | AO16: =SUMIF($C$5:$AL$5,AO$5,C16:AL16) | AP16: =SUMIF($C$5:$AL$5,AP$5,C16:AL16) | AQ16: =SUM(C16:AL16)
A17: Technology (cloud, hosting, messaging, tooling) | C17: =CHOOSE(C6,Assumptions!$F$92,Assumptions!$F$93,Assumptions!$F$94) | D17: =CHOOSE(D6,Assumptions!$F$92,Assumptions!$F$93,Assumptions!$F$94) | E17: =CHOOSE(E6,Assumptions!$F$92,Assumptions!$F$93,Assumptions!$F$94) | F17: =CHOOSE(F6,Assumptions!$F$92,Assumptions!$F$93,Assumptions!$F$94) | G17: =CHOOSE(G6,Assumptions!$F$92,Assumptions!$F$93,Assumptions!$F$94) | H17: =CHOOSE(H6,Assumptions!$F$92,Assumptions!$F$93,Assumptions!$F$94) | I17: =CHOOSE(I6,Assumptions!$F$92,Assumptions!$F$93,Assumptions!$F$94) | J17: =CHOOSE(J6,Assumptions!$F$92,Assumptions!$F$93,Assumptions!$F$94) | ... AL17: =CHOOSE(AL6,Assumptions!$F$92,Assumptions!$F$93,Assumptions!$F$94) | AN17: =SUMIF($C$5:$AL$5,AN$5,C17:AL17) | AO17: =SUMIF($C$5:$AL$5,AO$5,C17:AL17) | AP17: =SUMIF($C$5:$AL$5,AP$5,C17:AL17) | AQ17: =SUM(C17:AL17)
A18: Marketing (content, events, paid tests, demand generation) | C18: =CHOOSE(C6,Assumptions!$F$95,Assumptions!$F$96,Assumptions!$F$97) | D18: =CHOOSE(D6,Assumptions!$F$95,Assumptions!$F$96,Assumptions!$F$97) | E18: =CHOOSE(E6,Assumptions!$F$95,Assumptions!$F$96,Assumptions!$F$97) | F18: =CHOOSE(F6,Assumptions!$F$95,Assumptions!$F$96,Assumptions!$F$97) | G18: =CHOOSE(G6,Assumptions!$F$95,Assumptions!$F$96,Assumptions!$F$97) | H18: =CHOOSE(H6,Assumptions!$F$95,Assumptions!$F$96,Assumptions!$F$97) | I18: =CHOOSE(I6,Assumptions!$F$95,Assumptions!$F$96,Assumptions!$F$97) | J18: =CHOOSE(J6,Assumptions!$F$95,Assumptions!$F$96,Assumptions!$F$97) | ... AL18: =CHOOSE(AL6,Assumptions!$F$95,Assumptions!$F$96,Assumptions!$F$97) | AN18: =SUMIF($C$5:$AL$5,AN$5,C18:AL18) | AO18: =SUMIF($C$5:$AL$5,AO$5,C18:AL18) | AP18: =SUMIF($C$5:$AL$5,AP$5,C18:AL18) | AQ18: =SUM(C18:AL18)
A19: Legal (ongoing contracts, IP, employment) | C19: =CHOOSE(C6,Assumptions!$F$98,Assumptions!$F$99,Assumptions!$F$100) | D19: =CHOOSE(D6,Assumptions!$F$98,Assumptions!$F$99,Assumptions!$F$100) | E19: =CHOOSE(E6,Assumptions!$F$98,Assumptions!$F$99,Assumptions!$F$100) | F19: =CHOOSE(F6,Assumptions!$F$98,Assumptions!$F$99,Assumptions!$F$100) | G19: =CHOOSE(G6,Assumptions!$F$98,Assumptions!$F$99,Assumptions!$F$100) | H19: =CHOOSE(H6,Assumptions!$F$98,Assumptions!$F$99,Assumptions!$F$100) | I19: =CHOOSE(I6,Assumptions!$F$98,Assumptions!$F$99,Assumptions!$F$100) | J19: =CHOOSE(J6,Assumptions!$F$98,Assumptions!$F$99,Assumptions!$F$100) | ... AL19: =CHOOSE(AL6,Assumptions!$F$98,Assumptions!$F$99,Assumptions!$F$100) | AN19: =SUMIF($C$5:$AL$5,AN$5,C19:AL19) | AO19: =SUMIF($C$5:$AL$5,AO$5,C19:AL19) | AP19: =SUMIF($C$5:$AL$5,AP$5,C19:AL19) | AQ19: =SUM(C19:AL19)
A20: Compliance & regulatory (ICO, Cyber Essentials, DTAC/DSPT, clinical safety) | C20: =CHOOSE(C6,Assumptions!$F$101,Assumptions!$F$102,Assumptions!$F$103) | D20: =CHOOSE(D6,Assumptions!$F$101,Assumptions!$F$102,Assumptions!$F$103) | E20: =CHOOSE(E6,Assumptions!$F$101,Assumptions!$F$102,Assumptions!$F$103) | F20: =CHOOSE(F6,Assumptions!$F$101,Assumptions!$F$102,Assumptions!$F$103) | G20: =CHOOSE(G6,Assumptions!$F$101,Assumptions!$F$102,Assumptions!$F$103) | H20: =CHOOSE(H6,Assumptions!$F$101,Assumptions!$F$102,Assumptions!$F$103) | I20: =CHOOSE(I6,Assumptions!$F$101,Assumptions!$F$102,Assumptions!$F$103) | J20: =CHOOSE(J6,Assumptions!$F$101,Assumptions!$F$102,Assumptions!$F$103) | ... AL20: =CHOOSE(AL6,Assumptions!$F$101,Assumptions!$F$102,Assumptions!$F$103) | AN20: =SUMIF($C$5:$AL$5,AN$5,C20:AL20) | AO20: =SUMIF($C$5:$AL$5,AO$5,C20:AL20) | AP20: =SUMIF($C$5:$AL$5,AP$5,C20:AL20) | AQ20: =SUM(C20:AL20)
A21: Insurance (PI, PL, D&O, cyber) | C21: =CHOOSE(C6,Assumptions!$F$104,Assumptions!$F$105,Assumptions!$F$106) | D21: =CHOOSE(D6,Assumptions!$F$104,Assumptions!$F$105,Assumptions!$F$106) | E21: =CHOOSE(E6,Assumptions!$F$104,Assumptions!$F$105,Assumptions!$F$106) | F21: =CHOOSE(F6,Assumptions!$F$104,Assumptions!$F$105,Assumptions!$F$106) | G21: =CHOOSE(G6,Assumptions!$F$104,Assumptions!$F$105,Assumptions!$F$106) | H21: =CHOOSE(H6,Assumptions!$F$104,Assumptions!$F$105,Assumptions!$F$106) | I21: =CHOOSE(I6,Assumptions!$F$104,Assumptions!$F$105,Assumptions!$F$106) | J21: =CHOOSE(J6,Assumptions!$F$104,Assumptions!$F$105,Assumptions!$F$106) | ... AL21: =CHOOSE(AL6,Assumptions!$F$104,Assumptions!$F$105,Assumptions!$F$106) | AN21: =SUMIF($C$5:$AL$5,AN$5,C21:AL21) | AO21: =SUMIF($C$5:$AL$5,AO$5,C21:AL21) | AP21: =SUMIF($C$5:$AL$5,AP$5,C21:AL21) | AQ21: =SUM(C21:AL21)
A22: Software subscriptions | C22: =CHOOSE(C6,Assumptions!$F$107,Assumptions!$F$108,Assumptions!$F$109) | D22: =CHOOSE(D6,Assumptions!$F$107,Assumptions!$F$108,Assumptions!$F$109) | E22: =CHOOSE(E6,Assumptions!$F$107,Assumptions!$F$108,Assumptions!$F$109) | F22: =CHOOSE(F6,Assumptions!$F$107,Assumptions!$F$108,Assumptions!$F$109) | G22: =CHOOSE(G6,Assumptions!$F$107,Assumptions!$F$108,Assumptions!$F$109) | H22: =CHOOSE(H6,Assumptions!$F$107,Assumptions!$F$108,Assumptions!$F$109) | I22: =CHOOSE(I6,Assumptions!$F$107,Assumptions!$F$108,Assumptions!$F$109) | J22: =CHOOSE(J6,Assumptions!$F$107,Assumptions!$F$108,Assumptions!$F$109) | ... AL22: =CHOOSE(AL6,Assumptions!$F$107,Assumptions!$F$108,Assumptions!$F$109) | AN22: =SUMIF($C$5:$AL$5,AN$5,C22:AL22) | AO22: =SUMIF($C$5:$AL$5,AO$5,C22:AL22) | AP22: =SUMIF($C$5:$AL$5,AP$5,C22:AL22) | AQ22: =SUM(C22:AL22)
A23: Travel (UK and Nigeria) | C23: =CHOOSE(C6,Assumptions!$F$110,Assumptions!$F$111,Assumptions!$F$112) | D23: =CHOOSE(D6,Assumptions!$F$110,Assumptions!$F$111,Assumptions!$F$112) | E23: =CHOOSE(E6,Assumptions!$F$110,Assumptions!$F$111,Assumptions!$F$112) | F23: =CHOOSE(F6,Assumptions!$F$110,Assumptions!$F$111,Assumptions!$F$112) | G23: =CHOOSE(G6,Assumptions!$F$110,Assumptions!$F$111,Assumptions!$F$112) | H23: =CHOOSE(H6,Assumptions!$F$110,Assumptions!$F$111,Assumptions!$F$112) | I23: =CHOOSE(I6,Assumptions!$F$110,Assumptions!$F$111,Assumptions!$F$112) | J23: =CHOOSE(J6,Assumptions!$F$110,Assumptions!$F$111,Assumptions!$F$112) | ... AL23: =CHOOSE(AL6,Assumptions!$F$110,Assumptions!$F$111,Assumptions!$F$112) | AN23: =SUMIF($C$5:$AL$5,AN$5,C23:AL23) | AO23: =SUMIF($C$5:$AL$5,AO$5,C23:AL23) | AP23: =SUMIF($C$5:$AL$5,AP$5,C23:AL23) | AQ23: =SUM(C23:AL23)
A24: Operations (co-working, recruitment, in-country field support, misc.) | C24: =CHOOSE(C6,Assumptions!$F$113,Assumptions!$F$114,Assumptions!$F$115) | D24: =CHOOSE(D6,Assumptions!$F$113,Assumptions!$F$114,Assumptions!$F$115) | E24: =CHOOSE(E6,Assumptions!$F$113,Assumptions!$F$114,Assumptions!$F$115) | F24: =CHOOSE(F6,Assumptions!$F$113,Assumptions!$F$114,Assumptions!$F$115) | G24: =CHOOSE(G6,Assumptions!$F$113,Assumptions!$F$114,Assumptions!$F$115) | H24: =CHOOSE(H6,Assumptions!$F$113,Assumptions!$F$114,Assumptions!$F$115) | I24: =CHOOSE(I6,Assumptions!$F$113,Assumptions!$F$114,Assumptions!$F$115) | J24: =CHOOSE(J6,Assumptions!$F$113,Assumptions!$F$114,Assumptions!$F$115) | ... AL24: =CHOOSE(AL6,Assumptions!$F$113,Assumptions!$F$114,Assumptions!$F$115) | AN24: =SUMIF($C$5:$AL$5,AN$5,C24:AL24) | AO24: =SUMIF($C$5:$AL$5,AO$5,C24:AL24) | AP24: =SUMIF($C$5:$AL$5,AP$5,C24:AL24) | AQ24: =SUM(C24:AL24)
A25: Accountancy, payroll, company secretarial | C25: =CHOOSE(C6,Assumptions!$F$116,Assumptions!$F$117,Assumptions!$F$118) | D25: =CHOOSE(D6,Assumptions!$F$116,Assumptions!$F$117,Assumptions!$F$118) | E25: =CHOOSE(E6,Assumptions!$F$116,Assumptions!$F$117,Assumptions!$F$118) | F25: =CHOOSE(F6,Assumptions!$F$116,Assumptions!$F$117,Assumptions!$F$118) | G25: =CHOOSE(G6,Assumptions!$F$116,Assumptions!$F$117,Assumptions!$F$118) | H25: =CHOOSE(H6,Assumptions!$F$116,Assumptions!$F$117,Assumptions!$F$118) | I25: =CHOOSE(I6,Assumptions!$F$116,Assumptions!$F$117,Assumptions!$F$118) | J25: =CHOOSE(J6,Assumptions!$F$116,Assumptions!$F$117,Assumptions!$F$118) | ... AL25: =CHOOSE(AL6,Assumptions!$F$116,Assumptions!$F$117,Assumptions!$F$118) | AN25: =SUMIF($C$5:$AL$5,AN$5,C25:AL25) | AO25: =SUMIF($C$5:$AL$5,AO$5,C25:AL25) | AP25: =SUMIF($C$5:$AL$5,AP$5,C25:AL25) | AQ25: =SUM(C25:AL25)
A26: Legal & IP set-up (one-off) | C26: =IF(C3=1,Assumptions!$F$119,0) | D26: =IF(D3=1,Assumptions!$F$119,0) | E26: =IF(E3=1,Assumptions!$F$119,0) | F26: =IF(F3=1,Assumptions!$F$119,0) | G26: =IF(G3=1,Assumptions!$F$119,0) | H26: =IF(H3=1,Assumptions!$F$119,0) | I26: =IF(I3=1,Assumptions!$F$119,0) | J26: =IF(J3=1,Assumptions!$F$119,0) | ... AL26: =IF(AL3=1,Assumptions!$F$119,0) | AN26: =SUMIF($C$5:$AL$5,AN$5,C26:AL26) | AO26: =SUMIF($C$5:$AL$5,AO$5,C26:AL26) | AP26: =SUMIF($C$5:$AL$5,AP$5,C26:AL26) | AQ26: =SUM(C26:AL26)
A27: E-learning content build (one-off at launch) | C27: =IF(C3=Assumptions!$F$33,Assumptions!$F$42,0) | D27: =IF(D3=Assumptions!$F$33,Assumptions!$F$42,0) | E27: =IF(E3=Assumptions!$F$33,Assumptions!$F$42,0) | F27: =IF(F3=Assumptions!$F$33,Assumptions!$F$42,0) | G27: =IF(G3=Assumptions!$F$33,Assumptions!$F$42,0) | H27: =IF(H3=Assumptions!$F$33,Assumptions!$F$42,0) | I27: =IF(I3=Assumptions!$F$33,Assumptions!$F$42,0) | J27: =IF(J3=Assumptions!$F$33,Assumptions!$F$42,0) | ... AL27: =IF(AL3=Assumptions!$F$33,Assumptions!$F$42,0) | AN27: =SUMIF($C$5:$AL$5,AN$5,C27:AL27) | AO27: =SUMIF($C$5:$AL$5,AO$5,C27:AL27) | AP27: =SUMIF($C$5:$AL$5,AP$5,C27:AL27) | AQ27: =SUM(C27:AL27)
A28: Total other operating costs | C28: =SUM(C16:C27) | D28: =SUM(D16:D27) | E28: =SUM(E16:E27) | F28: =SUM(F16:F27) | G28: =SUM(G16:G27) | H28: =SUM(H16:H27) | I28: =SUM(I16:I27) | J28: =SUM(J16:J27) | ... AL28: =SUM(AL16:AL27) | AN28: =SUMIF($C$5:$AL$5,AN$5,C28:AL28) | AO28: =SUMIF($C$5:$AL$5,AO$5,C28:AL28) | AP28: =SUMIF($C$5:$AL$5,AP$5,C28:AL28) | AQ28: =SUM(C28:AL28)
A30: TOTAL OPERATING EXPENSES | C30: ='Opex'!C13+'Opex'!C28 | D30: ='Opex'!D13+'Opex'!D28 | E30: ='Opex'!E13+'Opex'!E28 | F30: ='Opex'!F13+'Opex'!F28 | G30: ='Opex'!G13+'Opex'!G28 | H30: ='Opex'!H13+'Opex'!H28 | I30: ='Opex'!I13+'Opex'!I28 | J30: ='Opex'!J13+'Opex'!J28 | ... AL30: ='Opex'!AL13+'Opex'!AL28 | AN30: =SUMIF($C$5:$AL$5,AN$5,C30:AL30) | AO30: =SUMIF($C$5:$AL$5,AO$5,C30:AL30) | AP30: =SUMIF($C$5:$AL$5,AP$5,C30:AL30) | AQ30: =SUM(C30:AL30)

Sheet Headcount
A1: Headcount and payroll (employer NI 15% above £5,000; pension 3% of qualifying earnings)
A2: ="Scenario: "&Assumptions!$D$4&" — all figures GBP, scenario values, not actuals"
A3: Month # | C3: 1 | D3: 2 | E3: 3 | F3: 4 | G3: 5 | H3: 6 | I3: 7 | J3: 8 | K3: 9 | L3: 10 | M3: 11 | N3: 12 | O3: 13 | P3: 14 | Q3: 15 | R3: 16 | S3: 17 | T3: 18 | U3: 19 | V3: 20 | W3: 21 | X3: 22 | Y3: 23 | Z3: 24 | AA3: 25 | AB3: 26 | AC3: 27 | AD3: 28 | AE3: 29 | AF3: 30 | AG3: 31 | AH3: 32 | AI3: 33 | AJ3: 34 | AK3: 35 | AL3: 36
A4: Month | C4: 46388 | D4: 46419 | E4: 46447 | F4: 46478 | G4: 46508 | H4: 46539 | I4: 46569 | J4: 46600 | K4: 46631 | L4: 46661 | M4: 46692 | N4: 46722 | O4: 46753 | P4: 46784 | Q4: 46813 | R4: 46844 | S4: 46874 | T4: 46905 | U4: 46935 | V4: 46966 | W4: 46997 | X4: 47027 | Y4: 47058 | Z4: 47088 | AA4: 47119 | AB4: 47150 | AC4: 47178 | AD4: 47209 | AE4: 47239 | AF4: 47270 | AG4: 47300 | AH4: 47331 | AI4: 47362 | AJ4: 47392 | AK4: 47423 | AL4: 47453 | AN4: FY2027 | AO4: FY2028 | AP4: FY2029 | AQ4: 3-year total
A5: Year | C5: 2027 | D5: 2027 | E5: 2027 | F5: 2027 | G5: 2027 | H5: 2027 | I5: 2027 | J5: 2027 | K5: 2027 | L5: 2027 | M5: 2027 | N5: 2027 | O5: 2028 | P5: 2028 | Q5: 2028 | R5: 2028 | S5: 2028 | T5: 2028 | U5: 2028 | V5: 2028 | W5: 2028 | X5: 2028 | Y5: 2028 | Z5: 2028 | AA5: 2029 | AB5: 2029 | AC5: 2029 | AD5: 2029 | AE5: 2029 | AF5: 2029 | AG5: 2029 | AH5: 2029 | AI5: 2029 | AJ5: 2029 | AK5: 2029 | AL5: 2029 | AN5: 2027 | AO5: 2028 | AP5: 2029
A6: Year index | C6: =C5-2026 | D6: =D5-2026 | E6: =E5-2026 | F6: =F5-2026 | G6: =G5-2026 | H6: =H5-2026 | I6: =I5-2026 | J6: =J5-2026 | ... AL6: =AL5-2026
A7: HEADCOUNT FLAGS (1 = employed in month)
A8: Founder | C8: =IF(C3>=Assumptions!$F$68,1,0) | D8: =IF(D3>=Assumptions!$F$68,1,0) | E8: =IF(E3>=Assumptions!$F$68,1,0) | F8: =IF(F3>=Assumptions!$F$68,1,0) | G8: =IF(G3>=Assumptions!$F$68,1,0) | H8: =IF(H3>=Assumptions!$F$68,1,0) | I8: =IF(I3>=Assumptions!$F$68,1,0) | J8: =IF(J3>=Assumptions!$F$68,1,0) | ... AL8: =IF(AL3>=Assumptions!$F$68,1,0) | AN8: =INDEX(C8:AL8,1,12) | AO8: =INDEX(C8:AL8,1,24) | AP8: =INDEX(C8:AL8,1,36) | AQ8: =INDEX(C8:AL8,1,36)
A9: Product lead / CTO | C9: =IF(C3>=Assumptions!$F$70,1,0) | D9: =IF(D3>=Assumptions!$F$70,1,0) | E9: =IF(E3>=Assumptions!$F$70,1,0) | F9: =IF(F3>=Assumptions!$F$70,1,0) | G9: =IF(G3>=Assumptions!$F$70,1,0) | H9: =IF(H3>=Assumptions!$F$70,1,0) | I9: =IF(I3>=Assumptions!$F$70,1,0) | J9: =IF(J3>=Assumptions!$F$70,1,0) | ... AL9: =IF(AL3>=Assumptions!$F$70,1,0) | AN9: =INDEX(C9:AL9,1,12) | AO9: =INDEX(C9:AL9,1,24) | AP9: =INDEX(C9:AL9,1,36) | AQ9: =INDEX(C9:AL9,1,36)
A10: Developer 1 | C10: =IF(C3>=Assumptions!$F$72,1,0) | D10: =IF(D3>=Assumptions!$F$72,1,0) | E10: =IF(E3>=Assumptions!$F$72,1,0) | F10: =IF(F3>=Assumptions!$F$72,1,0) | G10: =IF(G3>=Assumptions!$F$72,1,0) | H10: =IF(H3>=Assumptions!$F$72,1,0) | I10: =IF(I3>=Assumptions!$F$72,1,0) | J10: =IF(J3>=Assumptions!$F$72,1,0) | ... AL10: =IF(AL3>=Assumptions!$F$72,1,0) | AN10: =INDEX(C10:AL10,1,12) | AO10: =INDEX(C10:AL10,1,24) | AP10: =INDEX(C10:AL10,1,36) | AQ10: =INDEX(C10:AL10,1,36)
A11: Developer 2 | C11: =IF(C3>=Assumptions!$F$74,1,0) | D11: =IF(D3>=Assumptions!$F$74,1,0) | E11: =IF(E3>=Assumptions!$F$74,1,0) | F11: =IF(F3>=Assumptions!$F$74,1,0) | G11: =IF(G3>=Assumptions!$F$74,1,0) | H11: =IF(H3>=Assumptions!$F$74,1,0) | I11: =IF(I3>=Assumptions!$F$74,1,0) | J11: =IF(J3>=Assumptions!$F$74,1,0) | ... AL11: =IF(AL3>=Assumptions!$F$74,1,0) | AN11: =INDEX(C11:AL11,1,12) | AO11: =INDEX(C11:AL11,1,24) | AP11: =INDEX(C11:AL11,1,36) | AQ11: =INDEX(C11:AL11,1,36)
A12: Developer 3 | C12: =IF(C3>=Assumptions!$F$76,1,0) | D12: =IF(D3>=Assumptions!$F$76,1,0) | E12: =IF(E3>=Assumptions!$F$76,1,0) | F12: =IF(F3>=Assumptions!$F$76,1,0) | G12: =IF(G3>=Assumptions!$F$76,1,0) | H12: =IF(H3>=Assumptions!$F$76,1,0) | I12: =IF(I3>=Assumptions!$F$76,1,0) | J12: =IF(J3>=Assumptions!$F$76,1,0) | ... AL12: =IF(AL3>=Assumptions!$F$76,1,0) | AN12: =INDEX(C12:AL12,1,12) | AO12: =INDEX(C12:AL12,1,24) | AP12: =INDEX(C12:AL12,1,36) | AQ12: =INDEX(C12:AL12,1,36)
A13: BD / sales lead | C13: =IF(C3>=Assumptions!$F$78,1,0) | D13: =IF(D3>=Assumptions!$F$78,1,0) | E13: =IF(E3>=Assumptions!$F$78,1,0) | F13: =IF(F3>=Assumptions!$F$78,1,0) | G13: =IF(G3>=Assumptions!$F$78,1,0) | H13: =IF(H3>=Assumptions!$F$78,1,0) | I13: =IF(I3>=Assumptions!$F$78,1,0) | J13: =IF(J3>=Assumptions!$F$78,1,0) | ... AL13: =IF(AL3>=Assumptions!$F$78,1,0) | AN13: =INDEX(C13:AL13,1,12) | AO13: =INDEX(C13:AL13,1,24) | AP13: =INDEX(C13:AL13,1,36) | AQ13: =INDEX(C13:AL13,1,36)
A14: Programme manager (Nigeria) | C14: =IF(C3>=Assumptions!$F$80,1,0) | D14: =IF(D3>=Assumptions!$F$80,1,0) | E14: =IF(E3>=Assumptions!$F$80,1,0) | F14: =IF(F3>=Assumptions!$F$80,1,0) | G14: =IF(G3>=Assumptions!$F$80,1,0) | H14: =IF(H3>=Assumptions!$F$80,1,0) | I14: =IF(I3>=Assumptions!$F$80,1,0) | J14: =IF(J3>=Assumptions!$F$80,1,0) | ... AL14: =IF(AL3>=Assumptions!$F$80,1,0) | AN14: =INDEX(C14:AL14,1,12) | AO14: =INDEX(C14:AL14,1,24) | AP14: =INDEX(C14:AL14,1,36) | AQ14: =INDEX(C14:AL14,1,36)
A15: Clinical lead (midwife/obstetrician) | C15: =IF(C3>=Assumptions!$F$82,1,0) | D15: =IF(D3>=Assumptions!$F$82,1,0) | E15: =IF(E3>=Assumptions!$F$82,1,0) | F15: =IF(F3>=Assumptions!$F$82,1,0) | G15: =IF(G3>=Assumptions!$F$82,1,0) | H15: =IF(H3>=Assumptions!$F$82,1,0) | I15: =IF(I3>=Assumptions!$F$82,1,0) | J15: =IF(J3>=Assumptions!$F$82,1,0) | ... AL15: =IF(AL3>=Assumptions!$F$82,1,0) | AN15: =INDEX(C15:AL15,1,12) | AO15: =INDEX(C15:AL15,1,24) | AP15: =INDEX(C15:AL15,1,36) | AQ15: =INDEX(C15:AL15,1,36)
A16: E-learning content lead | C16: =IF(C3>=Assumptions!$F$84,1,0) | D16: =IF(D3>=Assumptions!$F$84,1,0) | E16: =IF(E3>=Assumptions!$F$84,1,0) | F16: =IF(F3>=Assumptions!$F$84,1,0) | G16: =IF(G3>=Assumptions!$F$84,1,0) | H16: =IF(H3>=Assumptions!$F$84,1,0) | I16: =IF(I3>=Assumptions!$F$84,1,0) | J16: =IF(J3>=Assumptions!$F$84,1,0) | ... AL16: =IF(AL3>=Assumptions!$F$84,1,0) | AN16: =INDEX(C16:AL16,1,12) | AO16: =INDEX(C16:AL16,1,24) | AP16: =INDEX(C16:AL16,1,36) | AQ16: =INDEX(C16:AL16,1,36)
A17: Senior consultant (billable) | C17: =IF(C3>=Assumptions!$F$86,1,0) | D17: =IF(D3>=Assumptions!$F$86,1,0) | E17: =IF(E3>=Assumptions!$F$86,1,0) | F17: =IF(F3>=Assumptions!$F$86,1,0) | G17: =IF(G3>=Assumptions!$F$86,1,0) | H17: =IF(H3>=Assumptions!$F$86,1,0) | I17: =IF(I3>=Assumptions!$F$86,1,0) | J17: =IF(J3>=Assumptions!$F$86,1,0) | ... AL17: =IF(AL3>=Assumptions!$F$86,1,0) | AN17: =INDEX(C17:AL17,1,12) | AO17: =INDEX(C17:AL17,1,24) | AP17: =INDEX(C17:AL17,1,36) | AQ17: =INDEX(C17:AL17,1,36)
A18: TOTAL HEADCOUNT | C18: =SUM(C8:C17) | D18: =SUM(D8:D17) | E18: =SUM(E8:E17) | F18: =SUM(F8:F17) | G18: =SUM(G8:G17) | H18: =SUM(H8:H17) | I18: =SUM(I8:I17) | J18: =SUM(J8:J17) | ... AL18: =SUM(AL8:AL17) | AN18: =INDEX(C18:AL18,1,12) | AO18: =INDEX(C18:AL18,1,24) | AP18: =INDEX(C18:AL18,1,36) | AQ18: =INDEX(C18:AL18,1,36)
A20: GROSS SALARIES (monthly)
A21: Founder | C21: ='Headcount'!C8*Assumptions!$C$134/12 | D21: ='Headcount'!D8*Assumptions!$C$134/12 | E21: ='Headcount'!E8*Assumptions!$C$134/12 | F21: ='Headcount'!F8*Assumptions!$C$134/12 | G21: ='Headcount'!G8*Assumptions!$C$134/12 | H21: ='Headcount'!H8*Assumptions!$C$134/12 | I21: ='Headcount'!I8*Assumptions!$C$134/12 | J21: ='Headcount'!J8*Assumptions!$C$134/12 | ... AL21: ='Headcount'!AL8*Assumptions!$C$134/12 | AN21: =SUMIF($C$5:$AL$5,AN$5,C21:AL21) | AO21: =SUMIF($C$5:$AL$5,AO$5,C21:AL21) | AP21: =SUMIF($C$5:$AL$5,AP$5,C21:AL21) | AQ21: =SUM(C21:AL21)
A22: Product lead / CTO | C22: ='Headcount'!C9*Assumptions!$C$135/12 | D22: ='Headcount'!D9*Assumptions!$C$135/12 | E22: ='Headcount'!E9*Assumptions!$C$135/12 | F22: ='Headcount'!F9*Assumptions!$C$135/12 | G22: ='Headcount'!G9*Assumptions!$C$135/12 | H22: ='Headcount'!H9*Assumptions!$C$135/12 | I22: ='Headcount'!I9*Assumptions!$C$135/12 | J22: ='Headcount'!J9*Assumptions!$C$135/12 | ... AL22: ='Headcount'!AL9*Assumptions!$C$135/12 | AN22: =SUMIF($C$5:$AL$5,AN$5,C22:AL22) | AO22: =SUMIF($C$5:$AL$5,AO$5,C22:AL22) | AP22: =SUMIF($C$5:$AL$5,AP$5,C22:AL22) | AQ22: =SUM(C22:AL22)
A23: Developer 1 | C23: ='Headcount'!C10*Assumptions!$C$136/12 | D23: ='Headcount'!D10*Assumptions!$C$136/12 | E23: ='Headcount'!E10*Assumptions!$C$136/12 | F23: ='Headcount'!F10*Assumptions!$C$136/12 | G23: ='Headcount'!G10*Assumptions!$C$136/12 | H23: ='Headcount'!H10*Assumptions!$C$136/12 | I23: ='Headcount'!I10*Assumptions!$C$136/12 | J23: ='Headcount'!J10*Assumptions!$C$136/12 | ... AL23: ='Headcount'!AL10*Assumptions!$C$136/12 | AN23: =SUMIF($C$5:$AL$5,AN$5,C23:AL23) | AO23: =SUMIF($C$5:$AL$5,AO$5,C23:AL23) | AP23: =SUMIF($C$5:$AL$5,AP$5,C23:AL23) | AQ23: =SUM(C23:AL23)
A24: Developer 2 | C24: ='Headcount'!C11*Assumptions!$C$137/12 | D24: ='Headcount'!D11*Assumptions!$C$137/12 | E24: ='Headcount'!E11*Assumptions!$C$137/12 | F24: ='Headcount'!F11*Assumptions!$C$137/12 | G24: ='Headcount'!G11*Assumptions!$C$137/12 | H24: ='Headcount'!H11*Assumptions!$C$137/12 | I24: ='Headcount'!I11*Assumptions!$C$137/12 | J24: ='Headcount'!J11*Assumptions!$C$137/12 | ... AL24: ='Headcount'!AL11*Assumptions!$C$137/12 | AN24: =SUMIF($C$5:$AL$5,AN$5,C24:AL24) | AO24: =SUMIF($C$5:$AL$5,AO$5,C24:AL24) | AP24: =SUMIF($C$5:$AL$5,AP$5,C24:AL24) | AQ24: =SUM(C24:AL24)
A25: Developer 3 | C25: ='Headcount'!C12*Assumptions!$C$138/12 | D25: ='Headcount'!D12*Assumptions!$C$138/12 | E25: ='Headcount'!E12*Assumptions!$C$138/12 | F25: ='Headcount'!F12*Assumptions!$C$138/12 | G25: ='Headcount'!G12*Assumptions!$C$138/12 | H25: ='Headcount'!H12*Assumptions!$C$138/12 | I25: ='Headcount'!I12*Assumptions!$C$138/12 | J25: ='Headcount'!J12*Assumptions!$C$138/12 | ... AL25: ='Headcount'!AL12*Assumptions!$C$138/12 | AN25: =SUMIF($C$5:$AL$5,AN$5,C25:AL25) | AO25: =SUMIF($C$5:$AL$5,AO$5,C25:AL25) | AP25: =SUMIF($C$5:$AL$5,AP$5,C25:AL25) | AQ25: =SUM(C25:AL25)
A26: BD / sales lead | C26: ='Headcount'!C13*Assumptions!$C$139/12 | D26: ='Headcount'!D13*Assumptions!$C$139/12 | E26: ='Headcount'!E13*Assumptions!$C$139/12 | F26: ='Headcount'!F13*Assumptions!$C$139/12 | G26: ='Headcount'!G13*Assumptions!$C$139/12 | H26: ='Headcount'!H13*Assumptions!$C$139/12 | I26: ='Headcount'!I13*Assumptions!$C$139/12 | J26: ='Headcount'!J13*Assumptions!$C$139/12 | ... AL26: ='Headcount'!AL13*Assumptions!$C$139/12 | AN26: =SUMIF($C$5:$AL$5,AN$5,C26:AL26) | AO26: =SUMIF($C$5:$AL$5,AO$5,C26:AL26) | AP26: =SUMIF($C$5:$AL$5,AP$5,C26:AL26) | AQ26: =SUM(C26:AL26)
A27: Programme manager (Nigeria) | C27: ='Headcount'!C14*Assumptions!$C$140/12 | D27: ='Headcount'!D14*Assumptions!$C$140/12 | E27: ='Headcount'!E14*Assumptions!$C$140/12 | F27: ='Headcount'!F14*Assumptions!$C$140/12 | G27: ='Headcount'!G14*Assumptions!$C$140/12 | H27: ='Headcount'!H14*Assumptions!$C$140/12 | I27: ='Headcount'!I14*Assumptions!$C$140/12 | J27: ='Headcount'!J14*Assumptions!$C$140/12 | ... AL27: ='Headcount'!AL14*Assumptions!$C$140/12 | AN27: =SUMIF($C$5:$AL$5,AN$5,C27:AL27) | AO27: =SUMIF($C$5:$AL$5,AO$5,C27:AL27) | AP27: =SUMIF($C$5:$AL$5,AP$5,C27:AL27) | AQ27: =SUM(C27:AL27)
A28: Clinical lead (midwife/obstetrician) | C28: ='Headcount'!C15*Assumptions!$C$141/12 | D28: ='Headcount'!D15*Assumptions!$C$141/12 | E28: ='Headcount'!E15*Assumptions!$C$141/12 | F28: ='Headcount'!F15*Assumptions!$C$141/12 | G28: ='Headcount'!G15*Assumptions!$C$141/12 | H28: ='Headcount'!H15*Assumptions!$C$141/12 | I28: ='Headcount'!I15*Assumptions!$C$141/12 | J28: ='Headcount'!J15*Assumptions!$C$141/12 | ... AL28: ='Headcount'!AL15*Assumptions!$C$141/12 | AN28: =SUMIF($C$5:$AL$5,AN$5,C28:AL28) | AO28: =SUMIF($C$5:$AL$5,AO$5,C28:AL28) | AP28: =SUMIF($C$5:$AL$5,AP$5,C28:AL28) | AQ28: =SUM(C28:AL28)
A29: E-learning content lead | C29: ='Headcount'!C16*Assumptions!$C$142/12 | D29: ='Headcount'!D16*Assumptions!$C$142/12 | E29: ='Headcount'!E16*Assumptions!$C$142/12 | F29: ='Headcount'!F16*Assumptions!$C$142/12 | G29: ='Headcount'!G16*Assumptions!$C$142/12 | H29: ='Headcount'!H16*Assumptions!$C$142/12 | I29: ='Headcount'!I16*Assumptions!$C$142/12 | J29: ='Headcount'!J16*Assumptions!$C$142/12 | ... AL29: ='Headcount'!AL16*Assumptions!$C$142/12 | AN29: =SUMIF($C$5:$AL$5,AN$5,C29:AL29) | AO29: =SUMIF($C$5:$AL$5,AO$5,C29:AL29) | AP29: =SUMIF($C$5:$AL$5,AP$5,C29:AL29) | AQ29: =SUM(C29:AL29)
A30: Senior consultant (billable) | C30: ='Headcount'!C17*Assumptions!$C$143/12 | D30: ='Headcount'!D17*Assumptions!$C$143/12 | E30: ='Headcount'!E17*Assumptions!$C$143/12 | F30: ='Headcount'!F17*Assumptions!$C$143/12 | G30: ='Headcount'!G17*Assumptions!$C$143/12 | H30: ='Headcount'!H17*Assumptions!$C$143/12 | I30: ='Headcount'!I17*Assumptions!$C$143/12 | J30: ='Headcount'!J17*Assumptions!$C$143/12 | ... AL30: ='Headcount'!AL17*Assumptions!$C$143/12 | AN30: =SUMIF($C$5:$AL$5,AN$5,C30:AL30) | AO30: =SUMIF($C$5:$AL$5,AO$5,C30:AL30) | AP30: =SUMIF($C$5:$AL$5,AP$5,C30:AL30) | AQ30: =SUM(C30:AL30)
A31: Total gross salaries | C31: =SUM(C21:C30) | D31: =SUM(D21:D30) | E31: =SUM(E21:E30) | F31: =SUM(F21:F30) | G31: =SUM(G21:G30) | H31: =SUM(H21:H30) | I31: =SUM(I21:I30) | J31: =SUM(J21:J30) | ... AL31: =SUM(AL21:AL30) | AN31: =SUMIF($C$5:$AL$5,AN$5,C31:AL31) | AO31: =SUMIF($C$5:$AL$5,AO$5,C31:AL31) | AP31: =SUMIF($C$5:$AL$5,AP$5,C31:AL31) | AQ31: =SUM(C31:AL31)
A33: EMPLOYER NATIONAL INSURANCE (monthly)
A34: Founder | C34: ='Headcount'!C8*Assumptions!$D$134/12 | D34: ='Headcount'!D8*Assumptions!$D$134/12 | E34: ='Headcount'!E8*Assumptions!$D$134/12 | F34: ='Headcount'!F8*Assumptions!$D$134/12 | G34: ='Headcount'!G8*Assumptions!$D$134/12 | H34: ='Headcount'!H8*Assumptions!$D$134/12 | I34: ='Headcount'!I8*Assumptions!$D$134/12 | J34: ='Headcount'!J8*Assumptions!$D$134/12 | ... AL34: ='Headcount'!AL8*Assumptions!$D$134/12 | AN34: =SUMIF($C$5:$AL$5,AN$5,C34:AL34) | AO34: =SUMIF($C$5:$AL$5,AO$5,C34:AL34) | AP34: =SUMIF($C$5:$AL$5,AP$5,C34:AL34) | AQ34: =SUM(C34:AL34)
A35: Product lead / CTO | C35: ='Headcount'!C9*Assumptions!$D$135/12 | D35: ='Headcount'!D9*Assumptions!$D$135/12 | E35: ='Headcount'!E9*Assumptions!$D$135/12 | F35: ='Headcount'!F9*Assumptions!$D$135/12 | G35: ='Headcount'!G9*Assumptions!$D$135/12 | H35: ='Headcount'!H9*Assumptions!$D$135/12 | I35: ='Headcount'!I9*Assumptions!$D$135/12 | J35: ='Headcount'!J9*Assumptions!$D$135/12 | ... AL35: ='Headcount'!AL9*Assumptions!$D$135/12 | AN35: =SUMIF($C$5:$AL$5,AN$5,C35:AL35) | AO35: =SUMIF($C$5:$AL$5,AO$5,C35:AL35) | AP35: =SUMIF($C$5:$AL$5,AP$5,C35:AL35) | AQ35: =SUM(C35:AL35)
A36: Developer 1 | C36: ='Headcount'!C10*Assumptions!$D$136/12 | D36: ='Headcount'!D10*Assumptions!$D$136/12 | E36: ='Headcount'!E10*Assumptions!$D$136/12 | F36: ='Headcount'!F10*Assumptions!$D$136/12 | G36: ='Headcount'!G10*Assumptions!$D$136/12 | H36: ='Headcount'!H10*Assumptions!$D$136/12 | I36: ='Headcount'!I10*Assumptions!$D$136/12 | J36: ='Headcount'!J10*Assumptions!$D$136/12 | ... AL36: ='Headcount'!AL10*Assumptions!$D$136/12 | AN36: =SUMIF($C$5:$AL$5,AN$5,C36:AL36) | AO36: =SUMIF($C$5:$AL$5,AO$5,C36:AL36) | AP36: =SUMIF($C$5:$AL$5,AP$5,C36:AL36) | AQ36: =SUM(C36:AL36)
A37: Developer 2 | C37: ='Headcount'!C11*Assumptions!$D$137/12 | D37: ='Headcount'!D11*Assumptions!$D$137/12 | E37: ='Headcount'!E11*Assumptions!$D$137/12 | F37: ='Headcount'!F11*Assumptions!$D$137/12 | G37: ='Headcount'!G11*Assumptions!$D$137/12 | H37: ='Headcount'!H11*Assumptions!$D$137/12 | I37: ='Headcount'!I11*Assumptions!$D$137/12 | J37: ='Headcount'!J11*Assumptions!$D$137/12 | ... AL37: ='Headcount'!AL11*Assumptions!$D$137/12 | AN37: =SUMIF($C$5:$AL$5,AN$5,C37:AL37) | AO37: =SUMIF($C$5:$AL$5,AO$5,C37:AL37) | AP37: =SUMIF($C$5:$AL$5,AP$5,C37:AL37) | AQ37: =SUM(C37:AL37)
A38: Developer 3 | C38: ='Headcount'!C12*Assumptions!$D$138/12 | D38: ='Headcount'!D12*Assumptions!$D$138/12 | E38: ='Headcount'!E12*Assumptions!$D$138/12 | F38: ='Headcount'!F12*Assumptions!$D$138/12 | G38: ='Headcount'!G12*Assumptions!$D$138/12 | H38: ='Headcount'!H12*Assumptions!$D$138/12 | I38: ='Headcount'!I12*Assumptions!$D$138/12 | J38: ='Headcount'!J12*Assumptions!$D$138/12 | ... AL38: ='Headcount'!AL12*Assumptions!$D$138/12 | AN38: =SUMIF($C$5:$AL$5,AN$5,C38:AL38) | AO38: =SUMIF($C$5:$AL$5,AO$5,C38:AL38) | AP38: =SUMIF($C$5:$AL$5,AP$5,C38:AL38) | AQ38: =SUM(C38:AL38)
A39: BD / sales lead | C39: ='Headcount'!C13*Assumptions!$D$139/12 | D39: ='Headcount'!D13*Assumptions!$D$139/12 | E39: ='Headcount'!E13*Assumptions!$D$139/12 | F39: ='Headcount'!F13*Assumptions!$D$139/12 | G39: ='Headcount'!G13*Assumptions!$D$139/12 | H39: ='Headcount'!H13*Assumptions!$D$139/12 | I39: ='Headcount'!I13*Assumptions!$D$139/12 | J39: ='Headcount'!J13*Assumptions!$D$139/12 | ... AL39: ='Headcount'!AL13*Assumptions!$D$139/12 | AN39: =SUMIF($C$5:$AL$5,AN$5,C39:AL39) | AO39: =SUMIF($C$5:$AL$5,AO$5,C39:AL39) | AP39: =SUMIF($C$5:$AL$5,AP$5,C39:AL39) | AQ39: =SUM(C39:AL39)
A40: Programme manager (Nigeria) | C40: ='Headcount'!C14*Assumptions!$D$140/12 | D40: ='Headcount'!D14*Assumptions!$D$140/12 | E40: ='Headcount'!E14*Assumptions!$D$140/12 | F40: ='Headcount'!F14*Assumptions!$D$140/12 | G40: ='Headcount'!G14*Assumptions!$D$140/12 | H40: ='Headcount'!H14*Assumptions!$D$140/12 | I40: ='Headcount'!I14*Assumptions!$D$140/12 | J40: ='Headcount'!J14*Assumptions!$D$140/12 | ... AL40: ='Headcount'!AL14*Assumptions!$D$140/12 | AN40: =SUMIF($C$5:$AL$5,AN$5,C40:AL40) | AO40: =SUMIF($C$5:$AL$5,AO$5,C40:AL40) | AP40: =SUMIF($C$5:$AL$5,AP$5,C40:AL40) | AQ40: =SUM(C40:AL40)
A41: Clinical lead (midwife/obstetrician) | C41: ='Headcount'!C15*Assumptions!$D$141/12 | D41: ='Headcount'!D15*Assumptions!$D$141/12 | E41: ='Headcount'!E15*Assumptions!$D$141/12 | F41: ='Headcount'!F15*Assumptions!$D$141/12 | G41: ='Headcount'!G15*Assumptions!$D$141/12 | H41: ='Headcount'!H15*Assumptions!$D$141/12 | I41: ='Headcount'!I15*Assumptions!$D$141/12 | J41: ='Headcount'!J15*Assumptions!$D$141/12 | ... AL41: ='Headcount'!AL15*Assumptions!$D$141/12 | AN41: =SUMIF($C$5:$AL$5,AN$5,C41:AL41) | AO41: =SUMIF($C$5:$AL$5,AO$5,C41:AL41) | AP41: =SUMIF($C$5:$AL$5,AP$5,C41:AL41) | AQ41: =SUM(C41:AL41)
A42: E-learning content lead | C42: ='Headcount'!C16*Assumptions!$D$142/12 | D42: ='Headcount'!D16*Assumptions!$D$142/12 | E42: ='Headcount'!E16*Assumptions!$D$142/12 | F42: ='Headcount'!F16*Assumptions!$D$142/12 | G42: ='Headcount'!G16*Assumptions!$D$142/12 | H42: ='Headcount'!H16*Assumptions!$D$142/12 | I42: ='Headcount'!I16*Assumptions!$D$142/12 | J42: ='Headcount'!J16*Assumptions!$D$142/12 | ... AL42: ='Headcount'!AL16*Assumptions!$D$142/12 | AN42: =SUMIF($C$5:$AL$5,AN$5,C42:AL42) | AO42: =SUMIF($C$5:$AL$5,AO$5,C42:AL42) | AP42: =SUMIF($C$5:$AL$5,AP$5,C42:AL42) | AQ42: =SUM(C42:AL42)
A43: Senior consultant (billable) | C43: ='Headcount'!C17*Assumptions!$D$143/12 | D43: ='Headcount'!D17*Assumptions!$D$143/12 | E43: ='Headcount'!E17*Assumptions!$D$143/12 | F43: ='Headcount'!F17*Assumptions!$D$143/12 | G43: ='Headcount'!G17*Assumptions!$D$143/12 | H43: ='Headcount'!H17*Assumptions!$D$143/12 | I43: ='Headcount'!I17*Assumptions!$D$143/12 | J43: ='Headcount'!J17*Assumptions!$D$143/12 | ... AL43: ='Headcount'!AL17*Assumptions!$D$143/12 | AN43: =SUMIF($C$5:$AL$5,AN$5,C43:AL43) | AO43: =SUMIF($C$5:$AL$5,AO$5,C43:AL43) | AP43: =SUMIF($C$5:$AL$5,AP$5,C43:AL43) | AQ43: =SUM(C43:AL43)
A44: Total employer NI (before Employment Allowance) | C44: =SUM(C34:C43) | D44: =SUM(D34:D43) | E44: =SUM(E34:E43) | F44: =SUM(F34:F43) | G44: =SUM(G34:G43) | H44: =SUM(H34:H43) | I44: =SUM(I34:I43) | J44: =SUM(J34:J43) | ... AL44: =SUM(AL34:AL43) | AN44: =SUMIF($C$5:$AL$5,AN$5,C44:AL44) | AO44: =SUMIF($C$5:$AL$5,AO$5,C44:AL44) | AP44: =SUMIF($C$5:$AL$5,AP$5,C44:AL44) | AQ44: =SUM(C44:AL44)
A46: EMPLOYER PENSION (monthly)
A47: Founder | C47: ='Headcount'!C8*Assumptions!$E$134/12 | D47: ='Headcount'!D8*Assumptions!$E$134/12 | E47: ='Headcount'!E8*Assumptions!$E$134/12 | F47: ='Headcount'!F8*Assumptions!$E$134/12 | G47: ='Headcount'!G8*Assumptions!$E$134/12 | H47: ='Headcount'!H8*Assumptions!$E$134/12 | I47: ='Headcount'!I8*Assumptions!$E$134/12 | J47: ='Headcount'!J8*Assumptions!$E$134/12 | ... AL47: ='Headcount'!AL8*Assumptions!$E$134/12 | AN47: =SUMIF($C$5:$AL$5,AN$5,C47:AL47) | AO47: =SUMIF($C$5:$AL$5,AO$5,C47:AL47) | AP47: =SUMIF($C$5:$AL$5,AP$5,C47:AL47) | AQ47: =SUM(C47:AL47)
A48: Product lead / CTO | C48: ='Headcount'!C9*Assumptions!$E$135/12 | D48: ='Headcount'!D9*Assumptions!$E$135/12 | E48: ='Headcount'!E9*Assumptions!$E$135/12 | F48: ='Headcount'!F9*Assumptions!$E$135/12 | G48: ='Headcount'!G9*Assumptions!$E$135/12 | H48: ='Headcount'!H9*Assumptions!$E$135/12 | I48: ='Headcount'!I9*Assumptions!$E$135/12 | J48: ='Headcount'!J9*Assumptions!$E$135/12 | ... AL48: ='Headcount'!AL9*Assumptions!$E$135/12 | AN48: =SUMIF($C$5:$AL$5,AN$5,C48:AL48) | AO48: =SUMIF($C$5:$AL$5,AO$5,C48:AL48) | AP48: =SUMIF($C$5:$AL$5,AP$5,C48:AL48) | AQ48: =SUM(C48:AL48)
A49: Developer 1 | C49: ='Headcount'!C10*Assumptions!$E$136/12 | D49: ='Headcount'!D10*Assumptions!$E$136/12 | E49: ='Headcount'!E10*Assumptions!$E$136/12 | F49: ='Headcount'!F10*Assumptions!$E$136/12 | G49: ='Headcount'!G10*Assumptions!$E$136/12 | H49: ='Headcount'!H10*Assumptions!$E$136/12 | I49: ='Headcount'!I10*Assumptions!$E$136/12 | J49: ='Headcount'!J10*Assumptions!$E$136/12 | ... AL49: ='Headcount'!AL10*Assumptions!$E$136/12 | AN49: =SUMIF($C$5:$AL$5,AN$5,C49:AL49) | AO49: =SUMIF($C$5:$AL$5,AO$5,C49:AL49) | AP49: =SUMIF($C$5:$AL$5,AP$5,C49:AL49) | AQ49: =SUM(C49:AL49)
A50: Developer 2 | C50: ='Headcount'!C11*Assumptions!$E$137/12 | D50: ='Headcount'!D11*Assumptions!$E$137/12 | E50: ='Headcount'!E11*Assumptions!$E$137/12 | F50: ='Headcount'!F11*Assumptions!$E$137/12 | G50: ='Headcount'!G11*Assumptions!$E$137/12 | H50: ='Headcount'!H11*Assumptions!$E$137/12 | I50: ='Headcount'!I11*Assumptions!$E$137/12 | J50: ='Headcount'!J11*Assumptions!$E$137/12 | ... AL50: ='Headcount'!AL11*Assumptions!$E$137/12 | AN50: =SUMIF($C$5:$AL$5,AN$5,C50:AL50) | AO50: =SUMIF($C$5:$AL$5,AO$5,C50:AL50) | AP50: =SUMIF($C$5:$AL$5,AP$5,C50:AL50) | AQ50: =SUM(C50:AL50)
A51: Developer 3 | C51: ='Headcount'!C12*Assumptions!$E$138/12 | D51: ='Headcount'!D12*Assumptions!$E$138/12 | E51: ='Headcount'!E12*Assumptions!$E$138/12 | F51: ='Headcount'!F12*Assumptions!$E$138/12 | G51: ='Headcount'!G12*Assumptions!$E$138/12 | H51: ='Headcount'!H12*Assumptions!$E$138/12 | I51: ='Headcount'!I12*Assumptions!$E$138/12 | J51: ='Headcount'!J12*Assumptions!$E$138/12 | ... AL51: ='Headcount'!AL12*Assumptions!$E$138/12 | AN51: =SUMIF($C$5:$AL$5,AN$5,C51:AL51) | AO51: =SUMIF($C$5:$AL$5,AO$5,C51:AL51) | AP51: =SUMIF($C$5:$AL$5,AP$5,C51:AL51) | AQ51: =SUM(C51:AL51)
A52: BD / sales lead | C52: ='Headcount'!C13*Assumptions!$E$139/12 | D52: ='Headcount'!D13*Assumptions!$E$139/12 | E52: ='Headcount'!E13*Assumptions!$E$139/12 | F52: ='Headcount'!F13*Assumptions!$E$139/12 | G52: ='Headcount'!G13*Assumptions!$E$139/12 | H52: ='Headcount'!H13*Assumptions!$E$139/12 | I52: ='Headcount'!I13*Assumptions!$E$139/12 | J52: ='Headcount'!J13*Assumptions!$E$139/12 | ... AL52: ='Headcount'!AL13*Assumptions!$E$139/12 | AN52: =SUMIF($C$5:$AL$5,AN$5,C52:AL52) | AO52: =SUMIF($C$5:$AL$5,AO$5,C52:AL52) | AP52: =SUMIF($C$5:$AL$5,AP$5,C52:AL52) | AQ52: =SUM(C52:AL52)
A53: Programme manager (Nigeria) | C53: ='Headcount'!C14*Assumptions!$E$140/12 | D53: ='Headcount'!D14*Assumptions!$E$140/12 | E53: ='Headcount'!E14*Assumptions!$E$140/12 | F53: ='Headcount'!F14*Assumptions!$E$140/12 | G53: ='Headcount'!G14*Assumptions!$E$140/12 | H53: ='Headcount'!H14*Assumptions!$E$140/12 | I53: ='Headcount'!I14*Assumptions!$E$140/12 | J53: ='Headcount'!J14*Assumptions!$E$140/12 | ... AL53: ='Headcount'!AL14*Assumptions!$E$140/12 | AN53: =SUMIF($C$5:$AL$5,AN$5,C53:AL53) | AO53: =SUMIF($C$5:$AL$5,AO$5,C53:AL53) | AP53: =SUMIF($C$5:$AL$5,AP$5,C53:AL53) | AQ53: =SUM(C53:AL53)
A54: Clinical lead (midwife/obstetrician) | C54: ='Headcount'!C15*Assumptions!$E$141/12 | D54: ='Headcount'!D15*Assumptions!$E$141/12 | E54: ='Headcount'!E15*Assumptions!$E$141/12 | F54: ='Headcount'!F15*Assumptions!$E$141/12 | G54: ='Headcount'!G15*Assumptions!$E$141/12 | H54: ='Headcount'!H15*Assumptions!$E$141/12 | I54: ='Headcount'!I15*Assumptions!$E$141/12 | J54: ='Headcount'!J15*Assumptions!$E$141/12 | ... AL54: ='Headcount'!AL15*Assumptions!$E$141/12 | AN54: =SUMIF($C$5:$AL$5,AN$5,C54:AL54) | AO54: =SUMIF($C$5:$AL$5,AO$5,C54:AL54) | AP54: =SUMIF($C$5:$AL$5,AP$5,C54:AL54) | AQ54: =SUM(C54:AL54)
A55: E-learning content lead | C55: ='Headcount'!C16*Assumptions!$E$142/12 | D55: ='Headcount'!D16*Assumptions!$E$142/12 | E55: ='Headcount'!E16*Assumptions!$E$142/12 | F55: ='Headcount'!F16*Assumptions!$E$142/12 | G55: ='Headcount'!G16*Assumptions!$E$142/12 | H55: ='Headcount'!H16*Assumptions!$E$142/12 | I55: ='Headcount'!I16*Assumptions!$E$142/12 | J55: ='Headcount'!J16*Assumptions!$E$142/12 | ... AL55: ='Headcount'!AL16*Assumptions!$E$142/12 | AN55: =SUMIF($C$5:$AL$5,AN$5,C55:AL55) | AO55: =SUMIF($C$5:$AL$5,AO$5,C55:AL55) | AP55: =SUMIF($C$5:$AL$5,AP$5,C55:AL55) | AQ55: =SUM(C55:AL55)
A56: Senior consultant (billable) | C56: ='Headcount'!C17*Assumptions!$E$143/12 | D56: ='Headcount'!D17*Assumptions!$E$143/12 | E56: ='Headcount'!E17*Assumptions!$E$143/12 | F56: ='Headcount'!F17*Assumptions!$E$143/12 | G56: ='Headcount'!G17*Assumptions!$E$143/12 | H56: ='Headcount'!H17*Assumptions!$E$143/12 | I56: ='Headcount'!I17*Assumptions!$E$143/12 | J56: ='Headcount'!J17*Assumptions!$E$143/12 | ... AL56: ='Headcount'!AL17*Assumptions!$E$143/12 | AN56: =SUMIF($C$5:$AL$5,AN$5,C56:AL56) | AO56: =SUMIF($C$5:$AL$5,AO$5,C56:AL56) | AP56: =SUMIF($C$5:$AL$5,AP$5,C56:AL56) | AQ56: =SUM(C56:AL56)
A57: Total employer pension | C57: =SUM(C47:C56) | D57: =SUM(D47:D56) | E57: =SUM(E47:E56) | F57: =SUM(F47:F56) | G57: =SUM(G47:G56) | H57: =SUM(H47:H56) | I57: =SUM(I47:I56) | J57: =SUM(J47:J56) | ... AL57: =SUM(AL47:AL56) | AN57: =SUMIF($C$5:$AL$5,AN$5,C57:AL57) | AO57: =SUMIF($C$5:$AL$5,AO$5,C57:AL57) | AP57: =SUMIF($C$5:$AL$5,AP$5,C57:AL57) | AQ57: =SUM(C57:AL57)
A59: Employment Allowance credit (once headcount ≥ 2) | C59: =-MIN('Headcount'!C44,IF('Headcount'!C18>=2,Assumptions!$F$63/12,0)) | D59: =-MIN('Headcount'!D44,IF('Headcount'!D18>=2,Assumptions!$F$63/12,0)) | E59: =-MIN('Headcount'!E44,IF('Headcount'!E18>=2,Assumptions!$F$63/12,0)) | F59: =-MIN('Headcount'!F44,IF('Headcount'!F18>=2,Assumptions!$F$63/12,0)) | G59: =-MIN('Headcount'!G44,IF('Headcount'!G18>=2,Assumptions!$F$63/12,0)) | H59: =-MIN('Headcount'!H44,IF('Headcount'!H18>=2,Assumptions!$F$63/12,0)) | I59: =-MIN('Headcount'!I44,IF('Headcount'!I18>=2,Assumptions!$F$63/12,0)) | J59: =-MIN('Headcount'!J44,IF('Headcount'!J18>=2,Assumptions!$F$63/12,0)) | ... AL59: =-MIN('Headcount'!AL44,IF('Headcount'!AL18>=2,Assumptions!$F$63/12,0)) | AN59: =SUMIF($C$5:$AL$5,AN$5,C59:AL59) | AO59: =SUMIF($C$5:$AL$5,AO$5,C59:AL59) | AP59: =SUMIF($C$5:$AL$5,AP$5,C59:AL59) | AQ59: =SUM(C59:AL59)
A60: TOTAL EMPLOYMENT COST | C60: ='Headcount'!C31+'Headcount'!C44+'Headcount'!C57+'Headcount'!C59 | D60: ='Headcount'!D31+'Headcount'!D44+'Headcount'!D57+'Headcount'!D59 | E60: ='Headcount'!E31+'Headcount'!E44+'Headcount'!E57+'Headcount'!E59 | F60: ='Headcount'!F31+'Headcount'!F44+'Headcount'!F57+'Headcount'!F59 | G60: ='Headcount'!G31+'Headcount'!G44+'Headcount'!G57+'Headcount'!G59 | H60: ='Headcount'!H31+'Headcount'!H44+'Headcount'!H57+'Headcount'!H59 | I60: ='Headcount'!I31+'Headcount'!I44+'Headcount'!I57+'Headcount'!I59 | J60: ='Headcount'!J31+'Headcount'!J44+'Headcount'!J57+'Headcount'!J59 | ... AL60: ='Headcount'!AL31+'Headcount'!AL44+'Headcount'!AL57+'Headcount'!AL59 | AN60: =SUMIF($C$5:$AL$5,AN$5,C60:AL60) | AO60: =SUMIF($C$5:$AL$5,AO$5,C60:AL60) | AP60: =SUMIF($C$5:$AL$5,AP$5,C60:AL60) | AQ60: =SUM(C60:AL60)

Sheet P&L
A1: Profit and loss — monthly (columns C:AL) and annual (columns AN:AQ)
A2: ="Scenario: "&Assumptions!$D$4&" — all figures GBP, scenario values, not actuals"
A3: Month # | C3: 1 | D3: 2 | E3: 3 | F3: 4 | G3: 5 | H3: 6 | I3: 7 | J3: 8 | K3: 9 | L3: 10 | M3: 11 | N3: 12 | O3: 13 | P3: 14 | Q3: 15 | R3: 16 | S3: 17 | T3: 18 | U3: 19 | V3: 20 | W3: 21 | X3: 22 | Y3: 23 | Z3: 24 | AA3: 25 | AB3: 26 | AC3: 27 | AD3: 28 | AE3: 29 | AF3: 30 | AG3: 31 | AH3: 32 | AI3: 33 | AJ3: 34 | AK3: 35 | AL3: 36
A4: Month | C4: 46388 | D4: 46419 | E4: 46447 | F4: 46478 | G4: 46508 | H4: 46539 | I4: 46569 | J4: 46600 | K4: 46631 | L4: 46661 | M4: 46692 | N4: 46722 | O4: 46753 | P4: 46784 | Q4: 46813 | R4: 46844 | S4: 46874 | T4: 46905 | U4: 46935 | V4: 46966 | W4: 46997 | X4: 47027 | Y4: 47058 | Z4: 47088 | AA4: 47119 | AB4: 47150 | AC4: 47178 | AD4: 47209 | AE4: 47239 | AF4: 47270 | AG4: 47300 | AH4: 47331 | AI4: 47362 | AJ4: 47392 | AK4: 47423 | AL4: 47453 | AN4: FY2027 | AO4: FY2028 | AP4: FY2029 | AQ4: 3-year total
A5: Year | C5: 2027 | D5: 2027 | E5: 2027 | F5: 2027 | G5: 2027 | H5: 2027 | I5: 2027 | J5: 2027 | K5: 2027 | L5: 2027 | M5: 2027 | N5: 2027 | O5: 2028 | P5: 2028 | Q5: 2028 | R5: 2028 | S5: 2028 | T5: 2028 | U5: 2028 | V5: 2028 | W5: 2028 | X5: 2028 | Y5: 2028 | Z5: 2028 | AA5: 2029 | AB5: 2029 | AC5: 2029 | AD5: 2029 | AE5: 2029 | AF5: 2029 | AG5: 2029 | AH5: 2029 | AI5: 2029 | AJ5: 2029 | AK5: 2029 | AL5: 2029 | AN5: 2027 | AO5: 2028 | AP5: 2029
A6: Year index | C6: =C5-2026 | D6: =D5-2026 | E6: =E5-2026 | F6: =F5-2026 | G6: =G5-2026 | H6: =H5-2026 | I6: =I5-2026 | J6: =J5-2026 | ... AL6: =AL5-2026
A7: REVENUE
A8: Advisory | C8: ='Revenue build'!C23 | D8: ='Revenue build'!D23 | E8: ='Revenue build'!E23 | F8: ='Revenue build'!F23 | G8: ='Revenue build'!G23 | H8: ='Revenue build'!H23 | I8: ='Revenue build'!I23 | J8: ='Revenue build'!J23 | ... AL8: ='Revenue build'!AL23 | AN8: =SUMIF($C$5:$AL$5,AN$5,C8:AL8) | AO8: =SUMIF($C$5:$AL$5,AO$5,C8:AL8) | AP8: =SUMIF($C$5:$AL$5,AP$5,C8:AL8) | AQ8: =SUM(C8:AL8)
A9: Consulting | C9: ='Revenue build'!C27 | D9: ='Revenue build'!D27 | E9: ='Revenue build'!E27 | F9: ='Revenue build'!F27 | G9: ='Revenue build'!G27 | H9: ='Revenue build'!H27 | I9: ='Revenue build'!I27 | J9: ='Revenue build'!J27 | ... AL9: ='Revenue build'!AL27 | AN9: =SUMIF($C$5:$AL$5,AN$5,C9:AL9) | AO9: =SUMIF($C$5:$AL$5,AO$5,C9:AL9) | AP9: =SUMIF($C$5:$AL$5,AP$5,C9:AL9) | AQ9: =SUM(C9:AL9)
A10: E-learning | C10: ='Revenue build'!C36 | D10: ='Revenue build'!D36 | E10: ='Revenue build'!E36 | F10: ='Revenue build'!F36 | G10: ='Revenue build'!G36 | H10: ='Revenue build'!H36 | I10: ='Revenue build'!I36 | J10: ='Revenue build'!J36 | ... AL10: ='Revenue build'!AL36 | AN10: =SUMIF($C$5:$AL$5,AN$5,C10:AL10) | AO10: =SUMIF($C$5:$AL$5,AO$5,C10:AL10) | AP10: =SUMIF($C$5:$AL$5,AP$5,C10:AL10) | AQ10: =SUM(C10:AL10)
A11: MaternaLink (in development) | C11: ='Revenue build'!C48 | D11: ='Revenue build'!D48 | E11: ='Revenue build'!E48 | F11: ='Revenue build'!F48 | G11: ='Revenue build'!G48 | H11: ='Revenue build'!H48 | I11: ='Revenue build'!I48 | J11: ='Revenue build'!J48 | ... AL11: ='Revenue build'!AL48 | AN11: =SUMIF($C$5:$AL$5,AN$5,C11:AL11) | AO11: =SUMIF($C$5:$AL$5,AO$5,C11:AL11) | AP11: =SUMIF($C$5:$AL$5,AP$5,C11:AL11) | AQ11: =SUM(C11:AL11)
A12: TOTAL REVENUE | C12: =SUM(C8:C11) | D12: =SUM(D8:D11) | E12: =SUM(E8:E11) | F12: =SUM(F8:F11) | G12: =SUM(G8:G11) | H12: =SUM(H8:H11) | I12: =SUM(I8:I11) | J12: =SUM(J8:J11) | ... AL12: =SUM(AL8:AL11) | AN12: =SUMIF($C$5:$AL$5,AN$5,C12:AL12) | AO12: =SUMIF($C$5:$AL$5,AO$5,C12:AL12) | AP12: =SUMIF($C$5:$AL$5,AP$5,C12:AL12) | AQ12: =SUM(C12:AL12)
A13: Cost of sales | C13: =-'Cost of sales'!C12 | D13: =-'Cost of sales'!D12 | E13: =-'Cost of sales'!E12 | F13: =-'Cost of sales'!F12 | G13: =-'Cost of sales'!G12 | H13: =-'Cost of sales'!H12 | I13: =-'Cost of sales'!I12 | J13: =-'Cost of sales'!J12 | ... AL13: =-'Cost of sales'!AL12 | AN13: =SUMIF($C$5:$AL$5,AN$5,C13:AL13) | AO13: =SUMIF($C$5:$AL$5,AO$5,C13:AL13) | AP13: =SUMIF($C$5:$AL$5,AP$5,C13:AL13) | AQ13: =SUM(C13:AL13)
A14: GROSS PROFIT | C14: ='P&L'!C12+'P&L'!C13 | D14: ='P&L'!D12+'P&L'!D13 | E14: ='P&L'!E12+'P&L'!E13 | F14: ='P&L'!F12+'P&L'!F13 | G14: ='P&L'!G12+'P&L'!G13 | H14: ='P&L'!H12+'P&L'!H13 | I14: ='P&L'!I12+'P&L'!I13 | J14: ='P&L'!J12+'P&L'!J13 | ... AL14: ='P&L'!AL12+'P&L'!AL13 | AN14: =SUMIF($C$5:$AL$5,AN$5,C14:AL14) | AO14: =SUMIF($C$5:$AL$5,AO$5,C14:AL14) | AP14: =SUMIF($C$5:$AL$5,AP$5,C14:AL14) | AQ14: =SUM(C14:AL14)
A15: Gross margin % | C15: =IF('P&L'!C12>0,'P&L'!C14/'P&L'!C12,0) | D15: =IF('P&L'!D12>0,'P&L'!D14/'P&L'!D12,0) | E15: =IF('P&L'!E12>0,'P&L'!E14/'P&L'!E12,0) | F15: =IF('P&L'!F12>0,'P&L'!F14/'P&L'!F12,0) | G15: =IF('P&L'!G12>0,'P&L'!G14/'P&L'!G12,0) | H15: =IF('P&L'!H12>0,'P&L'!H14/'P&L'!H12,0) | I15: =IF('P&L'!I12>0,'P&L'!I14/'P&L'!I12,0) | J15: =IF('P&L'!J12>0,'P&L'!J14/'P&L'!J12,0) | ... AL15: =IF('P&L'!AL12>0,'P&L'!AL14/'P&L'!AL12,0) | AN15: =IF(AN12<>0,AN14/AN12,0) | AO15: =IF(AO12<>0,AO14/AO12,0) | AP15: =IF(AP12<>0,AP14/AP12,0) | AQ15: =IF(AQ12<>0,AQ14/AQ12,0)
A16: OPERATING EXPENSES
A17: Employment (founder + hires, incl. NI and pension) | C17: =-'Opex'!C13 | D17: =-'Opex'!D13 | E17: =-'Opex'!E13 | F17: =-'Opex'!F13 | G17: =-'Opex'!G13 | H17: =-'Opex'!H13 | I17: =-'Opex'!I13 | J17: =-'Opex'!J13 | ... AL17: =-'Opex'!AL13 | AN17: =SUMIF($C$5:$AL$5,AN$5,C17:AL17) | AO17: =SUMIF($C$5:$AL$5,AO$5,C17:AL17) | AP17: =SUMIF($C$5:$AL$5,AP$5,C17:AL17) | AQ17: =SUM(C17:AL17)
A18: Contractors | C18: =-'Opex'!C16 | D18: =-'Opex'!D16 | E18: =-'Opex'!E16 | F18: =-'Opex'!F16 | G18: =-'Opex'!G16 | H18: =-'Opex'!H16 | I18: =-'Opex'!I16 | J18: =-'Opex'!J16 | ... AL18: =-'Opex'!AL16 | AN18: =SUMIF($C$5:$AL$5,AN$5,C18:AL18) | AO18: =SUMIF($C$5:$AL$5,AO$5,C18:AL18) | AP18: =SUMIF($C$5:$AL$5,AP$5,C18:AL18) | AQ18: =SUM(C18:AL18)
A19: Technology | C19: =-'Opex'!C17 | D19: =-'Opex'!D17 | E19: =-'Opex'!E17 | F19: =-'Opex'!F17 | G19: =-'Opex'!G17 | H19: =-'Opex'!H17 | I19: =-'Opex'!I17 | J19: =-'Opex'!J17 | ... AL19: =-'Opex'!AL17 | AN19: =SUMIF($C$5:$AL$5,AN$5,C19:AL19) | AO19: =SUMIF($C$5:$AL$5,AO$5,C19:AL19) | AP19: =SUMIF($C$5:$AL$5,AP$5,C19:AL19) | AQ19: =SUM(C19:AL19)
A20: Marketing | C20: =-'Opex'!C18 | D20: =-'Opex'!D18 | E20: =-'Opex'!E18 | F20: =-'Opex'!F18 | G20: =-'Opex'!G18 | H20: =-'Opex'!H18 | I20: =-'Opex'!I18 | J20: =-'Opex'!J18 | ... AL20: =-'Opex'!AL18 | AN20: =SUMIF($C$5:$AL$5,AN$5,C20:AL20) | AO20: =SUMIF($C$5:$AL$5,AO$5,C20:AL20) | AP20: =SUMIF($C$5:$AL$5,AP$5,C20:AL20) | AQ20: =SUM(C20:AL20)
A21: Legal | C21: =-'Opex'!C19 | D21: =-'Opex'!D19 | E21: =-'Opex'!E19 | F21: =-'Opex'!F19 | G21: =-'Opex'!G19 | H21: =-'Opex'!H19 | I21: =-'Opex'!I19 | J21: =-'Opex'!J19 | ... AL21: =-'Opex'!AL19 | AN21: =SUMIF($C$5:$AL$5,AN$5,C21:AL21) | AO21: =SUMIF($C$5:$AL$5,AO$5,C21:AL21) | AP21: =SUMIF($C$5:$AL$5,AP$5,C21:AL21) | AQ21: =SUM(C21:AL21)
A22: Compliance & regulatory | C22: =-'Opex'!C20 | D22: =-'Opex'!D20 | E22: =-'Opex'!E20 | F22: =-'Opex'!F20 | G22: =-'Opex'!G20 | H22: =-'Opex'!H20 | I22: =-'Opex'!I20 | J22: =-'Opex'!J20 | ... AL22: =-'Opex'!AL20 | AN22: =SUMIF($C$5:$AL$5,AN$5,C22:AL22) | AO22: =SUMIF($C$5:$AL$5,AO$5,C22:AL22) | AP22: =SUMIF($C$5:$AL$5,AP$5,C22:AL22) | AQ22: =SUM(C22:AL22)
A23: Insurance | C23: =-'Opex'!C21 | D23: =-'Opex'!D21 | E23: =-'Opex'!E21 | F23: =-'Opex'!F21 | G23: =-'Opex'!G21 | H23: =-'Opex'!H21 | I23: =-'Opex'!I21 | J23: =-'Opex'!J21 | ... AL23: =-'Opex'!AL21 | AN23: =SUMIF($C$5:$AL$5,AN$5,C23:AL23) | AO23: =SUMIF($C$5:$AL$5,AO$5,C23:AL23) | AP23: =SUMIF($C$5:$AL$5,AP$5,C23:AL23) | AQ23: =SUM(C23:AL23)
A24: Software subscriptions | C24: =-'Opex'!C22 | D24: =-'Opex'!D22 | E24: =-'Opex'!E22 | F24: =-'Opex'!F22 | G24: =-'Opex'!G22 | H24: =-'Opex'!H22 | I24: =-'Opex'!I22 | J24: =-'Opex'!J22 | ... AL24: =-'Opex'!AL22 | AN24: =SUMIF($C$5:$AL$5,AN$5,C24:AL24) | AO24: =SUMIF($C$5:$AL$5,AO$5,C24:AL24) | AP24: =SUMIF($C$5:$AL$5,AP$5,C24:AL24) | AQ24: =SUM(C24:AL24)
A25: Travel | C25: =-'Opex'!C23 | D25: =-'Opex'!D23 | E25: =-'Opex'!E23 | F25: =-'Opex'!F23 | G25: =-'Opex'!G23 | H25: =-'Opex'!H23 | I25: =-'Opex'!I23 | J25: =-'Opex'!J23 | ... AL25: =-'Opex'!AL23 | AN25: =SUMIF($C$5:$AL$5,AN$5,C25:AL25) | AO25: =SUMIF($C$5:$AL$5,AO$5,C25:AL25) | AP25: =SUMIF($C$5:$AL$5,AP$5,C25:AL25) | AQ25: =SUM(C25:AL25)
A26: Operations | C26: =-'Opex'!C24 | D26: =-'Opex'!D24 | E26: =-'Opex'!E24 | F26: =-'Opex'!F24 | G26: =-'Opex'!G24 | H26: =-'Opex'!H24 | I26: =-'Opex'!I24 | J26: =-'Opex'!J24 | ... AL26: =-'Opex'!AL24 | AN26: =SUMIF($C$5:$AL$5,AN$5,C26:AL26) | AO26: =SUMIF($C$5:$AL$5,AO$5,C26:AL26) | AP26: =SUMIF($C$5:$AL$5,AP$5,C26:AL26) | AQ26: =SUM(C26:AL26)
A27: Accountancy, payroll, company secretarial | C27: =-'Opex'!C25 | D27: =-'Opex'!D25 | E27: =-'Opex'!E25 | F27: =-'Opex'!F25 | G27: =-'Opex'!G25 | H27: =-'Opex'!H25 | I27: =-'Opex'!I25 | J27: =-'Opex'!J25 | ... AL27: =-'Opex'!AL25 | AN27: =SUMIF($C$5:$AL$5,AN$5,C27:AL27) | AO27: =SUMIF($C$5:$AL$5,AO$5,C27:AL27) | AP27: =SUMIF($C$5:$AL$5,AP$5,C27:AL27) | AQ27: =SUM(C27:AL27)
A28: Legal & IP set-up (one-off) | C28: =-'Opex'!C26 | D28: =-'Opex'!D26 | E28: =-'Opex'!E26 | F28: =-'Opex'!F26 | G28: =-'Opex'!G26 | H28: =-'Opex'!H26 | I28: =-'Opex'!I26 | J28: =-'Opex'!J26 | ... AL28: =-'Opex'!AL26 | AN28: =SUMIF($C$5:$AL$5,AN$5,C28:AL28) | AO28: =SUMIF($C$5:$AL$5,AO$5,C28:AL28) | AP28: =SUMIF($C$5:$AL$5,AP$5,C28:AL28) | AQ28: =SUM(C28:AL28)
A29: E-learning content build | C29: =-'Opex'!C27 | D29: =-'Opex'!D27 | E29: =-'Opex'!E27 | F29: =-'Opex'!F27 | G29: =-'Opex'!G27 | H29: =-'Opex'!H27 | I29: =-'Opex'!I27 | J29: =-'Opex'!J27 | ... AL29: =-'Opex'!AL27 | AN29: =SUMIF($C$5:$AL$5,AN$5,C29:AL29) | AO29: =SUMIF($C$5:$AL$5,AO$5,C29:AL29) | AP29: =SUMIF($C$5:$AL$5,AP$5,C29:AL29) | AQ29: =SUM(C29:AL29)
A30: TOTAL OPERATING EXPENSES | C30: =SUM(C17:C29) | D30: =SUM(D17:D29) | E30: =SUM(E17:E29) | F30: =SUM(F17:F29) | G30: =SUM(G17:G29) | H30: =SUM(H17:H29) | I30: =SUM(I17:I29) | J30: =SUM(J17:J29) | ... AL30: =SUM(AL17:AL29) | AN30: =SUMIF($C$5:$AL$5,AN$5,C30:AL30) | AO30: =SUMIF($C$5:$AL$5,AO$5,C30:AL30) | AP30: =SUMIF($C$5:$AL$5,AP$5,C30:AL30) | AQ30: =SUM(C30:AL30)
A32: EBITDA / OPERATING RESULT (before grants) | C32: ='P&L'!C14+'P&L'!C30 | D32: ='P&L'!D14+'P&L'!D30 | E32: ='P&L'!E14+'P&L'!E30 | F32: ='P&L'!F14+'P&L'!F30 | G32: ='P&L'!G14+'P&L'!G30 | H32: ='P&L'!H14+'P&L'!H30 | I32: ='P&L'!I14+'P&L'!I30 | J32: ='P&L'!J14+'P&L'!J30 | ... AL32: ='P&L'!AL14+'P&L'!AL30 | AN32: =SUMIF($C$5:$AL$5,AN$5,C32:AL32) | AO32: =SUMIF($C$5:$AL$5,AO$5,C32:AL32) | AP32: =SUMIF($C$5:$AL$5,AP$5,C32:AL32) | AQ32: =SUM(C32:AL32)
A33: EBITDA positive (1/0) | C33: =IF('P&L'!C32>0,1,0) | D33: =IF('P&L'!D32>0,1,0) | E33: =IF('P&L'!E32>0,1,0) | F33: =IF('P&L'!F32>0,1,0) | G33: =IF('P&L'!G32>0,1,0) | H33: =IF('P&L'!H32>0,1,0) | I33: =IF('P&L'!I32>0,1,0) | J33: =IF('P&L'!J32>0,1,0) | ... AL33: =IF('P&L'!AL32>0,1,0)
A34: EBITDA positive from this month to month 36 (1/0) — sustained break-even | C34: =IF(MIN(C32:AL32)>0,1,0) | D34: =IF(MIN(D32:AL32)>0,1,0) | E34: =IF(MIN(E32:AL32)>0,1,0) | F34: =IF(MIN(F32:AL32)>0,1,0) | G34: =IF(MIN(G32:AL32)>0,1,0) | H34: =IF(MIN(H32:AL32)>0,1,0) | I34: =IF(MIN(I32:AL32)>0,1,0) | J34: =IF(MIN(J32:AL32)>0,1,0) | K34: =IF(MIN(K32:AL32)>0,1,0) | L34: =IF(MIN(L32:AL32)>0,1,0) | M34: =IF(MIN(M32:AL32)>0,1,0) | N34: =IF(MIN(N32:AL32)>0,1,0) | O34: =IF(MIN(O32:AL32)>0,1,0) | P34: =IF(MIN(P32:AL32)>0,1,0) | Q34: =IF(MIN(Q32:AL32)>0,1,0) | R34: =IF(MIN(R32:AL32)>0,1,0) | S34: =IF(MIN(S32:AL32)>0,1,0) | T34: =IF(MIN(T32:AL32)>0,1,0) | U34: =IF(MIN(U32:AL32)>0,1,0) | V34: =IF(MIN(V32:AL32)>0,1,0) | W34: =IF(MIN(W32:AL32)>0,1,0) | X34: =IF(MIN(X32:AL32)>0,1,0) | Y34: =IF(MIN(Y32:AL32)>0,1,0) | Z34: =IF(MIN(Z32:AL32)>0,1,0) | AA34: =IF(MIN(AA32:AL32)>0,1,0) | AB34: =IF(MIN(AB32:AL32)>0,1,0) | AC34: =IF(MIN(AC32:AL32)>0,1,0) | AD34: =IF(MIN(AD32:AL32)>0,1,0) | AE34: =IF(MIN(AE32:AL32)>0,1,0) | AF34: =IF(MIN(AF32:AL32)>0,1,0) | AG34: =IF(MIN(AG32:AL32)>0,1,0) | AH34: =IF(MIN(AH32:AL32)>0,1,0) | AI34: =IF(MIN(AI32:AL32)>0,1,0) | AJ34: =IF(MIN(AJ32:AL32)>0,1,0) | AK34: =IF(MIN(AK32:AL32)>0,1,0) | AL34: =IF(MIN(AL32:AL32)>0,1,0)
A35: Grant income (other income; TO VALIDATE) | C35: ='Cash flow'!C18 | D35: ='Cash flow'!D18 | E35: ='Cash flow'!E18 | F35: ='Cash flow'!F18 | G35: ='Cash flow'!G18 | H35: ='Cash flow'!H18 | I35: ='Cash flow'!I18 | J35: ='Cash flow'!J18 | ... AL35: ='Cash flow'!AL18 | AN35: =SUMIF($C$5:$AL$5,AN$5,C35:AL35) | AO35: =SUMIF($C$5:$AL$5,AO$5,C35:AL35) | AP35: =SUMIF($C$5:$AL$5,AP$5,C35:AL35) | AQ35: =SUM(C35:AL35)
A36: NET RESULT BEFORE TAX | C36: ='P&L'!C32+'P&L'!C35 | D36: ='P&L'!D32+'P&L'!D35 | E36: ='P&L'!E32+'P&L'!E35 | F36: ='P&L'!F32+'P&L'!F35 | G36: ='P&L'!G32+'P&L'!G35 | H36: ='P&L'!H32+'P&L'!H35 | I36: ='P&L'!I32+'P&L'!I35 | J36: ='P&L'!J32+'P&L'!J35 | ... AL36: ='P&L'!AL32+'P&L'!AL35 | AN36: =SUMIF($C$5:$AL$5,AN$5,C36:AL36) | AO36: =SUMIF($C$5:$AL$5,AO$5,C36:AL36) | AP36: =SUMIF($C$5:$AL$5,AP$5,C36:AL36) | AQ36: =SUM(C36:AL36)
A37: Cumulative net result | C37: ='P&L'!C36 | D37: ='P&L'!C37+'P&L'!D36 | E37: ='P&L'!D37+'P&L'!E36 | F37: ='P&L'!E37+'P&L'!F36 | G37: ='P&L'!F37+'P&L'!G36 | H37: ='P&L'!G37+'P&L'!H36 | I37: ='P&L'!H37+'P&L'!I36 | J37: ='P&L'!I37+'P&L'!J36 | K37: ='P&L'!J37+'P&L'!K36 | ... AL37: ='P&L'!AK37+'P&L'!AL36 | AN37: =INDEX(C37:AL37,1,12) | AO37: =INDEX(C37:AL37,1,24) | AP37: =INDEX(C37:AL37,1,36) | AQ37: =INDEX(C37:AL37,1,36)
A38: Cumulative result positive (1/0) | C38: =IF('P&L'!C37>0,1,0) | D38: =IF('P&L'!D37>0,1,0) | E38: =IF('P&L'!E37>0,1,0) | F38: =IF('P&L'!F37>0,1,0) | G38: =IF('P&L'!G37>0,1,0) | H38: =IF('P&L'!H37>0,1,0) | I38: =IF('P&L'!I37>0,1,0) | J38: =IF('P&L'!J37>0,1,0) | ... AL38: =IF('P&L'!AL37>0,1,0)
A40: No depreciation, interest, corporation tax or VAT modelled (loss-making; R&D tax relief is an unmodelled upside, TO VALIDATE).

Sheet Cash flow
A1: Cash flow — receipts with collection lag, funding injections, closing cash, runway
A2: ="Scenario: "&Assumptions!$D$4&" — all figures GBP, scenario values, not actuals"
A3: Month # | C3: 1 | D3: 2 | E3: 3 | F3: 4 | G3: 5 | H3: 6 | I3: 7 | J3: 8 | K3: 9 | L3: 10 | M3: 11 | N3: 12 | O3: 13 | P3: 14 | Q3: 15 | R3: 16 | S3: 17 | T3: 18 | U3: 19 | V3: 20 | W3: 21 | X3: 22 | Y3: 23 | Z3: 24 | AA3: 25 | AB3: 26 | AC3: 27 | AD3: 28 | AE3: 29 | AF3: 30 | AG3: 31 | AH3: 32 | AI3: 33 | AJ3: 34 | AK3: 35 | AL3: 36
A4: Month | C4: 46388 | D4: 46419 | E4: 46447 | F4: 46478 | G4: 46508 | H4: 46539 | I4: 46569 | J4: 46600 | K4: 46631 | L4: 46661 | M4: 46692 | N4: 46722 | O4: 46753 | P4: 46784 | Q4: 46813 | R4: 46844 | S4: 46874 | T4: 46905 | U4: 46935 | V4: 46966 | W4: 46997 | X4: 47027 | Y4: 47058 | Z4: 47088 | AA4: 47119 | AB4: 47150 | AC4: 47178 | AD4: 47209 | AE4: 47239 | AF4: 47270 | AG4: 47300 | AH4: 47331 | AI4: 47362 | AJ4: 47392 | AK4: 47423 | AL4: 47453 | AN4: FY2027 | AO4: FY2028 | AP4: FY2029 | AQ4: 3-year total
A5: Year | C5: 2027 | D5: 2027 | E5: 2027 | F5: 2027 | G5: 2027 | H5: 2027 | I5: 2027 | J5: 2027 | K5: 2027 | L5: 2027 | M5: 2027 | N5: 2027 | O5: 2028 | P5: 2028 | Q5: 2028 | R5: 2028 | S5: 2028 | T5: 2028 | U5: 2028 | V5: 2028 | W5: 2028 | X5: 2028 | Y5: 2028 | Z5: 2028 | AA5: 2029 | AB5: 2029 | AC5: 2029 | AD5: 2029 | AE5: 2029 | AF5: 2029 | AG5: 2029 | AH5: 2029 | AI5: 2029 | AJ5: 2029 | AK5: 2029 | AL5: 2029 | AN5: 2027 | AO5: 2028 | AP5: 2029
A6: Year index | C6: =C5-2026 | D6: =D5-2026 | E6: =E5-2026 | F6: =F5-2026 | G6: =G5-2026 | H6: =H5-2026 | I6: =I5-2026 | J6: =J5-2026 | ... AL6: =AL5-2026
A7: Opening cash | C7: =Assumptions!$F$9 | D7: ='Cash flow'!C25 | E7: ='Cash flow'!D25 | F7: ='Cash flow'!E25 | G7: ='Cash flow'!F25 | H7: ='Cash flow'!G25 | I7: ='Cash flow'!H25 | J7: ='Cash flow'!I25 | K7: ='Cash flow'!J25 | ... AL7: ='Cash flow'!AK25
A8: OPERATING CASH FLOW
A9: Receipts — advisory & consulting (lagged) | C9: =IF(C3-Assumptions!$F$10<1,0,INDEX('Revenue build'!$C$23:$AL$23,1,C3-Assumptions!$F$10))+IF(C3-Assumptions!$F$10<1,0,INDEX('Revenue build'!$C$27:$AL$27,1,C3-Assumptions!$F$10)) | D9: =IF(D3-Assumptions!$F$10<1,0,INDEX('Revenue build'!$C$23:$AL$23,1,D3-Assumptions!$F$10))+IF(D3-Assumptions!$F$10<1,0,INDEX('Revenue build'!$C$27:$AL$27,1,D3-Assumptions!$F$10)) | E9: =IF(E3-Assumptions!$F$10<1,0,INDEX('Revenue build'!$C$23:$AL$23,1,E3-Assumptions!$F$10))+IF(E3-Assumptions!$F$10<1,0,INDEX('Revenue build'!$C$27:$AL$27,1,E3-Assumptions!$F$10)) | F9: =IF(F3-Assumptions!$F$10<1,0,INDEX('Revenue build'!$C$23:$AL$23,1,F3-Assumptions!$F$10))+IF(F3-Assumptions!$F$10<1,0,INDEX('Revenue build'!$C$27:$AL$27,1,F3-Assumptions!$F$10)) | G9: =IF(G3-Assumptions!$F$10<1,0,INDEX('Revenue build'!$C$23:$AL$23,1,G3-Assumptions!$F$10))+IF(G3-Assumptions!$F$10<1,0,INDEX('Revenue build'!$C$27:$AL$27,1,G3-Assumptions!$F$10)) | H9: =IF(H3-Assumptions!$F$10<1,0,INDEX('Revenue build'!$C$23:$AL$23,1,H3-Assumptions!$F$10))+IF(H3-Assumptions!$F$10<1,0,INDEX('Revenue build'!$C$27:$AL$27,1,H3-Assumptions!$F$10)) | I9: =IF(I3-Assumptions!$F$10<1,0,INDEX('Revenue build'!$C$23:$AL$23,1,I3-Assumptions!$F$10))+IF(I3-Assumptions!$F$10<1,0,INDEX('Revenue build'!$C$27:$AL$27,1,I3-Assumptions!$F$10)) | J9: =IF(J3-Assumptions!$F$10<1,0,INDEX('Revenue build'!$C$23:$AL$23,1,J3-Assumptions!$F$10))+IF(J3-Assumptions!$F$10<1,0,INDEX('Revenue build'!$C$27:$AL$27,1,J3-Assumptions!$F$10)) | ... AL9: =IF(AL3-Assumptions!$F$10<1,0,INDEX('Revenue build'!$C$23:$AL$23,1,AL3-Assumptions!$F$10))+IF(AL3-Assumptions!$F$10<1,0,INDEX('Revenue build'!$C$27:$AL$27,1,AL3-Assumptions!$F$10)) | AN9: =SUMIF($C$5:$AL$5,AN$5,C9:AL9) | AO9: =SUMIF($C$5:$AL$5,AO$5,C9:AL9) | AP9: =SUMIF($C$5:$AL$5,AP$5,C9:AL9) | AQ9: =SUM(C9:AL9)
A10: Receipts — e-learning (prepaid) | C10: ='Revenue build'!C36 | D10: ='Revenue build'!D36 | E10: ='Revenue build'!E36 | F10: ='Revenue build'!F36 | G10: ='Revenue build'!G36 | H10: ='Revenue build'!H36 | I10: ='Revenue build'!I36 | J10: ='Revenue build'!J36 | ... AL10: ='Revenue build'!AL36 | AN10: =SUMIF($C$5:$AL$5,AN$5,C10:AL10) | AO10: =SUMIF($C$5:$AL$5,AO$5,C10:AL10) | AP10: =SUMIF($C$5:$AL$5,AP$5,C10:AL10) | AQ10: =SUM(C10:AL10)
A11: Receipts — MaternaLink (lagged) | C11: =IF(C3-Assumptions!$F$10<1,0,INDEX('Revenue build'!$C$48:$AL$48,1,C3-Assumptions!$F$10)) | D11: =IF(D3-Assumptions!$F$10<1,0,INDEX('Revenue build'!$C$48:$AL$48,1,D3-Assumptions!$F$10)) | E11: =IF(E3-Assumptions!$F$10<1,0,INDEX('Revenue build'!$C$48:$AL$48,1,E3-Assumptions!$F$10)) | F11: =IF(F3-Assumptions!$F$10<1,0,INDEX('Revenue build'!$C$48:$AL$48,1,F3-Assumptions!$F$10)) | G11: =IF(G3-Assumptions!$F$10<1,0,INDEX('Revenue build'!$C$48:$AL$48,1,G3-Assumptions!$F$10)) | H11: =IF(H3-Assumptions!$F$10<1,0,INDEX('Revenue build'!$C$48:$AL$48,1,H3-Assumptions!$F$10)) | I11: =IF(I3-Assumptions!$F$10<1,0,INDEX('Revenue build'!$C$48:$AL$48,1,I3-Assumptions!$F$10)) | J11: =IF(J3-Assumptions!$F$10<1,0,INDEX('Revenue build'!$C$48:$AL$48,1,J3-Assumptions!$F$10)) | ... AL11: =IF(AL3-Assumptions!$F$10<1,0,INDEX('Revenue build'!$C$48:$AL$48,1,AL3-Assumptions!$F$10)) | AN11: =SUMIF($C$5:$AL$5,AN$5,C11:AL11) | AO11: =SUMIF($C$5:$AL$5,AO$5,C11:AL11) | AP11: =SUMIF($C$5:$AL$5,AP$5,C11:AL11) | AQ11: =SUM(C11:AL11)
A12: Total receipts | C12: =SUM(C9:C11) | D12: =SUM(D9:D11) | E12: =SUM(E9:E11) | F12: =SUM(F9:F11) | G12: =SUM(G9:G11) | H12: =SUM(H9:H11) | I12: =SUM(I9:I11) | J12: =SUM(J9:J11) | ... AL12: =SUM(AL9:AL11) | AN12: =SUMIF($C$5:$AL$5,AN$5,C12:AL12) | AO12: =SUMIF($C$5:$AL$5,AO$5,C12:AL12) | AP12: =SUMIF($C$5:$AL$5,AP$5,C12:AL12) | AQ12: =SUM(C12:AL12)
A13: Payments — cost of sales | C13: =-'Cost of sales'!C12 | D13: =-'Cost of sales'!D12 | E13: =-'Cost of sales'!E12 | F13: =-'Cost of sales'!F12 | G13: =-'Cost of sales'!G12 | H13: =-'Cost of sales'!H12 | I13: =-'Cost of sales'!I12 | J13: =-'Cost of sales'!J12 | ... AL13: =-'Cost of sales'!AL12 | AN13: =SUMIF($C$5:$AL$5,AN$5,C13:AL13) | AO13: =SUMIF($C$5:$AL$5,AO$5,C13:AL13) | AP13: =SUMIF($C$5:$AL$5,AP$5,C13:AL13) | AQ13: =SUM(C13:AL13)
A14: Payments — operating expenses | C14: =-'Opex'!C30 | D14: =-'Opex'!D30 | E14: =-'Opex'!E30 | F14: =-'Opex'!F30 | G14: =-'Opex'!G30 | H14: =-'Opex'!H30 | I14: =-'Opex'!I30 | J14: =-'Opex'!J30 | ... AL14: =-'Opex'!AL30 | AN14: =SUMIF($C$5:$AL$5,AN$5,C14:AL14) | AO14: =SUMIF($C$5:$AL$5,AO$5,C14:AL14) | AP14: =SUMIF($C$5:$AL$5,AP$5,C14:AL14) | AQ14: =SUM(C14:AL14)
A15: NET OPERATING CASH FLOW | C15: ='Cash flow'!C12+'Cash flow'!C13+'Cash flow'!C14 | D15: ='Cash flow'!D12+'Cash flow'!D13+'Cash flow'!D14 | E15: ='Cash flow'!E12+'Cash flow'!E13+'Cash flow'!E14 | F15: ='Cash flow'!F12+'Cash flow'!F13+'Cash flow'!F14 | G15: ='Cash flow'!G12+'Cash flow'!G13+'Cash flow'!G14 | H15: ='Cash flow'!H12+'Cash flow'!H13+'Cash flow'!H14 | I15: ='Cash flow'!I12+'Cash flow'!I13+'Cash flow'!I14 | J15: ='Cash flow'!J12+'Cash flow'!J13+'Cash flow'!J14 | ... AL15: ='Cash flow'!AL12+'Cash flow'!AL13+'Cash flow'!AL14 | AN15: =SUMIF($C$5:$AL$5,AN$5,C15:AL15) | AO15: =SUMIF($C$5:$AL$5,AO$5,C15:AL15) | AP15: =SUMIF($C$5:$AL$5,AP$5,C15:AL15) | AQ15: =SUM(C15:AL15)
A17: FUNDING INJECTIONS (by round / month)
A18: Grant receipts (non-dilutive; TO VALIDATE) | C18: =IF(C3=Assumptions!$F$128,Assumptions!$F$127,0)+IF(C3=Assumptions!$F$130,Assumptions!$F$129,0) | D18: =IF(D3=Assumptions!$F$128,Assumptions!$F$127,0)+IF(D3=Assumptions!$F$130,Assumptions!$F$129,0) | E18: =IF(E3=Assumptions!$F$128,Assumptions!$F$127,0)+IF(E3=Assumptions!$F$130,Assumptions!$F$129,0) | F18: =IF(F3=Assumptions!$F$128,Assumptions!$F$127,0)+IF(F3=Assumptions!$F$130,Assumptions!$F$129,0) | G18: =IF(G3=Assumptions!$F$128,Assumptions!$F$127,0)+IF(G3=Assumptions!$F$130,Assumptions!$F$129,0) | H18: =IF(H3=Assumptions!$F$128,Assumptions!$F$127,0)+IF(H3=Assumptions!$F$130,Assumptions!$F$129,0) | I18: =IF(I3=Assumptions!$F$128,Assumptions!$F$127,0)+IF(I3=Assumptions!$F$130,Assumptions!$F$129,0) | J18: =IF(J3=Assumptions!$F$128,Assumptions!$F$127,0)+IF(J3=Assumptions!$F$130,Assumptions!$F$129,0) | ... AL18: =IF(AL3=Assumptions!$F$128,Assumptions!$F$127,0)+IF(AL3=Assumptions!$F$130,Assumptions!$F$129,0) | AN18: =SUMIF($C$5:$AL$5,AN$5,C18:AL18) | AO18: =SUMIF($C$5:$AL$5,AO$5,C18:AL18) | AP18: =SUMIF($C$5:$AL$5,AP$5,C18:AL18) | AQ18: =SUM(C18:AL18)
A19: Pre-seed equity (SEIS/EIS angels) | C19: =IF(C3=Assumptions!$F$122,Assumptions!$F$121,0) | D19: =IF(D3=Assumptions!$F$122,Assumptions!$F$121,0) | E19: =IF(E3=Assumptions!$F$122,Assumptions!$F$121,0) | F19: =IF(F3=Assumptions!$F$122,Assumptions!$F$121,0) | G19: =IF(G3=Assumptions!$F$122,Assumptions!$F$121,0) | H19: =IF(H3=Assumptions!$F$122,Assumptions!$F$121,0) | I19: =IF(I3=Assumptions!$F$122,Assumptions!$F$121,0) | J19: =IF(J3=Assumptions!$F$122,Assumptions!$F$121,0) | ... AL19: =IF(AL3=Assumptions!$F$122,Assumptions!$F$121,0) | AN19: =SUMIF($C$5:$AL$5,AN$5,C19:AL19) | AO19: =SUMIF($C$5:$AL$5,AO$5,C19:AL19) | AP19: =SUMIF($C$5:$AL$5,AP$5,C19:AL19) | AQ19: =SUM(C19:AL19)
A20: Seed equity | C20: =IF(C3=Assumptions!$F$124,Assumptions!$F$123,0) | D20: =IF(D3=Assumptions!$F$124,Assumptions!$F$123,0) | E20: =IF(E3=Assumptions!$F$124,Assumptions!$F$123,0) | F20: =IF(F3=Assumptions!$F$124,Assumptions!$F$123,0) | G20: =IF(G3=Assumptions!$F$124,Assumptions!$F$123,0) | H20: =IF(H3=Assumptions!$F$124,Assumptions!$F$123,0) | I20: =IF(I3=Assumptions!$F$124,Assumptions!$F$123,0) | J20: =IF(J3=Assumptions!$F$124,Assumptions!$F$123,0) | ... AL20: =IF(AL3=Assumptions!$F$124,Assumptions!$F$123,0) | AN20: =SUMIF($C$5:$AL$5,AN$5,C20:AL20) | AO20: =SUMIF($C$5:$AL$5,AO$5,C20:AL20) | AP20: =SUMIF($C$5:$AL$5,AP$5,C20:AL20) | AQ20: =SUM(C20:AL20)
A21: Series A equity | C21: =IF(C3=Assumptions!$F$126,Assumptions!$F$125,0) | D21: =IF(D3=Assumptions!$F$126,Assumptions!$F$125,0) | E21: =IF(E3=Assumptions!$F$126,Assumptions!$F$125,0) | F21: =IF(F3=Assumptions!$F$126,Assumptions!$F$125,0) | G21: =IF(G3=Assumptions!$F$126,Assumptions!$F$125,0) | H21: =IF(H3=Assumptions!$F$126,Assumptions!$F$125,0) | I21: =IF(I3=Assumptions!$F$126,Assumptions!$F$125,0) | J21: =IF(J3=Assumptions!$F$126,Assumptions!$F$125,0) | ... AL21: =IF(AL3=Assumptions!$F$126,Assumptions!$F$125,0) | AN21: =SUMIF($C$5:$AL$5,AN$5,C21:AL21) | AO21: =SUMIF($C$5:$AL$5,AO$5,C21:AL21) | AP21: =SUMIF($C$5:$AL$5,AP$5,C21:AL21) | AQ21: =SUM(C21:AL21)
A22: Total funding received | C22: =SUM(C18:C21) | D22: =SUM(D18:D21) | E22: =SUM(E18:E21) | F22: =SUM(F18:F21) | G22: =SUM(G18:G21) | H22: =SUM(H18:H21) | I22: =SUM(I18:I21) | J22: =SUM(J18:J21) | ... AL22: =SUM(AL18:AL21) | AN22: =SUMIF($C$5:$AL$5,AN$5,C22:AL22) | AO22: =SUMIF($C$5:$AL$5,AO$5,C22:AL22) | AP22: =SUMIF($C$5:$AL$5,AP$5,C22:AL22) | AQ22: =SUM(C22:AL22)
A24: NET CASH FLOW | C24: ='Cash flow'!C15+'Cash flow'!C22 | D24: ='Cash flow'!D15+'Cash flow'!D22 | E24: ='Cash flow'!E15+'Cash flow'!E22 | F24: ='Cash flow'!F15+'Cash flow'!F22 | G24: ='Cash flow'!G15+'Cash flow'!G22 | H24: ='Cash flow'!H15+'Cash flow'!H22 | I24: ='Cash flow'!I15+'Cash flow'!I22 | J24: ='Cash flow'!J15+'Cash flow'!J22 | ... AL24: ='Cash flow'!AL15+'Cash flow'!AL22 | AN24: =SUMIF($C$5:$AL$5,AN$5,C24:AL24) | AO24: =SUMIF($C$5:$AL$5,AO$5,C24:AL24) | AP24: =SUMIF($C$5:$AL$5,AP$5,C24:AL24) | AQ24: =SUM(C24:AL24)
A25: CLOSING CASH | C25: ='Cash flow'!C7+'Cash flow'!C24 | D25: ='Cash flow'!D7+'Cash flow'!D24 | E25: ='Cash flow'!E7+'Cash flow'!E24 | F25: ='Cash flow'!F7+'Cash flow'!F24 | G25: ='Cash flow'!G7+'Cash flow'!G24 | H25: ='Cash flow'!H7+'Cash flow'!H24 | I25: ='Cash flow'!I7+'Cash flow'!I24 | J25: ='Cash flow'!J7+'Cash flow'!J24 | ... AL25: ='Cash flow'!AL7+'Cash flow'!AL24 | AN25: =INDEX(C25:AL25,1,12) | AO25: =INDEX(C25:AL25,1,24) | AP25: =INDEX(C25:AL25,1,36) | AQ25: =INDEX(C25:AL25,1,36)
A26: Minimum closing cash to date | C26: ='Cash flow'!C25 | D26: =MIN('Cash flow'!C26,'Cash flow'!D25) | E26: =MIN('Cash flow'!D26,'Cash flow'!E25) | F26: =MIN('Cash flow'!E26,'Cash flow'!F25) | G26: =MIN('Cash flow'!F26,'Cash flow'!G25) | H26: =MIN('Cash flow'!G26,'Cash flow'!H25) | I26: =MIN('Cash flow'!H26,'Cash flow'!I25) | J26: =MIN('Cash flow'!I26,'Cash flow'!J25) | K26: =MIN('Cash flow'!J26,'Cash flow'!K25) | ... AL26: =MIN('Cash flow'!AK26,'Cash flow'!AL25) | AN26: =INDEX(C26:AL26,1,12) | AO26: =INDEX(C26:AL26,1,24) | AP26: =INDEX(C26:AL26,1,36) | AQ26: =INDEX(C26:AL26,1,36)
A27: Cumulative cash BEFORE external funding (opening cash + operating cash flow) | C27: =Assumptions!$F$9+'Cash flow'!C15 | D27: ='Cash flow'!C27+'Cash flow'!D15 | E27: ='Cash flow'!D27+'Cash flow'!E15 | F27: ='Cash flow'!E27+'Cash flow'!F15 | G27: ='Cash flow'!F27+'Cash flow'!G15 | H27: ='Cash flow'!G27+'Cash flow'!H15 | I27: ='Cash flow'!H27+'Cash flow'!I15 | J27: ='Cash flow'!I27+'Cash flow'!J15 | K27: ='Cash flow'!J27+'Cash flow'!K15 | ... AL27: ='Cash flow'!AK27+'Cash flow'!AL15 | AN27: =INDEX(C27:AL27,1,12) | AO27: =INDEX(C27:AL27,1,24) | AP27: =INDEX(C27:AL27,1,36) | AQ27: =INDEX(C27:AL27,1,36)
A28: Monthly burn (negative of operating cash flow) | C28: =-'Cash flow'!C15 | D28: =-'Cash flow'!D15 | E28: =-'Cash flow'!E15 | F28: =-'Cash flow'!F15 | G28: =-'Cash flow'!G15 | H28: =-'Cash flow'!H15 | I28: =-'Cash flow'!I15 | J28: =-'Cash flow'!J15 | ... AL28: =-'Cash flow'!AL15 | AN28: =AVERAGEIF($C$5:$AL$5,AN$5,C28:AL28) | AO28: =AVERAGEIF($C$5:$AL$5,AO$5,C28:AL28) | AP28: =AVERAGEIF($C$5:$AL$5,AP$5,C28:AL28) | AQ28: =AVERAGE(C28:AL28)
A29: Runway (months of closing cash at trailing 3-month burn) | C29: =IF(AVERAGE(C28:C28)>0,'Cash flow'!C25/AVERAGE(C28:C28),"cash-generative") | D29: =IF(AVERAGE(C28:D28)>0,'Cash flow'!D25/AVERAGE(C28:D28),"cash-generative") | E29: =IF(AVERAGE(C28:E28)>0,'Cash flow'!E25/AVERAGE(C28:E28),"cash-generative") | F29: =IF(AVERAGE(D28:F28)>0,'Cash flow'!F25/AVERAGE(D28:F28),"cash-generative") | G29: =IF(AVERAGE(E28:G28)>0,'Cash flow'!G25/AVERAGE(E28:G28),"cash-generative") | H29: =IF(AVERAGE(F28:H28)>0,'Cash flow'!H25/AVERAGE(F28:H28),"cash-generative") | I29: =IF(AVERAGE(G28:I28)>0,'Cash flow'!I25/AVERAGE(G28:I28),"cash-generative") | J29: =IF(AVERAGE(H28:J28)>0,'Cash flow'!J25/AVERAGE(H28:J28),"cash-generative") | K29: =IF(AVERAGE(I28:K28)>0,'Cash flow'!K25/AVERAGE(I28:K28),"cash-generative") | L29: =IF(AVERAGE(J28:L28)>0,'Cash flow'!L25/AVERAGE(J28:L28),"cash-generative") | ... AL29: =IF(AVERAGE(AJ28:AL28)>0,'Cash flow'!AL25/AVERAGE(AJ28:AL28),"cash-generative") | AN29: =INDEX(C29:AL29,1,12) | AO29: =INDEX(C29:AL29,1,24) | AP29: =INDEX(C29:AL29,1,36) | AQ29: =INDEX(C29:AL29,1,36)

Sheet Funding requirement
A1: Funding requirement — peak cash need, break-even, runway (active scenario)
A2: ="Scenario: "&Assumptions!$D$4
A4: Peak cash need before external funding (max cumulative deficit incl. opening cash) | B4: =MAX(0,-MIN('Cash flow'!$C$27:$AL$27))
A5: Month of peak cash need | B5: =MATCH(MIN('Cash flow'!$C$27:$AL$27),'Cash flow'!$C$27:$AL$27,0)
A6: Date of peak cash need | B6: =IF(ISNUMBER(B5),TEXT(DATE(2027,B5,1),"mmm yyyy"),"—")
A7: First month with positive EBITDA (monthly operating break-even) | B7: =IFERROR(MATCH(1,'P&L'!$C$33:$AL$33,0),"Not reached in 36 months")
A8: Date of monthly break-even | B8: =IF(ISNUMBER(B7),TEXT(DATE(2027,B7,1),"mmm yyyy"),"—")
A9: First month with positive cumulative net result | B9: =IFERROR(MATCH(1,'P&L'!$C$38:$AL$38,0),"Not reached in 36 months")
A10: Minimum closing cash AFTER funding | B10: =MIN('Cash flow'!$C$25:$AL$25)
A11: Month of minimum closing cash | B11: =MATCH(MIN('Cash flow'!$C$25:$AL$25),'Cash flow'!$C$25:$AL$25,0)
A12: Funded-through check | B12: =IF(B10>=0,"Funding covers all 36 months","SHORTFALL — cash goes negative; raise earlier/more or cut cost")
A13: Closing cash at month 36 (Dec 2029) | B13: =INDEX('Cash flow'!$C$25:$AL$25,1,36)
A14: Runway at month 36 (months) | B14: =INDEX('Cash flow'!$C$29:$AL$29,1,36)
A15: Total equity raised in model (36 months) | B15: =SUM('Cash flow'!$C$19:$AL$19)+SUM('Cash flow'!$C$20:$AL$20)+SUM('Cash flow'!$C$21:$AL$21)
A16: Total grant income in model (36 months) | B16: =SUM('Cash flow'!$C$18:$AL$18)
A17: 3-year revenue | B17: =SUM('P&L'!$C$12:$AL$12)
A18: 3-year EBITDA | B18: =SUM('P&L'!$C$32:$AL$32)
A19: Headcount at month 36 | B19: =INDEX('Headcount'!$C$18:$AL$18,1,36)
A20: First month of SUSTAINED positive EBITDA (stays positive to month 36) | B20: =IFERROR(MATCH(1,'P&L'!$C$34:$AL$34,0),"Not reached in 36 months")
A22: Funding rounds in the active scenario (PROPOSED; every round is conditional on the milestones in 09_FUNDING_STRATEGY.md)
A23: Round | B23: Month | C23: Date | D23: Amount (GBP) | E23: Cumulative cash before this round (model)
A24: Pre-seed (SEIS/EIS) | B24: =Assumptions!$F$122 | C24: =IF(Assumptions!$F$122<=36,TEXT(DATE(2027,Assumptions!$F$122,1),"mmm yyyy"),"not in model") | D24: =Assumptions!$F$121 | E24: =IF(Assumptions!$F$122<=36,INDEX('Cash flow'!$C$27:$AL$27,1,Assumptions!$F$122),"—")
A25: Seed | B25: =Assumptions!$F$124 | C25: =IF(Assumptions!$F$124<=36,TEXT(DATE(2027,Assumptions!$F$124,1),"mmm yyyy"),"not in model") | D25: =Assumptions!$F$123 | E25: =IF(Assumptions!$F$124<=36,INDEX('Cash flow'!$C$27:$AL$27,1,Assumptions!$F$124),"—")
A26: Series A | B26: =Assumptions!$F$126 | C26: =IF(Assumptions!$F$126<=36,TEXT(DATE(2027,Assumptions!$F$126,1),"mmm yyyy"),"not in model") | D26: =Assumptions!$F$125 | E26: =IF(Assumptions!$F$126<=36,INDEX('Cash flow'!$C$27:$AL$27,1,Assumptions!$F$126),"—")
A27: Grant 1 | B27: =Assumptions!$F$128 | C27: =IF(Assumptions!$F$128<=36,TEXT(DATE(2027,Assumptions!$F$128,1),"mmm yyyy"),"not in model") | D27: =Assumptions!$F$127 | E27: =IF(Assumptions!$F$128<=36,INDEX('Cash flow'!$C$27:$AL$27,1,Assumptions!$F$128),"—")
A28: Grant 2 | B28: =Assumptions!$F$130 | C28: =IF(Assumptions!$F$130<=36,TEXT(DATE(2027,Assumptions!$F$130,1),"mmm yyyy"),"not in model") | D28: =Assumptions!$F$129 | E28: =IF(Assumptions!$F$130<=36,INDEX('Cash flow'!$C$27:$AL$27,1,Assumptions!$F$130),"—")
A30: Reading this sheet
A31: • Peak cash need is the external money required to keep cash ≥ 0 with no equity or grants — the number to raise (plus a buffer of 20–30%).
A32: • Break-even = first month EBITDA > 0 (before grant income) — this can be a pre-salary blip in months 2–4; use the SUSTAINED figure (row 20) as the real break-even. Cumulative break-even is when losses to date are recovered.
A33: • If the funded-through check shows SHORTFALL, the scenario's rounds are too small or too late for its cost base.
A34: • Grants are recognised when received; they are competitive and none is secured (TO VALIDATE).

Sheet Dashboard
A1: Dashboard — active scenario
A2: ="Scenario: "&Assumptions!$D$4&" (change Assumptions!C4). Scenario values, not actuals."
A4: Metric | B4: FY2027 | C4: FY2028 | D4: FY2029 | E4: 3-year
A5: Advisory revenue | B5: ='P&L'!AN8 | C5: ='P&L'!AO8 | D5: ='P&L'!AP8 | E5: ='P&L'!AQ8
A6: Consulting revenue | B6: ='P&L'!AN9 | C6: ='P&L'!AO9 | D6: ='P&L'!AP9 | E6: ='P&L'!AQ9
A7: E-learning revenue | B7: ='P&L'!AN10 | C7: ='P&L'!AO10 | D7: ='P&L'!AP10 | E7: ='P&L'!AQ10
A8: MaternaLink revenue (in development) | B8: ='P&L'!AN11 | C8: ='P&L'!AO11 | D8: ='P&L'!AP11 | E8: ='P&L'!AQ11
A9: TOTAL REVENUE | B9: ='P&L'!AN12 | C9: ='P&L'!AO12 | D9: ='P&L'!AP12 | E9: ='P&L'!AQ12
A10: Gross profit | B10: ='P&L'!AN14 | C10: ='P&L'!AO14 | D10: ='P&L'!AP14 | E10: ='P&L'!AQ14
A11: Gross margin % | B11: ='P&L'!AN15 | C11: ='P&L'!AO15 | D11: ='P&L'!AP15 | E11: ='P&L'!AQ15
A12: Total operating expenses | B12: ='P&L'!AN30 | C12: ='P&L'!AO30 | D12: ='P&L'!AP30 | E12: ='P&L'!AQ30
A13: EBITDA (before grants) | B13: ='P&L'!AN32 | C13: ='P&L'!AO32 | D13: ='P&L'!AP32 | E13: ='P&L'!AQ32
A14: Grant income | B14: ='P&L'!AN35 | C14: ='P&L'!AO35 | D14: ='P&L'!AP35 | E14: ='P&L'!AQ35
A15: Net result | B15: ='P&L'!AN36 | C15: ='P&L'!AO36 | D15: ='P&L'!AP36 | E15: ='P&L'!AQ36
A16: Net operating cash flow | B16: ='Cash flow'!AN15 | C16: ='Cash flow'!AO15 | D16: ='Cash flow'!AP15 | E16: ='Cash flow'!AQ15
A17: Funding received (equity + grants) | B17: ='Cash flow'!AN22 | C17: ='Cash flow'!AO22 | D17: ='Cash flow'!AP22 | E17: ='Cash flow'!AQ22
A18: Closing cash (year end) | B18: ='Cash flow'!AN25 | C18: ='Cash flow'!AO25 | D18: ='Cash flow'!AP25 | E18: ='Cash flow'!AQ25
A19: Headcount (year end) | B19: ='Headcount'!AN18 | C19: ='Headcount'!AO18 | D19: ='Headcount'!AP18 | E19: ='Headcount'!AQ18
A21: Funding metrics
A22: Peak cash need before external funding | B22: ='Funding requirement'!B4
A23: Month of peak cash need | B23: ='Funding requirement'!B5
A24: First month with positive EBITDA | B24: ='Funding requirement'!B7
A25: First month of sustained positive EBITDA | B25: ='Funding requirement'!B20
A26: Minimum closing cash after funding | B26: ='Funding requirement'!B10
A27: Funded-through check | B27: ='Funding requirement'!B12
A28: Runway at month 36 (months) | B28: ='Funding requirement'!B14

Sheet Sensitivity
A1: Sensitivity — Python-computed (static). Re-run build_model.py after changing assumptions.
A2: Each table flexes one or two inputs around the named scenario with everything else unchanged.
A4: Table 1 — Base scenario: 3-year TOTAL REVENUE (GBP) by founder day rate × utilisation
B5: Utilisation 30% | C5: Utilisation 42% | D5: Utilisation 55%
A6: Day rate £1,200 | B6: 1448541 | C6: 1469140 | D6: 1495273
A7: Day rate £1,500 | B7: 1448541 | C7: 1474289 | D7: 1506956
A8: Day rate £1,800 | B8: 1448541 | C8: 1479439 | D8: 1518639
A10: Table 2 — Base scenario: PEAK CASH NEED before external funding (GBP) by day rate × utilisation
B11: Utilisation 30% | C11: Utilisation 42% | D11: Utilisation 55%
A12: Day rate £1,200 | B12: 1082925 | C12: 1063184 | D12: 1038140
A13: Day rate £1,500 | B13: 1082925 | C13: 1058035 | D13: 1026457
A14: Day rate £1,800 | B14: 1082925 | C14: 1052885 | D14: 1014774
A16: Table 3 — Base scenario: 3-year EBITDA (GBP) by day rate × utilisation
B17: Utilisation 30% | C17: Utilisation 42% | D17: Utilisation 55%
A18: Day rate £1,200 | B18: -1057091 | C18: -1037351 | D18: -1012306
A19: Day rate £1,500 | B19: -1057091 | C19: -1032201 | D19: -1000623
A20: Day rate £1,800 | B20: -1057091 | C20: -1027052 | D20: -988940
A22: Table — Base scenario: MaternaLink licence go-live delay
A23: Delay | B23: MaternaLink 3-yr revenue | C23: Total 3-yr revenue | D23: 3-yr EBITDA | E23: Peak cash need | F23: First EBITDA-positive month | G23: Closing cash M36
A24: Go-live delay 0 months (go-live month 19) | B24: 387000 | C24: 1474289 | D24: -1032201 | E24: 1058035 | F24: 4 | G24: 1416965
A25: Go-live delay 3 months (go-live month 22) | B25: 345000 | C25: 1432289 | D25: -1058976 | E25: 1082810 | F25: 4 | G25: 1392190
A26: Go-live delay 6 months (go-live month 25) | B26: 309000 | C26: 1396289 | D26: -1081926 | E26: 1103760 | F26: 4 | G26: 1371240
A27: Go-live delay 12 months (go-live month 31) | B27: 255000 | C27: 1342289 | D27: -1116351 | E27: 1134185 | F27: 4 | G27: 1340815
A29: Table — High-growth scenario: MaternaLink licence go-live delay
A30: Delay | B30: MaternaLink 3-yr revenue | C30: Total 3-yr revenue | D30: 3-yr EBITDA | E30: Peak cash need | F30: First EBITDA-positive month | G30: Closing cash M36
A31: Go-live delay 0 months (go-live month 15) | B31: 2301500 | C31: 5249714 | D31: 113985 | E31: 144705 | F31: 2 | G31: 3839985
A32: Go-live delay 3 months (go-live month 18) | B32: 2001500 | C32: 4949714 | D32: -122265 | E32: 326751 | F32: 2 | G32: 3615735
A33: Go-live delay 6 months (go-live month 21) | B33: 1737500 | C33: 4685714 | D33: -330165 | E33: 495471 | F33: 2 | G33: 3419835
A34: Go-live delay 12 months (go-live month 27) | B34: 1317500 | C34: 4265714 | D34: -660915 | E34: 786915 | F34: 2 | G34: 3113085
A36: Table — Conservative scenario: MaternaLink licence go-live delay
A37: Delay | B37: MaternaLink 3-yr revenue | C37: Total 3-yr revenue | D37: 3-yr EBITDA | E37: Peak cash need | F37: First EBITDA-positive month | G37: Closing cash M36
A38: Go-live delay 0 months (go-live month 27) | B38: 71479 | C38: 412514 | D38: -239543 | E38: 228872 | F38: 3 | G38: 21128
A39: Go-live delay 3 months (go-live month 30) | B39: 68029 | C39: 409064 | D39: -240893 | E39: 229935 | F39: 3 | G39: 20065
A40: Go-live delay 6 months (go-live month 33) | B40: 65442 | C40: 406477 | D40: -241906 | E40: 230660 | F40: 3 | G40: 19340
A41: Go-live delay 12 months (go-live month 39) | B41: 63333 | C41: 404369 | D41: -242731 | E41: 230814 | F41: 3 | G41: 19186
A43: Table — Base scenario one-at-a-time flex (Base 3-yr revenue £1,474,289; 3-yr EBITDA £-1,032,201; peak need £1,058,035)
A44: Input | B44: Low | C44: High | D44: Δ Revenue (low) | E44: Δ Revenue (high) | F44: Δ EBITDA (low) | G44: Δ EBITDA (high) | H44: Δ Peak need (low) | I44: Δ Peak need (high)
A45: Founder day rate | B45: 1200 | C45: 1800 | D45: -5150 | E45: 5150 | F45: -5150 | G45: 5150 | H45: 5150 | I45: -5150
A46: Founder utilisation | B46: 0.3 | C46: 0.55 | D46: -25748 | E46: 32667 | F46: -24890 | G46: 31578 | H46: 24890 | I46: -31578
A47: Average consulting project value | B47: 15000 | C47: 30000 | D47: -110833 | E47: 221667 | F47: -72042 | G47: 144083 | H47: 67875 | I47: -135750
A48: E-learning ARPU | B48: 150 | C48: 300 | D48: -43802 | E48: 87604 | F48: -37232 | G48: 74463 | H48: 37232 | I48: -74463
A49: MaternaLink pilot value per year | B49: 40000 | C49: 150000 | D49: -105000 | E49: 225000 | F49: -57750 | G49: 123750 | H49: 51917 | I49: -111250
A50: Africa licence £/woman/yr | B50: 3 | C50: 12 | D50: -60750 | E50: 121500 | F50: -60750 | G50: 121500 | H50: 55250 | I50: -110500
A51: UK licence £/woman/yr | B51: 8 | C51: 40 | D51: -24300 | E51: 40500 | F51: -24300 | G51: 40500 | H51: 22100 | I51: -36833
A52: Africa women added per month | B52: 250 | C52: 3000 | D52: -57375 | E52: 153000 | F52: -33469 | G52: 89250 | H52: 27094 | I52: -72250
A53: Retainers Y2/Y3 | B53: 1 | C53: 3 | D53: -93985 | E53: 96000 | F53: -91052 | G53: 93000 | H53: 87052 | I53: -89000

Sheet Static summary
A1: Static summary — Python-computed values for all three scenarios (visible without recalculation)
A2: Same logic as the formula sheets (build_model.py, function compute). If a recalculated workbook differs from this sheet, the formulas have been edited.
A4: Conservative scenario — annual P&L and cash
A5: Line | B5: FY2027 | C5: FY2028 | D5: FY2029 | E5: 3-year
A6: Advisory | B6: 46568.6 | C6: 42465.6 | D6: 42000 | E6: 131034.2
A7: Consulting | B7: 23750 | C7: 60000 | D7: 75000 | E7: 158750
A8: E-learning | B8: 1200 | C8: 20041.35 | D8: 30009.77 | E8: 51251.12
A9: MaternaLink (in development) | B9: 0 | C9: 23333.33 | D9: 48145.83 | E9: 71479.17
A10: TOTAL REVENUE | B10: 71518.6 | C10: 145840.28 | D10: 195155.6 | E10: 412514.48
A11: Cost of sales | B11: 9141.19 | C11: 34192.27 | D11: 53459.8 | E11: 96793.26
A12: Gross profit | B12: 62377.41 | C12: 111648.01 | D12: 141695.8 | E12: 315721.22
A13: Employment cost | B13: 31157.1 | C13: 100613.7 | D13: 100613.7 | E13: 232384.5
A14: Total operating expenses | B14: 84037.1 | C14: 188813.7 | D14: 282413.7 | E14: 555264.5
A15: EBITDA (before grants) | B15: -21659.69 | C15: -77165.69 | D15: -140717.9 | E15: -239543.28
A16: Grant income | B16: 0 | C16: 0 | D16: 0 | E16: 0
A17: Net result | B17: -21659.69 | C17: -77165.69 | D17: -140717.9 | E17: -239543.28
... A21: Gross margin % | B21: 0.87218442 | C21: 0.7655499 | D21: 0.72606577 | E21: 0.76535791
A22: Peak cash need before external funding | B22: 228872.44
A23: Month of peak cash need | B23: 36
A24: First month with positive EBITDA (may be a blip) | B24: 3
A25: First month of SUSTAINED positive EBITDA (break-even) | B25: Not reached in 36 months
A26: First month cumulative result positive | B26: Not reached in 36 months
A27: Minimum closing cash after funding | B27: 4726.19
A28: Month of minimum closing cash | B28: 5
A29: Closing cash month 36 | B29: 21127.56
A30: Equity raised in model | B30: 250000
A31: Grants in model | B31: 0
A32: Runway at month 36 (months) | B32: 1.85
A34: Base scenario — annual P&L and cash
A35: Line | B35: FY2027 | C35: FY2028 | D35: FY2029 | E35: 3-year
A36: Advisory | B36: 69748.03 | C36: 150000 | D36: 204000 | E36: 423748.03
A37: Consulting | B37: 83333.33 | C37: 160000 | D37: 200000 | E37: 443333.33
A38: E-learning | B38: 12930.38 | C38: 73042.1 | D38: 134235.27 | E38: 220207.75
A39: MaternaLink (in development) | B39: 0 | C39: 105000 | D39: 282000 | E39: 387000
A40: TOTAL REVENUE | B40: 166011.74 | C40: 488042.1 | D40: 820235.27 | E40: 1474289.1
A41: Cost of sales | B41: 33339.49 | C41: 114581.32 | D41: 208485.29 | E41: 356406.1
A42: Gross profit | B42: 132672.25 | C42: 373460.79 | D42: 611749.98 | E42: 1117883
A43: Employment cost | B43: 94784.68 | C43: 290116.87 | D43: 485582.9 | E43: 870484.45
A44: Total operating expenses | B44: 188184.67 | C44: 563116.88 | D44: 1398782.9 | E44: 2150084.5
A45: EBITDA (before grants) | B45: -55512.42 | C45: -189656.09 | D45: -787032.92 | E45: -1032201.4
A46: Grant income | B46: 0 | C46: 75000 | D46: 0 | E46: 75000
A47: Net result | B47: -55512.42 | C47: -114656.09 | D47: -787032.92 | E47: -957201.43
... A51: Gross margin % | B51: 0.7991739 | C51: 0.76522248 | D51: 0.74582257 | E51: 0.75825224
A52: Peak cash need before external funding | B52: 1058034.8
A53: Month of peak cash need | B53: 36
A54: First month with positive EBITDA (may be a blip) | B54: 4
A55: First month of SUSTAINED positive EBITDA (break-even) | B55: Not reached in 36 months
A56: First month cumulative result positive | B56: Not reached in 36 months
A57: Minimum closing cash after funding | B57: 6098.81
A58: Month of minimum closing cash | B58: 3
A59: Closing cash month 36 | B59: 1416965.2
A60: Equity raised in model | B60: 2400000
A61: Grants in model | B61: 75000
A62: Runway at month 36 (months) | B62: 22.62
A64: High-growth scenario — annual P&L and cash
A65: Line | B65: FY2027 | C65: FY2028 | D65: FY2029 | E65: 3-year
A66: Advisory | B66: 161567 | C66: 300000 | D66: 300000 | E66: 761567
A67: Consulting | B67: 210000 | C67: 420000 | D67: 540000 | E67: 1170000
A68: E-learning | B68: 68879.62 | C68: 295611.68 | D68: 652155.78 | E68: 1016647.1
A69: MaternaLink (in development) | B69: 37500 | C69: 680000 | D69: 1584000 | E69: 2301500
A70: TOTAL REVENUE | B70: 477946.62 | C70: 1695611.7 | D70: 3076155.8 | E70: 5249714.1
A71: Cost of sales | B71: 123181.03 | C71: 438591.75 | D71: 794423.37 | E71: 1356196.1
A72: Gross profit | B72: 354765.59 | C72: 1257019.9 | D72: 2281732.4 | E72: 3893517.9
A73: Employment cost | B73: 190632.47 | C73: 545607.85 | D73: 655692.8 | E73: 1391933.1
A74: Total operating expenses | B74: 330632.47 | C74: 1175607.9 | D74: 2273292.8 | E74: 3779533.1
A75: EBITDA (before grants) | B75: 24133.12 | C75: 81412.07 | D75: 8439.62 | E75: 113984.81
A76: Grant income | B76: 150000 | C76: 250000 | D76: 0 | E76: 400000
A77: Net result | B77: 174133.12 | C77: 331412.07 | D77: 8439.62 | E77: 513984.81
... A81: Gross margin % | B81: 0.74227033 | C81: 0.74133715 | D81: 0.74174801 | E81: 0.74166286
A82: Peak cash need before external funding | B82: 144704.74
A83: Month of peak cash need | B83: 31
A84: First month with positive EBITDA (may be a blip) | B84: 2
A85: First month of SUSTAINED positive EBITDA (break-even) | B85: 31
A86: First month cumulative result positive | B86: 9
A87: Minimum closing cash after funding | B87: 12750
A88: Month of minimum closing cash | B88: 2
A89: Closing cash month 36 | B89: 3839984.8
A90: Equity raised in model | B90: 3500000
A91: Grants in model | B91: 400000
A92: Runway at month 36 (months) | B92: cash-generative
